Workbook
Name Slicer_CourseName: #N/A
Name Slicer_MentorName: #N/A
Name Slicer_Platform: #N/A

Sheet Dataset
A1: StudentID | B1: StudentName | C1: CourseID | D1: CourseName | E1: BatchID | F1: MentorName | G1: Platform | H1: PaymentAmount | I1: DiscountCode | J1: DiscountPercent | K1: TargetRevenue | L1: PaymentDate
A2: S1000 | B2: Rohit Shah | C2: C201 | D2: Data Analytics | E2: B3 | F2: Priya | G2: Web | H2: 12914 | I2: DISC20 | J2: 0.2 | K2: 14000 | L2: 45339
A3: S1001 | B3: Riya Singh | C3: C201 | D3: Data Analytics | E3: B3 | F3: Priya | G3: Web | H3: 12122 | I3: DISC10 | J3: 0.1 | K3: 14000 | L3: 45305
A4: S1002 | B4: Sneha Gupta | C4: C201 | D4: Data Analytics | E4: B3 | F4: Saurabh | G4: Tablet | H4: 14661 | I4: DISC15 | K4: 14000 | L4: 45318
A5: S1003 | B5: Sneha Iyer | C5: C203 | D5: Full Stack Dev | E5: B1 | F5: Saurabh | G5: Tablet | H5: 16731 | I5: DISC30 | J5: 0.3 | K5: 17000 | L5: 45309
A6: S1004 | B6: Karan Patil | C6: C203 | D6: Full Stack Dev | E6: B1 | F6: Saurabh | G6: Mobile | H6: 15396 | I6: DISC30 | J6: 0.3 | K6: 17000 | L6: 45346
A7: S1005 | B7: Pooja Joshi | C7: C203 | D7: Full Stack Dev | E7: B1 | F7: Amit | G7: Mobile | H7: 17196 | I7: DISC10 | J7: 0.1 | K7: 17000 | L7: 45351
A8: S1006 | B8: Rahul Shah | C8: C203 | D8: Full Stack Dev | E8: B3 | F8: Amit | G8: Mobile | H8: 17364 | I8: DISC20 | J8: 0.2 | K8: 17000 | L8: 45337
A9: S1007 | B9: Riya Kulkarni | C9: C202 | D9: Data Science | E9: B2 | F9: Saurabh | G9: Web | H9: 14549 | I9: DISC10 | J9: 0.1 | K9: 13000 | L9: 45316
A10: S1008 | B10: Aditya Iyer | C10: C203 | D10: Full Stack Dev | E10: B1 | F10: Priya | G10: Mobile | H10: 15858 | I10: DISC30 | J10: 0.3 | K10: 17000 | L10: 45336
A11: S1009 | B11: Kunal Singh | C11: C201 | D11: Data Analytics | E11: B3 | F11: Amit | G11: Web | H11: 14187 | I11: DISC20 | J11: 0.2 | K11: 14000 | L11: 45302
A12: S1010 | B12: Neha Verma | C12: C203 | D12: Full Stack Dev | E12: B3 | F12: Amit | G12: Tablet | H12: 15899 | I12: DISC30 | J12: 0.3 | K12: 17000 | L12: 45345
A13: S1011 | B13: Dev Patel | C13: C201 | D13: Data Analytics | E13: B1 | F13: Saurabh | G13: Mobile | H13: 13643 | I13: DISC30 | J13: 0.3 | K13: 14000 | L13: 45296
A14: S1012 | B14: Sneha Joshi | C14: C203 | D14: Full Stack Dev | E14: B1 | F14: Amit | G14: Mobile | H14: 16620 | K14: 17000 | L14: 45301
A15: S1013 | B15: Aditya Mehta | C15: C202 | D15: Data Science | E15: B3 | F15: Amit | G15: Tablet | H15: 12076 | I15: DISC15 | K15: 13000 | L15: 45319
A16: S1014 | B16: Kunal Joshi | C16: C204 | D16: UI UX Design | E16: B2 | F16: Saurabh | G16: Web | H16: 9087 | K16: 9000 | L16: 45297
A17: S1015 | B17: Dev Kulkarni | C17: C201 | D17: Data Analytics | E17: B1 | F17: Amit | G17: Web | H17: 15244 | K17: 14000 | L17: 45330
A18: S1016 | B18: Riya Verma | C18: C204 | D18: UI UX Design | E18: B3 | F18: Priya | G18: Tablet | H18: 8029 | I18: DISC15 | K18: 9000 | L18: 45347
A19: S1017 | B19: Aarav Singh | C19: C201 | D19: Data Analytics | E19: B3 | F19: Amit | G19: Mobile | H19: 15148 | I19: DISC30 | J19: 0.3 | K19: 14000 | L19: 45299
A20: S1018 | B20: Aditya Verma | C20: C202 | D20: Data Science | E20: B2 | F20: Saurabh | G20: Tablet | H20: 14587 | I20: DISC30 | J20: 0.3 | K20: 13000 | L20: 45324
A21: S1019 | B21: Dev Mehta | C21: C201 | D21: Data Analytics | E21: B3 | F21: Priya | G21: Tablet | H21: 14079 | I21: DISC15 | K21: 14000 | L21: 45304
A22: S1020 | B22: Karan Jain | C22: C202 | D22: Data Science | E22: B3 | F22: Amit | G22: Web | H22: 13453 | I22: DISC30 | J22: 0.3 | K22: 13000 | L22: 45323
A23: S1021 | B23: Aarav Shah | C23: C203 | D23: Full Stack Dev | E23: B2 | F23: Saurabh | G23: Web | H23: 15986 | I23: DISC15 | K23: 17000 | L23: 45352
A24: S1022 | B24: Riya Shah | C24: C204 | D24: UI UX Design | E24: B1 | F24: Amit | G24: Web | H24: 7525 | K24: 9000 | L24: 45352
A25: S1023 | B25: Manish Mehta | C25: C203 | D25: Full Stack Dev | E25: B3 | F25: Amit | G25: Mobile | H25: 18950 | I25: DISC20 | J25: 0.2 | K25: 17000 | L25: 45351
A26: S1024 | B26: Manish Patel | C26: C202 | D26: Data Science | E26: B3 | F26: Priya | G26: Mobile | H26: 13751 | I26: DISC30 | J26: 0.3 | K26: 13000 | L26: 45320
A27: S1025 | B27: Kunal Gupta | C27: C204 | D27: UI UX Design | E27: B1 | F27: Saurabh | G27: Web | H27: 7262 | I27: DISC30 | J27: 0.3 | K27: 9000 | L27: 45293
A28: S1026 | B28: Kavita Gupta | C28: C202 | D28: Data Science | E28: B3 | F28: Saurabh | G28: Web | H28: 11290 | I28: DISC10 | J28: 0.1 | K28: 13000 | L28: 45306
A29: S1027 | B29: Riya Kulkarni | C29: C203 | D29: Full Stack Dev | E29: B1 | F29: Amit | G29: Web | H29: 16140 | K29: 17000 | L29: 45305
A30: S1028 | B30: Manish Mehta | C30: C204 | D30: UI UX Design | E30: B1 | F30: Priya | G30: Mobile | H30: 7779 | I30: DISC10 | J30: 0.1 | K30: 9000 | L30: 45298
A31: S1029 | B31: Rohit Verma | C31: C203 | D31: Full Stack Dev | E31: B2 | F31: Priya | G31: Mobile | H31: 18538 | I31: DISC10 | J31: 0.1 | K31: 17000 | L31: 45335
A32: S1030 | B32: Rohit Singh | C32: C201 | D32: Data Analytics | E32: B1 | F32: Priya | G32: Tablet | H32: 13389 | I32: DISC10 | J32: 0.1 | K32: 14000 | L32: 45307
A33: S1031 | B33: Sneha Patil | C33: C204 | D33: UI UX Design | E33: B1 | F33: Priya | G33: Web | H33: 8140 | K33: 9000 | L33: 45307
A34: S1032 | B34: Meera Shah | C34: C204 | D34: UI UX Design | E34: B3 | F34: Saurabh | G34: Web | H34: 9671 | I34: DISC15 | K34: 9000 | L34: 45345
A35: S1033 | B35: Aarav Shah | C35: C202 | D35: Data Science | E35: B1 | F35: Priya | G35: Mobile | H35: 12971 | I35: DISC20 | J35: 0.2 | K35: 13000 | L35: 45347
A36: S1034 | B36: Rahul Kulkarni | C36: C202 | D36: Data Science | E36: B2 | F36: Saurabh | G36: Mobile | H36: 12086 | K36: 13000 | L36: 45310
A37: S1035 | B37: Rahul Desai | C37: C204 | D37: UI UX Design | E37: B1 | F37: Saurabh | G37: Mobile | H37: 7891 | I37: DISC10 | J37: 0.1 | K37: 9000 | L37: 45329
A38: S1036 | B38: Anjali Gupta | C38: C201 | D38: Data Analytics | E38: B3 | F38: Priya | G38: Web | H38: 12205 | I38: DISC15 | K38: 14000 | L38: 45322
A39: S1037 | B39: Manish Nair | C39: C202 | D39: Data Science | E39: B1 | F39: Amit | G39: Web | H39: 14487 | I39: DISC20 | J39: 0.2 | K39: 13000 | L39: 45296
A40: S1038 | B40: Kavita Shah | C40: C202 | D40: Data Science | E40: B2 | F40: Saurabh | G40: Tablet | H40: 12008 | I40: DISC15 | K40: 13000 | L40: 45330
A41: S1039 | B41: Aarav Joshi | C41: C201 | D41: Data Analytics | E41: B2 | F41: Amit | G41: Tablet | H41: 14315 | I41: DISC15 | K41: 14000 | L41: 45312
A42: S1040 | B42: Kunal Rao | C42: C202 | D42: Data Science | E42: B3 | F42: Amit | G42: Mobile | H42: 11977 | I42: DISC30 | J42: 0.3 | K42: 13000 | L42: 45317
A43: S1041 | B43: Karan Singh | C43: C203 | D43: Full Stack Dev | E43: B2 | F43: Priya | G43: Web | H43: 15038 | K43: 17000 | L43: 45331
A44: S1042 | B44: Kavita Shah | C44: C201 | D44: Data Analytics | E44: B3 | F44: Saurabh | G44: Tablet | H44: 13086 | I44: DISC20 | J44: 0.2 | K44: 14000 | L44: 45351
A45: S1043 | B45: Pooja Shah | C45: C202 | D45: Data Science | E45: B2 | F45: Priya | G45: Web | H45: 12794 | I45: DISC15 | K45: 13000 | L45: 45337
A46: S1044 | B46: Aditya Joshi | C46: C201 | D46: Data Analytics | E46: B3 | F46: Amit | G46: Mobile | H46: 15816 | I46: DISC10 | J46: 0.1 | K46: 14000 | L46: 45352
A47: S1045 | B47: Kunal Mehta | C47: C203 | D47: Full Stack Dev | E47: B1 | F47: Saurabh | G47: Tablet | H47: 17266 | I47: DISC20 | J47: 0.2 | K47: 17000 | L47: 45309
A48: S1046 | B48: Aditya Joshi | C48: C202 | D48: Data Science | E48: B3 | F48: Priya | G48: Web | H48: 13815 | I48: DISC30 | J48: 0.3 | K48: 13000 | L48: 45324
A49: S1047 | B49: Neha Rao | C49: C201 | D49: Data Analytics | E49: B1 | F49: Amit | G49: Mobile | H49: 15397 | I49: DISC30 | J49: 0.3 | K49: 14000 | L49: 45294
A50: S1048 | B50: Aarav Jain | C50: C202 | D50: Data Science | E50: B3 | F50: Priya | G50: Web | H50: 14036 | K50: 13000 | L50: 45327
A51: S1049 | B51: Anjali Verma | C51: C201 | D51: Data Analytics | E51: B1 | F51: Saurabh | G51: Tablet | H51: 15702 | I51: DISC20 | J51: 0.2 | K51: 14000 | L51: 45326
A52: S1050 | B52: Aarav Nair | C52: C203 | D52: Full Stack Dev | E52: B3 | F52: Amit | G52: Web | H52: 16760 | I52: DISC20 | J52: 0.2 | K52: 17000 | L52: 45294
A53: S1051 | B53: Aditya Jain | C53: C201 | D53: Data Analytics | E53: B2 | F53: Saurabh | G53: Tablet | H53: 13022 | I53: DISC10 | J53: 0.1 | K53: 14000 | L53: 45314
A54: S1052 | B54: Dev Gupta | C54: C204 | D54: UI UX Design | E54: B3 | F54: Amit | G54: Web | H54: 10791 | I54: DISC20 | J54: 0.2 | K54: 9000 | L54: 45347
A55: S1053 | B55: Karan Patel | C55: C202 | D55: Data Science | E55: B2 | F55: Saurabh | G55: Web | H55: 14016 | I55: DISC30 | J55: 0.3 | K55: 13000 | L55: 45342
A56: S1054 | B56: Kunal Verma | C56: C202 | D56: Data Science | E56: B2 | F56: Saurabh | G56: Tablet | H56: 11442 | K56: 13000 | L56: 45347
A57: S1055 | B57: Aarav Nair | C57: C204 | D57: UI UX Design | E57: B1 | F57: Saurabh | G57: Mobile | H57: 8432 | I57: DISC30 | J57: 0.3 | K57: 9000 | L57: 45344
A58: S1056 | B58: Dev Nair | C58: C202 | D58: Data Science | E58: B1 | F58: Saurabh | G58: Tablet | H58: 11791 | K58: 13000 | L58: 45313
A59: S1057 | B59: Aditya Nair | C59: C201 | D59: Data Analytics | E59: B2 | F59: Priya | G59: Tablet | H59: 14086 | K59: 14000 | L59: 45335
A60: S1058 | B60: Meera Gupta | C60: C203 | D60: Full Stack Dev | E60: B1 | F60: Saurabh | G60: Mobile | H60: 15731 | I60: DISC15 | K60: 17000 | L60: 45308
A61: S1059 | B61: Aarav Shah | C61: C204 | D61: UI UX Design | E61: B2 | F61: Amit | G61: Mobile | H61: 8787 | I61: DISC15 | K61: 9000 | L61: 45324
A62: S1060 | B62: Riya Verma | C62: C202 | D62: Data Science | E62: B2 | F62: Saurabh | G62: Tablet | H62: 12786 | I62: DISC10 | J62: 0.1 | K62: 13000 | L62: 45325
A63: S1061 | B63: Kunal Patel | C63: C202 | D63: Data Science | E63: B2 | F63: Priya | G63: Web | H63: 14886 | I63: DISC30 | J63: 0.3 | K63: 13000 | L63: 45331
A64: S1062 | B64: Pooja Singh | C64: C201 | D64: Data Analytics | E64: B3 | F64: Priya | G64: Tablet | H64: 13266 | K64: 14000 | L64: 45312
A65: S1063 | B65: Rahul Desai | C65: C203 | D65: Full Stack Dev | E65: B3 | F65: Saurabh | G65: Web | H65: 16722 | K65: 17000 | L65: 45335
A66: S1064 | B66: Anjali Mehta | C66: C203 | D66: Full Stack Dev | E66: B2 | F66: Amit | G66: Web | H66: 16244 | I66: DISC30 | J66: 0.3 | K66: 17000 | L66: 45305
A67: S1065 | B67: Rahul Patel | C67: C203 | D67: Full Stack Dev | E67: B2 | F67: Priya | G67: Mobile | H67: 17767 | I67: DISC20 | J67: 0.2 | K67: 17000 | L67: 45324
A68: S1066 | B68: Neha Patel | C68: C202 | D68: Data Science | E68: B3 | F68: Saurabh | G68: Mobile | H68: 13111 | I68: DISC15 | K68: 13000 | L68: 45313
A69: S1067 | B69: Riya Nair | C69: C202 | D69: Data Science | E69: B3 | F69: Priya | G69: Web | H69: 14303 | I69: DISC20 | J69: 0.2 | K69: 13000 | L69: 45301
A70: S1068 | B70: Aarav Kulkarni | C70: C202 | D70: Data Science | E70: B2 | F70: Amit | G70: Web | H70: 12865 | K70: 13000 | L70: 45348
A71: S1069 | B71: Rohit Joshi | C71: C202 | D71: Data Science | E71: B3 | F71: Amit | G71: Mobile | H71: 13024 | K71: 13000 | L71: 45307
A72: S1070 | B72: Karan Singh | C72: C201 | D72: Data Analytics | E72: B1 | F72: Priya | G72: Web | H72: 12720 | I72: DISC15 | K72: 14000 | L72: 45321
A73: S1071 | B73: Aarav Gupta | C73: C202 | D73: Data Science | E73: B1 | F73: Priya | G73: Web | H73: 14282 | K73: 13000 | L73: 45334
A74: S1072 | B74: Manish Gupta | C74: C203 | D74: Full Stack Dev | E74: B2 | F74: Amit | G74: Tablet | H74: 18653 | I74: DISC15 | K74: 17000 | L74: 45319
A75: S1073 | B75: Meera Gupta | C75: C204 | D75: UI UX Design | E75: B1 | F75: Amit | G75: Mobile | H75: 8843 | I75: DISC30 | J75: 0.3 | K75: 9000 | L75: 45340
A76: S1074 | B76: Sneha Nair | C76: C203 | D76: Full Stack Dev | E76: B3 | F76: Priya | G76: Tablet | H76: 15979 | I76: DISC30 | J76: 0.3 | K76: 17000 | L76: 45320
A77: S1075 | B77: Riya Desai | C77: C203 | D77: Full Stack Dev | E77: B1 | F77: Priya | G77: Mobile | H77: 16309 | I77: DISC15 | K77: 17000 | L77: 45297
A78: S1076 | B78: Karan Mehta | C78: C202 | D78: Data Science | E78: B2 | F78: Amit | G78: Web | H78: 13893 | I78: DISC20 | J78: 0.2 | K78: 13000 | L78: 45296
A79: S1077 | B79: Rahul Verma | C79: C203 | D79: Full Stack Dev | E79: B3 | F79: Priya | G79: Mobile | H79: 15255 | I79: DISC20 | J79: 0.2 | K79: 17000 | L79: 45345
A80: S1078 | B80: Rahul Verma | C80: C201 | D80: Data Analytics | E80: B3 | F80: Priya | G80: Mobile | H80: 12024 | I80: DISC30 | J80: 0.3 | K80: 14000 | L80: 45311
A81: S1079 | B81: Dev Verma | C81: C204 | D81: UI UX Design | E81: B3 | F81: Amit | G81: Tablet | H81: 9236 | I81: DISC15 | K81: 9000 | L81: 45349
A82: S1080 | B82: Sneha Iyer | C82: C202 | D82: Data Science | E82: B2 | F82: Priya | G82: Mobile | H82: 11118 | K82: 13000 | L82: 45313
A83: S1081 | B83: Rohit Singh | C83: C204 | D83: UI UX Design | E83: B3 | F83: Saurabh | G83: Mobile | H83: 10766 | I83: DISC20 | J83: 0.2 | K83: 9000 | L83: 45331
A84: S1082 | B84: Manish Kulkarni | C84: C204 | D84: UI UX Design | E84: B3 | F84: Amit | G84: Tablet | H84: 7111 | I84: DISC10 | J84: 0.1 | K84: 9000 | L84: 45333
A85: S1083 | B85: Rahul Mehta | C85: C204 | D85: UI UX Design | E85: B1 | F85: Saurabh | G85: Mobile | H85: 8552 | I85: DISC30 | J85: 0.3 | K85: 9000 | L85: 45305
A86: S1084 | B86: Neha Jain | C86: C203 | D86: Full Stack Dev | E86: B2 | F86: Priya | G86: Mobile | H86: 16033 | I86: DISC10 | J86: 0.1 | K86: 17000 | L86: 45322
A87: S1085 | B87: Aarav Desai | C87: C201 | D87: Data Analytics | E87: B2 | F87: Saurabh | G87: Tablet | H87: 12281 | I87: DISC10 | J87: 0.1 | K87: 14000 | L87: 45340
A88: S1086 | B88: Aarav Patil | C88: C202 | D88: Data Science | E88: B1 | F88: Amit | G88: Web | H88: 11977 | I88: DISC20 | J88: 0.2 | K88: 13000 | L88: 45322
A89: S1087 | B89: Rohit Shah | C89: C202 | D89: Data Science | E89: B2 | F89: Amit | G89: Mobile | H89: 14141 | I89: DISC30 | J89: 0.3 | K89: 13000 | L89: 45302
A90: S1088 | B90: Kavita Joshi | C90: C201 | D90: Data Analytics | E90: B1 | F90: Priya | G90: Web | H90: 14370 | I90: DISC10 | J90: 0.1 | K90: 14000 | L90: 45351
A91: S1089 | B91: Aditya Joshi | C91: C204 | D91: UI UX Design | E91: B2 | F91: Amit | G91: Web | H91: 7311 | I91: DISC15 | K91: 9000 | L91: 45336
A92: S1090 | B92: Meera Singh | C92: C202 | D92: Data Science | E92: B1 | F92: Amit | G92: Mobile | H92: 14482 | I92: DISC15 | K92: 13000 | L92: 45343
A93: S1091 | B93: Riya Patel | C93: C201 | D93: Data Analytics | E93: B2 | F93: Amit | G93: Mobile | H93: 14709 | I93: DISC30 | J93: 0.3 | K93: 14000 | L93: 45296
A94: S1092 | B94: Manish Singh | C94: C203 | D94: Full Stack Dev | E94: B1 | F94: Priya | G94: Mobile | H94: 15432 | K94: 17000 | L94: 45315
A95: S1093 | B95: Rohit Nair | C95: C204 | D95: UI UX Design | E95: B3 | F95: Saurabh | G95: Mobile | H95: 7721 | I95: DISC15 | K95: 9000 | L95: 45333
A96: S1094 | B96: Aditya Joshi | C96: C204 | D96: UI UX Design | E96: B2 | F96: Priya | G96: Tablet | H96: 9426 | I96: DISC30 | J96: 0.3 | K96: 9000 | L96: 45312
A97: S1095 | B97: Meera Patil | C97: C201 | D97: Data Analytics | E97: B2 | F97: Priya | G97: Web | H97: 15073 | K97: 14000 | L97: 45328
A98: S1096 | B98: Kavita Singh | C98: C204 | D98: UI UX Design | E98: B2 | F98: Saurabh | G98: Mobile | H98: 10485 | I98: DISC30 | J98: 0.3 | K98: 9000 | L98: 45303
A99: S1097 | B99: Neha Patil | C99: C203 | D99: Full Stack Dev | E99: B2 | F99: Priya | G99: Mobile | H99: 18605 | I99: DISC15 | K99: 17000 | L99: 45336
A100: S1098 | B100: Kunal Rao | C100: C201 | D100: Data Analytics | E100: B3 | F100: Saurabh | G100: Web | H100: 12988 | K100: 14000 | L100: 45323
...

Sheet Q1
A1: CourseID | B1: CourseName
A2: C201 | B2: Data Analytics
A3: C203 | B3: Full Stack Dev
A4: C202 | B4: Data Science
A5: C204 | B5: UI UX Design

Sheet Q2
A1: Platform | B1: Total No of Enrollment
A2: Mobile | B2: =COUNTIF(Dataset!$A$1:$L$1001,'Q2'!A2) -> 321

Sheet Q3
A1: Course | B1: Total Payment Amount
A2: Data Analytics | B2: =SUMIF(Dataset!$D$1:$D$1001,'Q3'!A2,Dataset!$H$1:$H$1001) -> 3507731

Sheet Q4
A1: Student_id | B1: Mentor_name
A2: S1000 | B2: =VLOOKUP(A2,Dataset!$A$1:$L$1001,6,0) -> Priya
A3: s1007 | B3: =VLOOKUP(A3,Dataset!$A$1:$L$1001,6,0) -> Saurabh

Sheet Q5
A1: StudentID | B1: StudentName | C1: CourseID | D1: CourseName | E1: BatchID | F1: MentorName | G1: Platform | H1: PaymentAmount | I1: DiscountCode | J1: DiscountPercent | K1: TargetRevenue | L1: PaymentDate | M1: Performance Status | N1: Percentage of Record
A2: S1000 | B2: Rohit Shah | C2: C201 | D2: Data Analytics | E2: B3 | F2: Priya | G2: Web | H2: 12914 | I2: DISC20 | J2: 0.2 | K2: 14000 | L2: 45339 | M2: =IF(H2>=K2,"Target Achieved","Below Target") -> Below Target | N2: =COUNTIF($M$2:$M$1001,"Target Achieved")/COUNTA($M$2:$M$1001)*100 -> 51.6
A3: S1001 | B3: Riya Singh | C3: C201 | D3: Data Analytics | E3: B3 | F3: Priya | G3: Web | H3: 12122 | I3: DISC10 | J3: 0.1 | K3: 14000 | L3: 45305 | M3: =IF(H3>=K3,"Target Achieved","Below Target") -> Below Target
A4: S1002 | B4: Sneha Gupta | C4: C201 | D4: Data Analytics | E4: B3 | F4: Saurabh | G4: Tablet | H4: 14661 | I4: DISC15 | K4: 14000 | L4: 45318 | M4: =IF(H4>=K4,"Target Achieved","Below Target") -> Target Achieved
A5: S1003 | B5: Sneha Iyer | C5: C203 | D5: Full Stack Dev | E5: B1 | F5: Saurabh | G5: Tablet | H5: 16731 | I5: DISC30 | J5: 0.3 | K5: 17000 | L5: 45309 | M5: =IF(H5>=K5,"Target Achieved","Below Target") -> Below Target
A6: S1004 | B6: Karan Patil | C6: C203 | D6: Full Stack Dev | E6: B1 | F6: Saurabh | G6: Mobile | H6: 15396 | I6: DISC30 | J6: 0.3 | K6: 17000 | L6: 45346 | M6: =IF(H6>=K6,"Target Achieved","Below Target") -> Below Target
A7: S1005 | B7: Pooja Joshi | C7: C203 | D7: Full Stack Dev | E7: B1 | F7: Amit | G7: Mobile | H7: 17196 | I7: DISC10 | J7: 0.1 | K7: 17000 | L7: 45351 | M7: =IF(H7>=K7,"Target Achieved","Below Target") -> Target Achieved
A8: S1006 | B8: Rahul Shah | C8: C203 | D8: Full Stack Dev | E8: B3 | F8: Amit | G8: Mobile | H8: 17364 | I8: DISC20 | J8: 0.2 | K8: 17000 | L8: 45337 | M8: =IF(H8>=K8,"Target Achieved","Below Target") -> Target Achieved
A9: S1007 | B9: Riya Kulkarni | C9: C202 | D9: Data Science | E9: B2 | F9: Saurabh | G9: Web | H9: 14549 | I9: DISC10 | J9: 0.1 | K9: 13000 | L9: 45316 | M9: =IF(H9>=K9,"Target Achieved","Below Target") -> Target Achieved
A10: S1008 | B10: Aditya Iyer | C10: C203 | D10: Full Stack Dev | E10: B1 | F10: Priya | G10: Mobile | H10: 15858 | I10: DISC30 | J10: 0.3 | K10: 17000 | L10: 45336 | M10: =IF(H10>=K10,"Target Achieved","Below Target") -> Below Target
A11: S1009 | B11: Kunal Singh | C11: C201 | D11: Data Analytics | E11: B3 | F11: Amit | G11: Web | H11: 14187 | I11: DISC20 | J11: 0.2 | K11: 14000 | L11: 45302 | M11: =IF(H11>=K11,"Target Achieved","Below Target") -> Target Achieved
A12: S1010 | B12: Neha Verma | C12: C203 | D12: Full Stack Dev | E12: B3 | F12: Amit | G12: Tablet | H12: 15899 | I12: DISC30 | J12: 0.3 | K12: 17000 | L12: 45345 | M12: =IF(H12>=K12,"Target Achieved","Below Target") -> Below Target
A13: S1011 | B13: Dev Patel | C13: C201 | D13: Data Analytics | E13: B1 | F13: Saurabh | G13: Mobile | H13: 13643 | I13: DISC30 | J13: 0.3 | K13: 14000 | L13: 45296 | M13: =IF(H13>=K13,"Target Achieved","Below Target") -> Below Target
A14: S1012 | B14: Sneha Joshi | C14: C203 | D14: Full Stack Dev | E14: B1 | F14: Amit | G14: Mobile | H14: 16620 | K14: 17000 | L14: 45301 | M14: =IF(H14>=K14,"Target Achieved","Below Target") -> Below Target
A15: S1013 | B15: Aditya Mehta | C15: C202 | D15: Data Science | E15: B3 | F15: Amit | G15: Tablet | H15: 12076 | I15: DISC15 | K15: 13000 | L15: 45319 | M15: =IF(H15>=K15,"Target Achieved","Below Target") -> Below Target
A16: S1014 | B16: Kunal Joshi | C16: C204 | D16: UI UX Design | E16: B2 | F16: Saurabh | G16: Web | H16: 9087 | K16: 9000 | L16: 45297 | M16: =IF(H16>=K16,"Target Achieved","Below Target") -> Target Achieved
A17: S1015 | B17: Dev Kulkarni | C17: C201 | D17: Data Analytics | E17: B1 | F17: Amit | G17: Web | H17: 15244 | K17: 14000 | L17: 45330 | M17: =IF(H17>=K17,"Target Achieved","Below Target") -> Target Achieved
A18: S1016 | B18: Riya Verma | C18: C204 | D18: UI UX Design | E18: B3 | F18: Priya | G18: Tablet | H18: 8029 | I18: DISC15 | K18: 9000 | L18: 45347 | M18: =IF(H18>=K18,"Target Achieved","Below Target") -> Below Target
A19: S1017 | B19: Aarav Singh | C19: C201 | D19: Data Analytics | E19: B3 | F19: Amit | G19: Mobile | H19: 15148 | I19: DISC30 | J19: 0.3 | K19: 14000 | L19: 45299 | M19: =IF(H19>=K19,"Target Achieved","Below Target") -> Target Achieved
A20: S1018 | B20: Aditya Verma | C20: C202 | D20: Data Science | E20: B2 | F20: Saurabh | G20: Tablet | H20: 14587 | I20: DISC30 | J20: 0.3 | K20: 13000 | L20: 45324 | M20: =IF(H20>=K20,"Target Achieved","Below Target") -> Target Achieved
A21: S1019 | B21: Dev Mehta | C21: C201 | D21: Data Analytics | E21: B3 | F21: Priya | G21: Tablet | H21: 14079 | I21: DISC15 | K21: 14000 | L21: 45304 | M21: =IF(H21>=K21,"Target Achieved","Below Target") -> Target Achieved
A22: S1020 | B22: Karan Jain | C22: C202 | D22: Data Science | E22: B3 | F22: Amit | G22: Web | H22: 13453 | I22: DISC30 | J22: 0.3 | K22: 13000 | L22: 45323 | M22: =IF(H22>=K22,"Target Achieved","Below Target") -> Target Achieved
A23: S1021 | B23: Aarav Shah | C23: C203 | D23: Full Stack Dev | E23: B2 | F23: Saurabh | G23: Web | H23: 15986 | I23: DISC15 | K23: 17000 | L23: 45352 | M23: =IF(H23>=K23,"Target Achieved","Below Target") -> Below Target
A24: S1022 | B24: Riya Shah | C24: C204 | D24: UI UX Design | E24: B1 | F24: Amit | G24: Web | H24: 7525 | K24: 9000 | L24: 45352 | M24: =IF(H24>=K24,"Target Achieved","Below Target") -> Below Target
A25: S1023 | B25: Manish Mehta | C25: C203 | D25: Full Stack Dev | E25: B3 | F25: Amit | G25: Mobile | H25: 18950 | I25: DISC20 | J25: 0.2 | K25: 17000 | L25: 45351 | M25: =IF(H25>=K25,"Target Achieved","Below Target") -> Target Achieved
A26: S1024 | B26: Manish Patel | C26: C202 | D26: Data Science | E26: B3 | F26: Priya | G26: Mobile | H26: 13751 | I26: DISC30 | J26: 0.3 | K26: 13000 | L26: 45320 | M26: =IF(H26>=K26,"Target Achieved","Below Target") -> Target Achieved
A27: S1025 | B27: Kunal Gupta | C27: C204 | D27: UI UX Design | E27: B1 | F27: Saurabh | G27: Web | H27: 7262 | I27: DISC30 | J27: 0.3 | K27: 9000 | L27: 45293 | M27: =IF(H27>=K27,"Target Achieved","Below Target") -> Below Target
A28: S1026 | B28: Kavita Gupta | C28: C202 | D28: Data Science | E28: B3 | F28: Saurabh | G28: Web | H28: 11290 | I28: DISC10 | J28: 0.1 | K28: 13000 | L28: 45306 | M28: =IF(H28>=K28,"Target Achieved","Below Target") -> Below Target
A29: S1027 | B29: Riya Kulkarni | C29: C203 | D29: Full Stack Dev | E29: B1 | F29: Amit | G29: Web | H29: 16140 | K29: 17000 | L29: 45305 | M29: =IF(H29>=K29,"Target Achieved","Below Target") -> Below Target
A30: S1028 | B30: Manish Mehta | C30: C204 | D30: UI UX Design | E30: B1 | F30: Priya | G30: Mobile | H30: 7779 | I30: DISC10 | J30: 0.1 | K30: 9000 | L30: 45298 | M30: =IF(H30>=K30,"Target Achieved","Below Target") -> Below Target
A31: S1029 | B31: Rohit Verma | C31: C203 | D31: Full Stack Dev | E31: B2 | F31: Priya | G31: Mobile | H31: 18538 | I31: DISC10 | J31: 0.1 | K31: 17000 | L31: 45335 | M31: =IF(H31>=K31,"Target Achieved","Below Target") -> Target Achieved
A32: S1030 | B32: Rohit Singh | C32: C201 | D32: Data Analytics | E32: B1 | F32: Priya | G32: Tablet | H32: 13389 | I32: DISC10 | J32: 0.1 | K32: 14000 | L32: 45307 | M32: =IF(H32>=K32,"Target Achieved","Below Target") -> Below Target
A33: S1031 | B33: Sneha Patil | C33: C204 | D33: UI UX Design | E33: B1 | F33: Priya | G33: Web | H33: 8140 | K33: 9000 | L33: 45307 | M33: =IF(H33>=K33,"Target Achieved","Below Target") -> Below Target
A34: S1032 | B34: Meera Shah | C34: C204 | D34: UI UX Design | E34: B3 | F34: Saurabh | G34: Web | H34: 9671 | I34: DISC15 | K34: 9000 | L34: 45345 | M34: =IF(H34>=K34,"Target Achieved","Below Target") -> Target Achieved
A35: S1033 | B35: Aarav Shah | C35: C202 | D35: Data Science | E35: B1 | F35: Priya | G35: Mobile | H35: 12971 | I35: DISC20 | J35: 0.2 | K35: 13000 | L35: 45347 | M35: =IF(H35>=K35,"Target Achieved","Below Target") -> Below Target
A36: S1034 | B36: Rahul Kulkarni | C36: C202 | D36: Data Science | E36: B2 | F36: Saurabh | G36: Mobile | H36: 12086 | K36: 13000 | L36: 45310 | M36: =IF(H36>=K36,"Target Achieved","Below Target") -> Below Target
A37: S1035 | B37: Rahul Desai | C37: C204 | D37: UI UX Design | E37: B1 | F37: Saurabh | G37: Mobile | H37: 7891 | I37: DISC10 | J37: 0.1 | K37: 9000 | L37: 45329 | M37: =IF(H37>=K37,"Target Achieved","Below Target") -> Below Target
A38: S1036 | B38: Anjali Gupta | C38: C201 | D38: Data Analytics | E38: B3 | F38: Priya | G38: Web | H38: 12205 | I38: DISC15 | K38: 14000 | L38: 45322 | M38: =IF(H38>=K38,"Target Achieved","Below Target") -> Below Target
A39: S1037 | B39: Manish Nair | C39: C202 | D39: Data Science | E39: B1 | F39: Amit | G39: Web | H39: 14487 | I39: DISC20 | J39: 0.2 | K39: 13000 | L39: 45296 | M39: =IF(H39>=K39,"Target Achieved","Below Target") -> Target Achieved
A40: S1038 | B40: Kavita Shah | C40: C202 | D40: Data Science | E40: B2 | F40: Saurabh | G40: Tablet | H40: 12008 | I40: DISC15 | K40: 13000 | L40: 45330 | M40: =IF(H40>=K40,"Target Achieved","Below Target") -> Below Target
A41: S1039 | B41: Aarav Joshi | C41: C201 | D41: Data Analytics | E41: B2 | F41: Amit | G41: Tablet | H41: 14315 | I41: DISC15 | K41: 14000 | L41: 45312 | M41: =IF(H41>=K41,"Target Achieved","Below Target") -> Target Achieved
A42: S1040 | B42: Kunal Rao | C42: C202 | D42: Data Science | E42: B3 | F42: Amit | G42: Mobile | H42: 11977 | I42: DISC30 | J42: 0.3 | K42: 13000 | L42: 45317 | M42: =IF(H42>=K42,"Target Achieved","Below Target") -> Below Target
A43: S1041 | B43: Karan Singh | C43: C203 | D43: Full Stack Dev | E43: B2 | F43: Priya | G43: Web | H43: 15038 | K43: 17000 | L43: 45331 | M43: =IF(H43>=K43,"Target Achieved","Below Target") -> Below Target
A44: S1042 | B44: Kavita Shah | C44: C201 | D44: Data Analytics | E44: B3 | F44: Saurabh | G44: Tablet | H44: 13086 | I44: DISC20 | J44: 0.2 | K44: 14000 | L44: 45351 | M44: =IF(H44>=K44,"Target Achieved","Below Target") -> Below Target
A45: S1043 | B45: Pooja Shah | C45: C202 | D45: Data Science | E45: B2 | F45: Priya | G45: Web | H45: 12794 | I45: DISC15 | K45: 13000 | L45: 45337 | M45: =IF(H45>=K45,"Target Achieved","Below Target") -> Below Target
A46: S1044 | B46: Aditya Joshi | C46: C201 | D46: Data Analytics | E46: B3 | F46: Amit | G46: Mobile | H46: 15816 | I46: DISC10 | J46: 0.1 | K46: 14000 | L46: 45352 | M46: =IF(H46>=K46,"Target Achieved","Below Target") -> Target Achieved
A47: S1045 | B47: Kunal Mehta | C47: C203 | D47: Full Stack Dev | E47: B1 | F47: Saurabh | G47: Tablet | H47: 17266 | I47: DISC20 | J47: 0.2 | K47: 17000 | L47: 45309 | M47: =IF(H47>=K47,"Target Achieved","Below Target") -> Target Achieved
A48: S1046 | B48: Aditya Joshi | C48: C202 | D48: Data Science | E48: B3 | F48: Priya | G48: Web | H48: 13815 | I48: DISC30 | J48: 0.3 | K48: 13000 | L48: 45324 | M48: =IF(H48>=K48,"Target Achieved","Below Target") -> Target Achieved
A49: S1047 | B49: Neha Rao | C49: C201 | D49: Data Analytics | E49: B1 | F49: Amit | G49: Mobile | H49: 15397 | I49: DISC30 | J49: 0.3 | K49: 14000 | L49: 45294 | M49: =IF(H49>=K49,"Target Achieved","Below Target") -> Target Achieved
A50: S1048 | B50: Aarav Jain | C50: C202 | D50: Data Science | E50: B3 | F50: Priya | G50: Web | H50: 14036 | K50: 13000 | L50: 45327 | M50: =IF(H50>=K50,"Target Achieved","Below Target") -> Target Achieved
A51: S1049 | B51: Anjali Verma | C51: C201 | D51: Data Analytics | E51: B1 | F51: Saurabh | G51: Tablet | H51: 15702 | I51: DISC20 | J51: 0.2 | K51: 14000 | L51: 45326 | M51: =IF(H51>=K51,"Target Achieved","Below Target") -> Target Achieved
A52: S1050 | B52: Aarav Nair | C52: C203 | D52: Full Stack Dev | E52: B3 | F52: Amit | G52: Web | H52: 16760 | I52: DISC20 | J52: 0.2 | K52: 17000 | L52: 45294 | M52: =IF(H52>=K52,"Target Achieved","Below Target") -> Below Target
A53: S1051 | B53: Aditya Jain | C53: C201 | D53: Data Analytics | E53: B2 | F53: Saurabh | G53: Tablet | H53: 13022 | I53: DISC10 | J53: 0.1 | K53: 14000 | L53: 45314 | M53: =IF(H53>=K53,"Target Achieved","Below Target") -> Below Target
A54: S1052 | B54: Dev Gupta | C54: C204 | D54: UI UX Design | E54: B3 | F54: Amit | G54: Web | H54: 10791 | I54: DISC20 | J54: 0.2 | K54: 9000 | L54: 45347 | M54: =IF(H54>=K54,"Target Achieved","Below Target") -> Target Achieved
A55: S1053 | B55: Karan Patel | C55: C202 | D55: Data Science | E55: B2 | F55: Saurabh | G55: Web | H55: 14016 | I55: DISC30 | J55: 0.3 | K55: 13000 | L55: 45342 | M55: =IF(H55>=K55,"Target Achieved","Below Target") -> Target Achieved
A56: S1054 | B56: Kunal Verma | C56: C202 | D56: Data Science | E56: B2 | F56: Saurabh | G56: Tablet | H56: 11442 | K56: 13000 | L56: 45347 | M56: =IF(H56>=K56,"Target Achieved","Below Target") -> Below Target
A57: S1055 | B57: Aarav Nair | C57: C204 | D57: UI UX Design | E57: B1 | F57: Saurabh | G57: Mobile | H57: 8432 | I57: DISC30 | J57: 0.3 | K57: 9000 | L57: 45344 | M57: =IF(H57>=K57,"Target Achieved","Below Target") -> Below Target
A58: S1056 | B58: Dev Nair | C58: C202 | D58: Data Science | E58: B1 | F58: Saurabh | G58: Tablet | H58: 11791 | K58: 13000 | L58: 45313 | M58: =IF(H58>=K58,"Target Achieved","Below Target") -> Below Target
A59: S1057 | B59: Aditya Nair | C59: C201 | D59: Data Analytics | E59: B2 | F59: Priya | G59: Tablet | H59: 14086 | K59: 14000 | L59: 45335 | M59: =IF(H59>=K59,"Target Achieved","Below Target") -> Target Achieved
A60: S1058 | B60: Meera Gupta | C60: C203 | D60: Full Stack Dev | E60: B1 | F60: Saurabh | G60: Mobile | H60: 15731 | I60: DISC15 | K60: 17000 | L60: 45308 | M60: =IF(H60>=K60,"Target Achieved","Below Target") -> Below Target
A61: S1059 | B61: Aarav Shah | C61: C204 | D61: UI UX Design | E61: B2 | F61: Amit | G61: Mobile | H61: 8787 | I61: DISC15 | K61: 9000 | L61: 45324 | M61: =IF(H61>=K61,"Target Achieved","Below Target") -> Below Target
A62: S1060 | B62: Riya Verma | C62: C202 | D62: Data Science | E62: B2 | F62: Saurabh | G62: Tablet | H62: 12786 | I62: DISC10 | J62: 0.1 | K62: 13000 | L62: 45325 | M62: =IF(H62>=K62,"Target Achieved","Below Target") -> Below Target
A63: S1061 | B63: Kunal Patel | C63: C202 | D63: Data Science | E63: B2 | F63: Priya | G63: Web | H63: 14886 | I63: DISC30 | J63: 0.3 | K63: 13000 | L63: 45331 | M63: =IF(H63>=K63,"Target Achieved","Below Target") -> Target Achieved
A64: S1062 | B64: Pooja Singh | C64: C201 | D64: Data Analytics | E64: B3 | F64: Priya | G64: Tablet | H64: 13266 | K64: 14000 | L64: 45312 | M64: =IF(H64>=K64,"Target Achieved","Below Target") -> Below Target
A65: S1063 | B65: Rahul Desai | C65: C203 | D65: Full Stack Dev | E65: B3 | F65: Saurabh | G65: Web | H65: 16722 | K65: 17000 | L65: 45335 | M65: =IF(H65>=K65,"Target Achieved","Below Target") -> Below Target
A66: S1064 | B66: Anjali Mehta | C66: C203 | D66: Full Stack Dev | E66: B2 | F66: Amit | G66: Web | H66: 16244 | I66: DISC30 | J66: 0.3 | K66: 17000 | L66: 45305 | M66: =IF(H66>=K66,"Target Achieved","Below Target") -> Below Target
A67: S1065 | B67: Rahul Patel | C67: C203 | D67: Full Stack Dev | E67: B2 | F67: Priya | G67: Mobile | H67: 17767 | I67: DISC20 | J67: 0.2 | K67: 17000 | L67: 45324 | M67: =IF(H67>=K67,"Target Achieved","Below Target") -> Target Achieved
A68: S1066 | B68: Neha Patel | C68: C202 | D68: Data Science | E68: B3 | F68: Saurabh | G68: Mobile | H68: 13111 | I68: DISC15 | K68: 13000 | L68: 45313 | M68: =IF(H68>=K68,"Target Achieved","Below Target") -> Target Achieved
A69: S1067 | B69: Riya Nair | C69: C202 | D69: Data Science | E69: B3 | F69: Priya | G69: Web | H69: 14303 | I69: DISC20 | J69: 0.2 | K69: 13000 | L69: 45301 | M69: =IF(H69>=K69,"Target Achieved","Below Target") -> Target Achieved
A70: S1068 | B70: Aarav Kulkarni | C70: C202 | D70: Data Science | E70: B2 | F70: Amit | G70: Web | H70: 12865 | K70: 13000 | L70: 45348 | M70: =IF(H70>=K70,"Target Achieved","Below Target") -> Below Target
A71: S1069 | B71: Rohit Joshi | C71: C202 | D71: Data Science | E71: B3 | F71: Amit | G71: Mobile | H71: 13024 | K71: 13000 | L71: 45307 | M71: =IF(H71>=K71,"Target Achieved","Below Target") -> Target Achieved
A72: S1070 | B72: Karan Singh | C72: C201 | D72: Data Analytics | E72: B1 | F72: Priya | G72: Web | H72: 12720 | I72: DISC15 | K72: 14000 | L72: 45321 | M72: =IF(H72>=K72,"Target Achieved","Below Target") -> Below Target
A73: S1071 | B73: Aarav Gupta | C73: C202 | D73: Data Science | E73: B1 | F73: Priya | G73: Web | H73: 14282 | K73: 13000 | L73: 45334 | M73: =IF(H73>=K73,"Target Achieved","Below Target") -> Target Achieved
A74: S1072 | B74: Manish Gupta | C74: C203 | D74: Full Stack Dev | E74: B2 | F74: Amit | G74: Tablet | H74: 18653 | I74: DISC15 | K74: 17000 | L74: 45319 | M74: =IF(H74>=K74,"Target Achieved","Below Target") -> Target Achieved
A75: S1073 | B75: Meera Gupta | C75: C204 | D75: UI UX Design | E75: B1 | F75: Amit | G75: Mobile | H75: 8843 | I75: DISC30 | J75: 0.3 | K75: 9000 | L75: 45340 | M75: =IF(H75>=K75,"Target Achieved","Below Target") -> Below Target
A76: S1074 | B76: Sneha Nair | C76: C203 | D76: Full Stack Dev | E76: B3 | F76: Priya | G76: Tablet | H76: 15979 | I76: DISC30 | J76: 0.3 | K76: 17000 | L76: 45320 | M76: =IF(H76>=K76,"Target Achieved","Below Target") -> Below Target
A77: S1075 | B77: Riya Desai | C77: C203 | D77: Full Stack Dev | E77: B1 | F77: Priya | G77: Mobile | H77: 16309 | I77: DISC15 | K77: 17000 | L77: 45297 | M77: =IF(H77>=K77,"Target Achieved","Below Target") -> Below Target
A78: S1076 | B78: Karan Mehta | C78: C202 | D78: Data Science | E78: B2 | F78: Amit | G78: Web | H78: 13893 | I78: DISC20 | J78: 0.2 | K78: 13000 | L78: 45296 | M78: =IF(H78>=K78,"Target Achieved","Below Target") -> Target Achieved
A79: S1077 | B79: Rahul Verma | C79: C203 | D79: Full Stack Dev | E79: B3 | F79: Priya | G79: Mobile | H79: 15255 | I79: DISC20 | J79: 0.2 | K79: 17000 | L79: 45345 | M79: =IF(H79>=K79,"Target Achieved","Below Target") -> Below Target
A80: S1078 | B80: Rahul Verma | C80: C201 | D80: Data Analytics | E80: B3 | F80: Priya | G80: Mobile | H80: 12024 | I80: DISC30 | J80: 0.3 | K80: 14000 | L80: 45311 | M80: =IF(H80>=K80,"Target Achieved","Below Target") -> Below Target
A81: S1079 | B81: Dev Verma | C81: C204 | D81: UI UX Design | E81: B3 | F81: Amit | G81: Tablet | H81: 9236 | I81: DISC15 | K81: 9000 | L81: 45349 | M81: =IF(H81>=K81,"Target Achieved","Below Target") -> Target Achieved
A82: S1080 | B82: Sneha Iyer | C82: C202 | D82: Data Science | E82: B2 | F82: Priya | G82: Mobile | H82: 11118 | K82: 13000 | L82: 45313 | M82: =IF(H82>=K82,"Target Achieved","Below Target") -> Below Target
A83: S1081 | B83: Rohit Singh | C83: C204 | D83: UI UX Design | E83: B3 | F83: Saurabh | G83: Mobile | H83: 10766 | I83: DISC20 | J83: 0.2 | K83: 9000 | L83: 45331 | M83: =IF(H83>=K83,"Target Achieved","Below Target") -> Target Achieved
A84: S1082 | B84: Manish Kulkarni | C84: C204 | D84: UI UX Design | E84: B3 | F84: Amit | G84: Tablet | H84: 7111 | I84: DISC10 | J84: 0.1 | K84: 9000 | L84: 45333 | M84: =IF(H84>=K84,"Target Achieved","Below Target") -> Below Target
A85: S1083 | B85: Rahul Mehta | C85: C204 | D85: UI UX Design | E85: B1 | F85: Saurabh | G85: Mobile | H85: 8552 | I85: DISC30 | J85: 0.3 | K85: 9000 | L85: 45305 | M85: =IF(H85>=K85,"Target Achieved","Below Target") -> Below Target
A86: S1084 | B86: Neha Jain | C86: C203 | D86: Full Stack Dev | E86: B2 | F86: Priya | G86: Mobile | H86: 16033 | I86: DISC10 | J86: 0.1 | K86: 17000 | L86: 45322 | M86: =IF(H86>=K86,"Target Achieved","Below Target") -> Below Target
A87: S1085 | B87: Aarav Desai | C87: C201 | D87: Data Analytics | E87: B2 | F87: Saurabh | G87: Tablet | H87: 12281 | I87: DISC10 | J87: 0.1 | K87: 14000 | L87: 45340 | M87: =IF(H87>=K87,"Target Achieved","Below Target") -> Below Target
A88: S1086 | B88: Aarav Patil | C88: C202 | D88: Data Science | E88: B1 | F88: Amit | G88: Web | H88: 11977 | I88: DISC20 | J88: 0.2 | K88: 13000 | L88: 45322 | M88: =IF(H88>=K88,"Target Achieved","Below Target") -> Below Target
A89: S1087 | B89: Rohit Shah | C89: C202 | D89: Data Science | E89: B2 | F89: Amit | G89: Mobile | H89: 14141 | I89: DISC30 | J89: 0.3 | K89: 13000 | L89: 45302 | M89: =IF(H89>=K89,"Target Achieved","Below Target") -> Target Achieved
A90: S1088 | B90: Kavita Joshi | C90: C201 | D90: Data Analytics | E90: B1 | F90: Priya | G90: Web | H90: 14370 | I90: DISC10 | J90: 0.1 | K90: 14000 | L90: 45351 | M90: =IF(H90>=K90,"Target Achieved","Below Target") -> Target Achieved
A91: S1089 | B91: Aditya Joshi | C91: C204 | D91: UI UX Design | E91: B2 | F91: Amit | G91: Web | H91: 7311 | I91: DISC15 | K91: 9000 | L91: 45336 | M91: =IF(H91>=K91,"Target Achieved","Below Target") -> Below Target
A92: S1090 | B92: Meera Singh | C92: C202 | D92: Data Science | E92: B1 | F92: Amit | G92: Mobile | H92: 14482 | I92: DISC15 | K92: 13000 | L92: 45343 | M92: =IF(H92>=K92,"Target Achieved","Below Target") -> Target Achieved
A93: S1091 | B93: Riya Patel | C93: C201 | D93: Data Analytics | E93: B2 | F93: Amit | G93: Mobile | H93: 14709 | I93: DISC30 | J93: 0.3 | K93: 14000 | L93: 45296 | M93: =IF(H93>=K93,"Target Achieved","Below Target") -> Target Achieved
A94: S1092 | B94: Manish Singh | C94: C203 | D94: Full Stack Dev | E94: B1 | F94: Priya | G94: Mobile | H94: 15432 | K94: 17000 | L94: 45315 | M94: =IF(H94>=K94,"Target Achieved","Below Target") -> Below Target
A95: S1093 | B95: Rohit Nair | C95: C204 | D95: UI UX Design | E95: B3 | F95: Saurabh | G95: Mobile | H95: 7721 | I95: DISC15 | K95: 9000 | L95: 45333 | M95: =IF(H95>=K95,"Target Achieved","Below Target") -> Below Target
A96: S1094 | B96: Aditya Joshi | C96: C204 | D96: UI UX Design | E96: B2 | F96: Priya | G96: Tablet | H96: 9426 | I96: DISC30 | J96: 0.3 | K96: 9000 | L96: 45312 | M96: =IF(H96>=K96,"Target Achieved","Below Target") -> Target Achieved
A97: S1095 | B97: Meera Patil | C97: C201 | D97: Data Analytics | E97: B2 | F97: Priya | G97: Web | H97: 15073 | K97: 14000 | L97: 45328 | M97: =IF(H97>=K97,"Target Achieved","Below Target") -> Target Achieved
A98: S1096 | B98: Kavita Singh | C98: C204 | D98: UI UX Design | E98: B2 | F98: Saurabh | G98: Mobile | H98: 10485 | I98: DISC30 | J98: 0.3 | K98: 9000 | L98: 45303 | M98: =IF(H98>=K98,"Target Achieved","Below Target") -> Target Achieved
A99: S1097 | B99: Neha Patil | C99: C203 | D99: Full Stack Dev | E99: B2 | F99: Priya | G99: Mobile | H99: 18605 | I99: DISC15 | K99: 17000 | L99: 45336 | M99: =IF(H99>=K99,"Target Achieved","Below Target") -> Target Achieved
A100: S1098 | B100: Kunal Rao | C100: C201 | D100: Data Analytics | E100: B3 | F100: Saurabh | G100: Web | H100: 12988 | K100: 14000 | L100: 45323 | M100: =IF(H100>=K100,"Target Achieved","Below Target") -> Below Target
...

Sheet Q6
A1: StudentID | B1: StudentName | C1: CourseID | D1: CourseName | E1: BatchID | F1: MentorName | G1: Platform | H1: PaymentAmount | I1: DiscountCode | J1: DiscountPercent | K1: TargetRevenue | L1: PaymentDate | M1: New_DiscountPercent
A2: S1000 | B2: Rohit Shah | C2: C201 | D2: Data Analytics | E2: B3 | F2: Priya | G2: Web | H2: 12914 | I2: DISC20 | J2: 0.2 | K2: 14000 | L2: 45339 | M2: =IF(OR(I2="",ISNA(MATCH(I2,{"DISC10","DISC15","DISC20","DISC30"},0))),0,J2) -> 0.2
A3: S1001 | B3: Riya Singh | C3: C201 | D3: Data Analytics | E3: B3 | F3: Priya | G3: Web | H3: 12122 | I3: DISC10 | J3: 0.1 | K3: 14000 | L3: 45305 | M3: =IF(OR(I3="",ISNA(MATCH(I3,{"DISC10","DISC15","DISC20","DISC30"},0))),0,J3) -> 0.1
A4: S1002 | B4: Sneha Gupta | C4: C201 | D4: Data Analytics | E4: B3 | F4: Saurabh | G4: Tablet | H4: 14661 | I4: DISC15 | K4: 14000 | L4: 45318 | M4: =IF(OR(I4="",ISNA(MATCH(I4,{"DISC10","DISC15","DISC20","DISC30"},0))),0,J4) -> 0
A5: S1003 | B5: Sneha Iyer | C5: C203 | D5: Full Stack Dev | E5: B1 | F5: Saurabh | G5: Tablet | H5: 16731 | I5: DISC30 | J5: 0.3 | K5: 17000 | L5: 45309 | M5: =IF(OR(I5="",ISNA(MATCH(I5,{"DISC10","DISC15","DISC20","DISC30"},0))),0,J5) -> 0.3
A6: S1004 | B6: Karan Patil | C6: C203 | D6: Full Stack Dev | E6: B1 | F6: Saurabh | G6: Mobile | H6: 15396 | I6: DISC30 | J6: 0.3 | K6: 17000 | L6: 45346 | M6: =IF(OR(I6="",ISNA(MATCH(I6,{"DISC10","DISC15","DISC20","DISC30"},0))),0,J6) -> 0.3
A7: S1005 | B7: Pooja Joshi | C7: C203 | D7: Full Stack Dev | E7: B1 | F7: Amit | G7: Mobile | H7: 17196 | I7: DISC10 | J7: 0.1 | K7: 17000 | L7: 45351 | M7: =IF(OR(I7="",ISNA(MATCH(I7,{"DISC10","DISC15","DISC20","DISC30"},0))),0,J7) -> 0.1
A8: S1006 | B8: Rahul Shah | C8: C203 | D8: Full Stack Dev | E8: B3 | F8: Amit | G8: Mobile | H8: 17364 | I8: DISC20 | J8: 0.2 | K8: 17000 | L8: 45337 | M8: =IF(OR(I8="",ISNA(MATCH(I8,{"DISC10","DISC15","DISC20","DISC30"},0))),0,J8) -> 0.2
A9: S1007 | B9: Riya Kulkarni | C9: C202 | D9: Data Science | E9: B2 | F9: Saurabh | G9: Web | H9: 14549 | I9: DISC10 | J9: 0.1 | K9: 13000 | L9: 45316 | M9: =IF(OR(I9="",ISNA(MATCH(I9,{"DISC10","DISC15","DISC20","DISC30"},0))),0,J9) -> 0.1
A10: S1008 | B10: Aditya Iyer | C10: C203 | D10: Full Stack Dev | E10: B1 | F10: Priya | G10: Mobile | H10: 15858 | I10: DISC30 | J10: 0.3 | K10: 17000 | L10: 45336 | M10: =IF(OR(I10="",ISNA(MATCH(I10,{"DISC10","DISC15","DISC20","DISC30"},0))),0,J10) -> 0.3
A11: S1009 | B11: Kunal Singh | C11: C201 | D11: Data Analytics | E11: B3 | F11: Amit | G11: Web | H11: 14187 | I11: DISC20 | J11: 0.2 | K11: 14000 | L11: 45302 | M11: =IF(OR(I11="",ISNA(MATCH(I11,{"DISC10","DISC15","DISC20","DISC30"},0))),0,J11) -> 0.2
A12: S1010 | B12: Neha Verma | C12: C203 | D12: Full Stack Dev | E12: B3 | F12: Amit | G12: Tablet | H12: 15899 | I12: DISC30 | J12: 0.3 | K12: 17000 | L12: 45345 | M12: =IF(OR(I12="",ISNA(MATCH(I12,{"DISC10","DISC15","DISC20","DISC30"},0))),0,J12) -> 0.3
A13: S1011 | B13: Dev Patel | C13: C201 | D13: Data Analytics | E13: B1 | F13: Saurabh | G13: Mobile | H13: 13643 | I13: DISC30 | J13: 0.3 | K13: 14000 | L13: 45296 | M13: =IF(OR(I13="",ISNA(MATCH(I13,{"DISC10","DISC15","DISC20","DISC30"},0))),0,J13) -> 0.3
A14: S1012 | B14: Sneha Joshi | C14: C203 | D14: Full Stack Dev | E14: B1 | F14: Amit | G14: Mobile | H14: 16620 | K14: 17000 | L14: 45301 | M14: =IF(OR(I14="",ISNA(MATCH(I14,{"DISC10","DISC15","DISC20","DISC30"},0))),0,J14) -> 0
A15: S1013 | B15: Aditya Mehta | C15: C202 | D15: Data Science | E15: B3 | F15: Amit | G15: Tablet | H15: 12076 | I15: DISC15 | K15: 13000 | L15: 45319 | M15: =IF(OR(I15="",ISNA(MATCH(I15,{"DISC10","DISC15","DISC20","DISC30"},0))),0,J15) -> 0
A16: S1014 | B16: Kunal Joshi | C16: C204 | D16: UI UX Design | E16: B2 | F16: Saurabh | G16: Web | H16: 9087 | K16: 9000 | L16: 45297 | M16: =IF(OR(I16="",ISNA(MATCH(I16,{"DISC10","DISC15","DISC20","DISC30"},0))),0,J16) -> 0
A17: S1015 | B17: Dev Kulkarni | C17: C201 | D17: Data Analytics | E17: B1 | F17: Amit | G17: Web | H17: 15244 | K17: 14000 | L17: 45330 | M17: =IF(OR(I17="",ISNA(MATCH(I17,{"DISC10","DISC15","DISC20","DISC30"},0))),0,J17) -> 0
A18: S1016 | B18: Riya Verma | C18: C204 | D18: UI UX Design | E18: B3 | F18: Priya | G18: Tablet | H18: 8029 | I18: DISC15 | K18: 9000 | L18: 45347 | M18: =IF(OR(I18="",ISNA(MATCH(I18,{"DISC10","DISC15","DISC20","DISC30"},0))),0,J18) -> 0
A19: S1017 | B19: Aarav Singh | C19: C201 | D19: Data Analytics | E19: B3 | F19: Amit | G19: Mobile | H19: 15148 | I19: DISC30 | J19: 0.3 | K19: 14000 | L19: 45299 | M19: =IF(OR(I19="",ISNA(MATCH(I19,{"DISC10","DISC15","DISC20","DISC30"},0))),0,J19) -> 0.3
A20: S1018 | B20: Aditya Verma | C20: C202 | D20: Data Science | E20: B2 | F20: Saurabh | G20: Tablet | H20: 14587 | I20: DISC30 | J20: 0.3 | K20: 13000 | L20: 45324 | M20: =IF(OR(I20="",ISNA(MATCH(I20,{"DISC10","DISC15","DISC20","DISC30"},0))),0,J20) -> 0.3
A21: S1019 | B21: Dev Mehta | C21: C201 | D21: Data Analytics | E21: B3 | F21: Priya | G21: Tablet | H21: 14079 | I21: DISC15 | K21: 14000 | L21: 45304 | M21: =IF(OR(I21="",ISNA(MATCH(I21,{"DISC10","DISC15","DISC20","DISC30"},0))),0,J21) -> 0
A22: S1020 | B22: Karan Jain | C22: C202 | D22: Data Science | E22: B3 | F22: Amit | G22: Web | H22: 13453 | I22: DISC30 | J22: 0.3 | K22: 13000 | L22: 45323 | M22: =IF(OR(I22="",ISNA(MATCH(I22,{"DISC10","DISC15","DISC20","DISC30"},0))),0,J22) -> 0.3
A23: S1021 | B23: Aarav Shah | C23: C203 | D23: Full Stack Dev | E23: B2 | F23: Saurabh | G23: Web | H23: 15986 | I23: DISC15 | K23: 17000 | L23: 45352 | M23: =IF(OR(I23="",ISNA(MATCH(I23,{"DISC10","DISC15","DISC20","DISC30"},0))),0,J23) -> 0
A24: S1022 | B24: Riya Shah | C24: C204 | D24: UI UX Design | E24: B1 | F24: Amit | G24: Web | H24: 7525 | K24: 9000 | L24: 45352 | M24: =IF(OR(I24="",ISNA(MATCH(I24,{"DISC10","DISC15","DISC20","DISC30"},0))),0,J24) -> 0
A25: S1023 | B25: Manish Mehta | C25: C203 | D25: Full Stack Dev | E25: B3 | F25: Amit | G25: Mobile | H25: 18950 | I25: DISC20 | J25: 0.2 | K25: 17000 | L25: 45351 | M25: =IF(OR(I25="",ISNA(MATCH(I25,{"DISC10","DISC15","DISC20","DISC30"},0))),0,J25) -> 0.2
A26: S1024 | B26: Manish Patel | C26: C202 | D26: Data Science | E26: B3 | F26: Priya | G26: Mobile | H26: 13751 | I26: DISC30 | J26: 0.3 | K26: 13000 | L26: 45320 | M26: =IF(OR(I26="",ISNA(MATCH(I26,{"DISC10","DISC15","DISC20","DISC30"},0))),0,J26) -> 0.3
A27: S1025 | B27: Kunal Gupta | C27: C204 | D27: UI UX Design | E27: B1 | F27: Saurabh | G27: Web | H27: 7262 | I27: DISC30 | J27: 0.3 | K27: 9000 | L27: 45293 | M27: =IF(OR(I27="",ISNA(MATCH(I27,{"DISC10","DISC15","DISC20","DISC30"},0))),0,J27) -> 0.3
A28: S1026 | B28: Kavita Gupta | C28: C202 | D28: Data Science | E28: B3 | F28: Saurabh | G28: Web | H28: 11290 | I28: DISC10 | J28: 0.1 | K28: 13000 | L28: 45306 | M28: =IF(OR(I28="",ISNA(MATCH(I28,{"DISC10","DISC15","DISC20","DISC30"},0))),0,J28) -> 0.1
A29: S1027 | B29: Riya Kulkarni | C29: C203 | D29: Full Stack Dev | E29: B1 | F29: Amit | G29: Web | H29: 16140 | K29: 17000 | L29: 45305 | M29: =IF(OR(I29="",ISNA(MATCH(I29,{"DISC10","DISC15","DISC20","DISC30"},0))),0,J29) -> 0
A30: S1028 | B30: Manish Mehta | C30: C204 | D30: UI UX Design | E30: B1 | F30: Priya | G30: Mobile | H30: 7779 | I30: DISC10 | J30: 0.1 | K30: 9000 | L30: 45298 | M30: =IF(OR(I30="",ISNA(MATCH(I30,{"DISC10","DISC15","DISC20","DISC30"},0))),0,J30) -> 0.1
A31: S1029 | B31: Rohit Verma | C31: C203 | D31: Full Stack Dev | E31: B2 | F31: Priya | G31: Mobile | H31: 18538 | I31: DISC10 | J31: 0.1 | K31: 17000 | L31: 45335 | M31: =IF(OR(I31="",ISNA(MATCH(I31,{"DISC10","DISC15","DISC20","DISC30"},0))),0,J31) -> 0.1
A32: S1030 | B32: Rohit Singh | C32: C201 | D32: Data Analytics | E32: B1 | F32: Priya | G32: Tablet | H32: 13389 | I32: DISC10 | J32: 0.1 | K32: 14000 | L32: 45307 | M32: =IF(OR(I32="",ISNA(MATCH(I32,{"DISC10","DISC15","DISC20","DISC30"},0))),0,J32) -> 0.1
A33: S1031 | B33: Sneha Patil | C33: C204 | D33: UI UX Design | E33: B1 | F33: Priya | G33: Web | H33: 8140 | K33: 9000 | L33: 45307 | M33: =IF(OR(I33="",ISNA(MATCH(I33,{"DISC10","DISC15","DISC20","DISC30"},0))),0,J33) -> 0
A34: S1032 | B34: Meera Shah | C34: C204 | D34: UI UX Design | E34: B3 | F34: Saurabh | G34: Web | H34: 9671 | I34: DISC15 | K34: 9000 | L34: 45345 | M34: =IF(OR(I34="",ISNA(MATCH(I34,{"DISC10","DISC15","DISC20","DISC30"},0))),0,J34) -> 0
A35: S1033 | B35: Aarav Shah | C35: C202 | D35: Data Science | E35: B1 | F35: Priya | G35: Mobile | H35: 12971 | I35: DISC20 | J35: 0.2 | K35: 13000 | L35: 45347 | M35: =IF(OR(I35="",ISNA(MATCH(I35,{"DISC10","DISC15","DISC20","DISC30"},0))),0,J35) -> 0.2
A36: S1034 | B36: Rahul Kulkarni | C36: C202 | D36: Data Science | E36: B2 | F36: Saurabh | G36: Mobile | H36: 12086 | K36: 13000 | L36: 45310 | M36: =IF(OR(I36="",ISNA(MATCH(I36,{"DISC10","DISC15","DISC20","DISC30"},0))),0,J36) -> 0
A37: S1035 | B37: Rahul Desai | C37: C204 | D37: UI UX Design | E37: B1 | F37: Saurabh | G37: Mobile | H37: 7891 | I37: DISC10 | J37: 0.1 | K37: 9000 | L37: 45329 | M37: =IF(OR(I37="",ISNA(MATCH(I37,{"DISC10","DISC15","DISC20","DISC30"},0))),0,J37) -> 0.1
A38: S1036 | B38: Anjali Gupta | C38: C201 | D38: Data Analytics | E38: B3 | F38: Priya | G38: Web | H38: 12205 | I38: DISC15 | K38: 14000 | L38: 45322 | M38: =IF(OR(I38="",ISNA(MATCH(I38,{"DISC10","DISC15","DISC20","DISC30"},0))),0,J38) -> 0
A39: S1037 | B39: Manish Nair | C39: C202 | D39: Data Science | E39: B1 | F39: Amit | G39: Web | H39: 14487 | I39: DISC20 | J39: 0.2 | K39: 13000 | L39: 45296 | M39: =IF(OR(I39="",ISNA(MATCH(I39,{"DISC10","DISC15","DISC20","DISC30"},0))),0,J39) -> 0.2
A40: S1038 | B40: Kavita Shah | C40: C202 | D40: Data Science | E40: B2 | F40: Saurabh | G40: Tablet | H40: 12008 | I40: DISC15 | K40: 13000 | L40: 45330 | M40: =IF(OR(I40="",ISNA(MATCH(I40,{"DISC10","DISC15","DISC20","DISC30"},0))),0,J40) -> 0
A41: S1039 | B41: Aarav Joshi | C41: C201 | D41: Data Analytics | E41: B2 | F41: Amit | G41: Tablet | H41: 14315 | I41: DISC15 | K41: 14000 | L41: 45312 | M41: =IF(OR(I41="",ISNA(MATCH(I41,{"DISC10","DISC15","DISC20","DISC30"},0))),0,J41) -> 0
A42: S1040 | B42: Kunal Rao | C42: C202 | D42: Data Science | E42: B3 | F42: Amit | G42: Mobile | H42: 11977 | I42: DISC30 | J42: 0.3 | K42: 13000 | L42: 45317 | M42: =IF(OR(I42="",ISNA(MATCH(I42,{"DISC10","DISC15","DISC20","DISC30"},0))),0,J42) -> 0.3
A43: S1041 | B43: Karan Singh | C43: C203 | D43: Full Stack Dev | E43: B2 | F43: Priya | G43: Web | H43: 15038 | K43: 17000 | L43: 45331 | M43: =IF(OR(I43="",ISNA(MATCH(I43,{"DISC10","DISC15","DISC20","DISC30"},0))),0,J43) -> 0
A44: S1042 | B44: Kavita Shah | C44: C201 | D44: Data Analytics | E44: B3 | F44: Saurabh | G44: Tablet | H44: 13086 | I44: DISC20 | J44: 0.2 | K44: 14000 | L44: 45351 | M44: =IF(OR(I44="",ISNA(MATCH(I44,{"DISC10","DISC15","DISC20","DISC30"},0))),0,J44) -> 0.2
A45: S1043 | B45: Pooja Shah | C45: C202 | D45: Data Science | E45: B2 | F45: Priya | G45: Web | H45: 12794 | I45: DISC15 | K45: 13000 | L45: 45337 | M45: =IF(OR(I45="",ISNA(MATCH(I45,{"DISC10","DISC15","DISC20","DISC30"},0))),0,J45) -> 0
A46: S1044 | B46: Aditya Joshi | C46: C201 | D46: Data Analytics | E46: B3 | F46: Amit | G46: Mobile | H46: 15816 | I46: DISC10 | J46: 0.1 | K46: 14000 | L46: 45352 | M46: =IF(OR(I46="",ISNA(MATCH(I46,{"DISC10","DISC15","DISC20","DISC30"},0))),0,J46) -> 0.1
A47: S1045 | B47: Kunal Mehta | C47: C203 | D47: Full Stack Dev | E47: B1 | F47: Saurabh | G47: Tablet | H47: 17266 | I47: DISC20 | J47: 0.2 | K47: 17000 | L47: 45309 | M47: =IF(OR(I47="",ISNA(MATCH(I47,{"DISC10","DISC15","DISC20","DISC30"},0))),0,J47) -> 0.2
A48: S1046 | B48: Aditya Joshi | C48: C202 | D48: Data Science | E48: B3 | F48: Priya | G48: Web | H48: 13815 | I48: DISC30 | J48: 0.3 | K48: 13000 | L48: 45324 | M48: =IF(OR(I48="",ISNA(MATCH(I48,{"DISC10","DISC15","DISC20","DISC30"},0))),0,J48) -> 0.3
A49: S1047 | B49: Neha Rao | C49: C201 | D49: Data Analytics | E49: B1 | F49: Amit | G49: Mobile | H49: 15397 | I49: DISC30 | J49: 0.3 | K49: 14000 | L49: 45294 | M49: =IF(OR(I49="",ISNA(MATCH(I49,{"DISC10","DISC15","DISC20","DISC30"},0))),0,J49) -> 0.3
A50: S1048 | B50: Aarav Jain | C50: C202 | D50: Data Science | E50: B3 | F50: Priya | G50: Web | H50: 14036 | K50: 13000 | L50: 45327 | M50: =IF(OR(I50="",ISNA(MATCH(I50,{"DISC10","DISC15","DISC20","DISC30"},0))),0,J50) -> 0
A51: S1049 | B51: Anjali Verma | C51: C201 | D51: Data Analytics | E51: B1 | F51: Saurabh | G51: Tablet | H51: 15702 | I51: DISC20 | J51: 0.2 | K51: 14000 | L51: 45326 | M51: =IF(OR(I51="",ISNA(MATCH(I51,{"DISC10","DISC15","DISC20","DISC30"},0))),0,J51) -> 0.2
A52: S1050 | B52: Aarav Nair | C52: C203 | D52: Full Stack Dev | E52: B3 | F52: Amit | G52: Web | H52: 16760 | I52: DISC20 | J52: 0.2 | K52: 17000 | L52: 45294 | M52: =IF(OR(I52="",ISNA(MATCH(I52,{"DISC10","DISC15","DISC20","DISC30"},0))),0,J52) -> 0.2
A53: S1051 | B53: Aditya Jain | C53: C201 | D53: Data Analytics | E53: B2 | F53: Saurabh | G53: Tablet | H53: 13022 | I53: DISC10 | J53: 0.1 | K53: 14000 | L53: 45314 | M53: =IF(OR(I53="",ISNA(MATCH(I53,{"DISC10","DISC15","DISC20","DISC30"},0))),0,J53) -> 0.1
A54: S1052 | B54: Dev Gupta | C54: C204 | D54: UI UX Design | E54: B3 | F54: Amit | G54: Web | H54: 10791 | I54: DISC20 | J54: 0.2 | K54: 9000 | L54: 45347 | M54: =IF(OR(I54="",ISNA(MATCH(I54,{"DISC10","DISC15","DISC20","DISC30"},0))),0,J54) -> 0.2
A55: S1053 | B55: Karan Patel | C55: C202 | D55: Data Science | E55: B2 | F55: Saurabh | G55: Web | H55: 14016 | I55: DISC30 | J55: 0.3 | K55: 13000 | L55: 45342 | M55: =IF(OR(I55="",ISNA(MATCH(I55,{"DISC10","DISC15","DISC20","DISC30"},0))),0,J55) -> 0.3
A56: S1054 | B56: Kunal Verma | C56: C202 | D56: Data Science | E56: B2 | F56: Saurabh | G56: Tablet | H56: 11442 | K56: 13000 | L56: 45347 | M56: =IF(OR(I56="",ISNA(MATCH(I56,{"DISC10","DISC15","DISC20","DISC30"},0))),0,J56) -> 0
A57: S1055 | B57: Aarav Nair | C57: C204 | D57: UI UX Design | E57: B1 | F57: Saurabh | G57: Mobile | H57: 8432 | I57: DISC30 | J57: 0.3 | K57: 9000 | L57: 45344 | M57: =IF(OR(I57="",ISNA(MATCH(I57,{"DISC10","DISC15","DISC20","DISC30"},0))),0,J57) -> 0.3
A58: S1056 | B58: Dev Nair | C58: C202 | D58: Data Science | E58: B1 | F58: Saurabh | G58: Tablet | H58: 11791 | K58: 13000 | L58: 45313 | M58: =IF(OR(I58="",ISNA(MATCH(I58,{"DISC10","DISC15","DISC20","DISC30"},0))),0,J58) -> 0
A59: S1057 | B59: Aditya Nair | C59: C201 | D59: Data Analytics | E59: B2 | F59: Priya | G59: Tablet | H59: 14086 | K59: 14000 | L59: 45335 | M59: =IF(OR(I59="",ISNA(MATCH(I59,{"DISC10","DISC15","DISC20","DISC30"},0))),0,J59) -> 0
A60: S1058 | B60: Meera Gupta | C60: C203 | D60: Full Stack Dev | E60: B1 | F60: Saurabh | G60: Mobile | H60: 15731 | I60: DISC15 | K60: 17000 | L60: 45308 | M60: =IF(OR(I60="",ISNA(MATCH(I60,{"DISC10","DISC15","DISC20","DISC30"},0))),0,J60) -> 0
A61: S1059 | B61: Aarav Shah | C61: C204 | D61: UI UX Design | E61: B2 | F61: Amit | G61: Mobile | H61: 8787 | I61: DISC15 | K61: 9000 | L61: 45324 | M61: =IF(OR(I61="",ISNA(MATCH(I61,{"DISC10","DISC15","DISC20","DISC30"},0))),0,J61) -> 0
A62: S1060 | B62: Riya Verma | C62: C202 | D62: Data Science | E62: B2 | F62: Saurabh | G62: Tablet | H62: 12786 | I62: DISC10 | J62: 0.1 | K62: 13000 | L62: 45325 | M62: =IF(OR(I62="",ISNA(MATCH(I62,{"DISC10","DISC15","DISC20","DISC30"},0))),0,J62) -> 0.1
A63: S1061 | B63: Kunal Patel | C63: C202 | D63: Data Science | E63: B2 | F63: Priya | G63: Web | H63: 14886 | I63: DISC30 | J63: 0.3 | K63: 13000 | L63: 45331 | M63: =IF(OR(I63="",ISNA(MATCH(I63,{"DISC10","DISC15","DISC20","DISC30"},0))),0,J63) -> 0.3
A64: S1062 | B64: Pooja Singh | C64: C201 | D64: Data Analytics | E64: B3 | F64: Priya | G64: Tablet | H64: 13266 | K64: 14000 | L64: 45312 | M64: =IF(OR(I64="",ISNA(MATCH(I64,{"DISC10","DISC15","DISC20","DISC30"},0))),0,J64) -> 0
A65: S1063 | B65: Rahul Desai | C65: C203 | D65: Full Stack Dev | E65: B3 | F65: Saurabh | G65: Web | H65: 16722 | K65: 17000 | L65: 45335 | M65: =IF(OR(I65="",ISNA(MATCH(I65,{"DISC10","DISC15","DISC20","DISC30"},0))),0,J65) -> 0
A66: S1064 | B66: Anjali Mehta | C66: C203 | D66: Full Stack Dev | E66: B2 | F66: Amit | G66: Web | H66: 16244 | I66: DISC30 | J66: 0.3 | K66: 17000 | L66: 45305 | M66: =IF(OR(I66="",ISNA(MATCH(I66,{"DISC10","DISC15","DISC20","DISC30"},0))),0,J66) -> 0.3
A67: S1065 | B67: Rahul Patel | C67: C203 | D67: Full Stack Dev | E67: B2 | F67: Priya | G67: Mobile | H67: 17767 | I67: DISC20 | J67: 0.2 | K67: 17000 | L67: 45324 | M67: =IF(OR(I67="",ISNA(MATCH(I67,{"DISC10","DISC15","DISC20","DISC30"},0))),0,J67) -> 0.2
A68: S1066 | B68: Neha Patel | C68: C202 | D68: Data Science | E68: B3 | F68: Saurabh | G68: Mobile | H68: 13111 | I68: DISC15 | K68: 13000 | L68: 45313 | M68: =IF(OR(I68="",ISNA(MATCH(I68,{"DISC10","DISC15","DISC20","DISC30"},0))),0,J68) -> 0
A69: S1067 | B69: Riya Nair | C69: C202 | D69: Data Science | E69: B3 | F69: Priya | G69: Web | H69: 14303 | I69: DISC20 | J69: 0.2 | K69: 13000 | L69: 45301 | M69: =IF(OR(I69="",ISNA(MATCH(I69,{"DISC10","DISC15","DISC20","DISC30"},0))),0,J69) -> 0.2
A70: S1068 | B70: Aarav Kulkarni | C70: C202 | D70: Data Science | E70: B2 | F70: Amit | G70: Web | H70: 12865 | K70: 13000 | L70: 45348 | M70: =IF(OR(I70="",ISNA(MATCH(I70,{"DISC10","DISC15","DISC20","DISC30"},0))),0,J70) -> 0
A71: S1069 | B71: Rohit Joshi | C71: C202 | D71: Data Science | E71: B3 | F71: Amit | G71: Mobile | H71: 13024 | K71: 13000 | L71: 45307 | M71: =IF(OR(I71="",ISNA(MATCH(I71,{"DISC10","DISC15","DISC20","DISC30"},0))),0,J71) -> 0
A72: S1070 | B72: Karan Singh | C72: C201 | D72: Data Analytics | E72: B1 | F72: Priya | G72: Web | H72: 12720 | I72: DISC15 | K72: 14000 | L72: 45321 | M72: =IF(OR(I72="",ISNA(MATCH(I72,{"DISC10","DISC15","DISC20","DISC30"},0))),0,J72) -> 0
A73: S1071 | B73: Aarav Gupta | C73: C202 | D73: Data Science | E73: B1 | F73: Priya | G73: Web | H73: 14282 | K73: 13000 | L73: 45334 | M73: =IF(OR(I73="",ISNA(MATCH(I73,{"DISC10","DISC15","DISC20","DISC30"},0))),0,J73) -> 0
A74: S1072 | B74: Manish Gupta | C74: C203 | D74: Full Stack Dev | E74: B2 | F74: Amit | G74: Tablet | H74: 18653 | I74: DISC15 | K74: 17000 | L74: 45319 | M74: =IF(OR(I74="",ISNA(MATCH(I74,{"DISC10","DISC15","DISC20","DISC30"},0))),0,J74) -> 0
A75: S1073 | B75: Meera Gupta | C75: C204 | D75: UI UX Design | E75: B1 | F75: Amit | G75: Mobile | H75: 8843 | I75: DISC30 | J75: 0.3 | K75: 9000 | L75: 45340 | M75: =IF(OR(I75="",ISNA(MATCH(I75,{"DISC10","DISC15","DISC20","DISC30"},0))),0,J75) -> 0.3
A76: S1074 | B76: Sneha Nair | C76: C203 | D76: Full Stack Dev | E76: B3 | F76: Priya | G76: Tablet | H76: 15979 | I76: DISC30 | J76: 0.3 | K76: 17000 | L76: 45320 | M76: =IF(OR(I76="",ISNA(MATCH(I76,{"DISC10","DISC15","DISC20","DISC30"},0))),0,J76) -> 0.3
A77: S1075 | B77: Riya Desai | C77: C203 | D77: Full Stack Dev | E77: B1 | F77: Priya | G77: Mobile | H77: 16309 | I77: DISC15 | K77: 17000 | L77: 45297 | M77: =IF(OR(I77="",ISNA(MATCH(I77,{"DISC10","DISC15","DISC20","DISC30"},0))),0,J77) -> 0
A78: S1076 | B78: Karan Mehta | C78: C202 | D78: Data Science | E78: B2 | F78: Amit | G78: Web | H78: 13893 | I78: DISC20 | J78: 0.2 | K78: 13000 | L78: 45296 | M78: =IF(OR(I78="",ISNA(MATCH(I78,{"DISC10","DISC15","DISC20","DISC30"},0))),0,J78) -> 0.2
A79: S1077 | B79: Rahul Verma | C79: C203 | D79: Full Stack Dev | E79: B3 | F79: Priya | G79: Mobile | H79: 15255 | I79: DISC20 | J79: 0.2 | K79: 17000 | L79: 45345 | M79: =IF(OR(I79="",ISNA(MATCH(I79,{"DISC10","DISC15","DISC20","DISC30"},0))),0,J79) -> 0.2
A80: S1078 | B80: Rahul Verma | C80: C201 | D80: Data Analytics | E80: B3 | F80: Priya | G80: Mobile | H80: 12024 | I80: DISC30 | J80: 0.3 | K80: 14000 | L80: 45311 | M80: =IF(OR(I80="",ISNA(MATCH(I80,{"DISC10","DISC15","DISC20","DISC30"},0))),0,J80) -> 0.3
A81: S1079 | B81: Dev Verma | C81: C204 | D81: UI UX Design | E81: B3 | F81: Amit | G81: Tablet | H81: 9236 | I81: DISC15 | K81: 9000 | L81: 45349 | M81: =IF(OR(I81="",ISNA(MATCH(I81,{"DISC10","DISC15","DISC20","DISC30"},0))),0,J81) -> 0
A82: S1080 | B82: Sneha Iyer | C82: C202 | D82: Data Science | E82: B2 | F82: Priya | G82: Mobile | H82: 11118 | K82: 13000 | L82: 45313 | M82: =IF(OR(I82="",ISNA(MATCH(I82,{"DISC10","DISC15","DISC20","DISC30"},0))),0,J82) -> 0
A83: S1081 | B83: Rohit Singh | C83: C204 | D83: UI UX Design | E83: B3 | F83: Saurabh | G83: Mobile | H83: 10766 | I83: DISC20 | J83: 0.2 | K83: 9000 | L83: 45331 | M83: =IF(OR(I83="",ISNA(MATCH(I83,{"DISC10","DISC15","DISC20","DISC30"},0))),0,J83) -> 0.2
A84: S1082 | B84: Manish Kulkarni | C84: C204 | D84: UI UX Design | E84: B3 | F84: Amit | G84: Tablet | H84: 7111 | I84: DISC10 | J84: 0.1 | K84: 9000 | L84: 45333 | M84: =IF(OR(I84="",ISNA(MATCH(I84,{"DISC10","DISC15","DISC20","DISC30"},0))),0,J84) -> 0.1
A85: S1083 | B85: Rahul Mehta | C85: C204 | D85: UI UX Design | E85: B1 | F85: Saurabh | G85: Mobile | H85: 8552 | I85: DISC30 | J85: 0.3 | K85: 9000 | L85: 45305 | M85: =IF(OR(I85="",ISNA(MATCH(I85,{"DISC10","DISC15","DISC20","DISC30"},0))),0,J85) -> 0.3
A86: S1084 | B86: Neha Jain | C86: C203 | D86: Full Stack Dev | E86: B2 | F86: Priya | G86: Mobile | H86: 16033 | I86: DISC10 | J86: 0.1 | K86: 17000 | L86: 45322 | M86: =IF(OR(I86="",ISNA(MATCH(I86,{"DISC10","DISC15","DISC20","DISC30"},0))),0,J86) -> 0.1
A87: S1085 | B87: Aarav Desai | C87: C201 | D87: Data Analytics | E87: B2 | F87: Saurabh | G87: Tablet | H87: 12281 | I87: DISC10 | J87: 0.1 | K87: 14000 | L87: 45340 | M87: =IF(OR(I87="",ISNA(MATCH(I87,{"DISC10","DISC15","DISC20","DISC30"},0))),0,J87) -> 0.1
A88: S1086 | B88: Aarav Patil | C88: C202 | D88: Data Science | E88: B1 | F88: Amit | G88: Web | H88: 11977 | I88: DISC20 | J88: 0.2 | K88: 13000 | L88: 45322 | M88: =IF(OR(I88="",ISNA(MATCH(I88,{"DISC10","DISC15","DISC20","DISC30"},0))),0,J88) -> 0.2
A89: S1087 | B89: Rohit Shah | C89: C202 | D89: Data Science | E89: B2 | F89: Amit | G89: Mobile | H89: 14141 | I89: DISC30 | J89: 0.3 | K89: 13000 | L89: 45302 | M89: =IF(OR(I89="",ISNA(MATCH(I89,{"DISC10","DISC15","DISC20","DISC30"},0))),0,J89) -> 0.3
A90: S1088 | B90: Kavita Joshi | C90: C201 | D90: Data Analytics | E90: B1 | F90: Priya | G90: Web | H90: 14370 | I90: DISC10 | J90: 0.1 | K90: 14000 | L90: 45351 | M90: =IF(OR(I90="",ISNA(MATCH(I90,{"DISC10","DISC15","DISC20","DISC30"},0))),0,J90) -> 0.1
A91: S1089 | B91: Aditya Joshi | C91: C204 | D91: UI UX Design | E91: B2 | F91: Amit | G91: Web | H91: 7311 | I91: DISC15 | K91: 9000 | L91: 45336 | M91: =IF(OR(I91="",ISNA(MATCH(I91,{"DISC10","DISC15","DISC20","DISC30"},0))),0,J91) -> 0
A92: S1090 | B92: Meera Singh | C92: C202 | D92: Data Science | E92: B1 | F92: Amit | G92: Mobile | H92: 14482 | I92: DISC15 | K92: 13000 | L92: 45343 | M92: =IF(OR(I92="",ISNA(MATCH(I92,{"DISC10","DISC15","DISC20","DISC30"},0))),0,J92) -> 0
A93: S1091 | B93: Riya Patel | C93: C201 | D93: Data Analytics | E93: B2 | F93: Amit | G93: Mobile | H93: 14709 | I93: DISC30 | J93: 0.3 | K93: 14000 | L93: 45296 | M93: =IF(OR(I93="",ISNA(MATCH(I93,{"DISC10","DISC15","DISC20","DISC30"},0))),0,J93) -> 0.3
A94: S1092 | B94: Manish Singh | C94: C203 | D94: Full Stack Dev | E94: B1 | F94: Priya | G94: Mobile | H94: 15432 | K94: 17000 | L94: 45315 | M94: =IF(OR(I94="",ISNA(MATCH(I94,{"DISC10","DISC15","DISC20","DISC30"},0))),0,J94) -> 0
A95: S1093 | B95: Rohit Nair | C95: C204 | D95: UI UX Design | E95: B3 | F95: Saurabh | G95: Mobile | H95: 7721 | I95: DISC15 | K95: 9000 | L95: 45333 | M95: =IF(OR(I95="",ISNA(MATCH(I95,{"DISC10","DISC15","DISC20","DISC30"},0))),0,J95) -> 0
A96: S1094 | B96: Aditya Joshi | C96: C204 | D96: UI UX Design | E96: B2 | F96: Priya | G96: Tablet | H96: 9426 | I96: DISC30 | J96: 0.3 | K96: 9000 | L96: 45312 | M96: =IF(OR(I96="",ISNA(MATCH(I96,{"DISC10","DISC15","DISC20","DISC30"},0))),0,J96) -> 0.3
A97: S1095 | B97: Meera Patil | C97: C201 | D97: Data Analytics | E97: B2 | F97: Priya | G97: Web | H97: 15073 | K97: 14000 | L97: 45328 | M97: =IF(OR(I97="",ISNA(MATCH(I97,{"DISC10","DISC15","DISC20","DISC30"},0))),0,J97) -> 0
A98: S1096 | B98: Kavita Singh | C98: C204 | D98: UI UX Design | E98: B2 | F98: Saurabh | G98: Mobile | H98: 10485 | I98: DISC30 | J98: 0.3 | K98: 9000 | L98: 45303 | M98: =IF(OR(I98="",ISNA(MATCH(I98,{"DISC10","DISC15","DISC20","DISC30"},0))),0,J98) -> 0.3
A99: S1097 | B99: Neha Patil | C99: C203 | D99: Full Stack Dev | E99: B2 | F99: Priya | G99: Mobile | H99: 18605 | I99: DISC15 | K99: 17000 | L99: 45336 | M99: =IF(OR(I99="",ISNA(MATCH(I99,{"DISC10","DISC15","DISC20","DISC30"},0))),0,J99) -> 0
A100: S1098 | B100: Kunal Rao | C100: C201 | D100: Data Analytics | E100: B3 | F100: Saurabh | G100: Web | H100: 12988 | K100: 14000 | L100: 45323 | M100: =IF(OR(I100="",ISNA(MATCH(I100,{"DISC10","DISC15","DISC20","DISC30"},0))),0,J100) -> 0
...

Sheet Q7
A1: STUDENT_NAME | B1: PLATFORM
A2: Rohit Shah | B2: =INDEX(Dataset!$G$1:$G$1001,MATCH('Q7'!A2,Dataset!$B$1:$B$1001,0)) -> Web
A3: Riya Verma | B3: =INDEX(Dataset!$G$1:$G$1001,MATCH('Q7'!A3,Dataset!$B$1:$B$1001,0)) -> Tablet

Sheet Q8
A1: StudentID | B1: StudentName | C1: CourseID | D1: CourseName | E1: BatchID | F1: MentorName | G1: Platform | H1: PaymentAmount | I1: DiscountCode | J1: DiscountPercent | K1: TargetRevenue | L1: PaymentDate | M1: Total Net Revenue(AfterDiscount)
A2: S1000 | B2: Rohit Shah | C2: C201 | D2: Data Analytics | E2: B3 | F2: Priya | G2: Web | H2: 12914 | I2: DISC20 | J2: 0.2 | K2: 14000 | L2: 45339 | M2: {=SUM($H$2:$H$1001*(1-$J$2:$J$1001))} -> 11745723
A3: S1001 | B3: Riya Singh | C3: C201 | D3: Data Analytics | E3: B3 | F3: Priya | G3: Web | H3: 12122 | I3: DISC10 | J3: 0.1 | K3: 14000 | L3: 45305
A4: S1002 | B4: Sneha Gupta | C4: C201 | D4: Data Analytics | E4: B3 | F4: Saurabh | G4: Tablet | H4: 14661 | I4: DISC15 | K4: 14000 | L4: 45318
A5: S1003 | B5: Sneha Iyer | C5: C203 | D5: Full Stack Dev | E5: B1 | F5: Saurabh | G5: Tablet | H5: 16731 | I5: DISC30 | J5: 0.3 | K5: 17000 | L5: 45309 | M5: Total Revenue(Before Discount)
A6: S1004 | B6: Karan Patil | C6: C203 | D6: Full Stack Dev | E6: B1 | F6: Saurabh | G6: Mobile | H6: 15396 | I6: DISC30 | J6: 0.3 | K6: 17000 | L6: 45346 | M6: =SUM($H$2:$H$1001) -> 13395293
A7: S1005 | B7: Pooja Joshi | C7: C203 | D7: Full Stack Dev | E7: B1 | F7: Amit | G7: Mobile | H7: 17196 | I7: DISC10 | J7: 0.1 | K7: 17000 | L7: 45351
A8: S1006 | B8: Rahul Shah | C8: C203 | D8: Full Stack Dev | E8: B3 | F8: Amit | G8: Mobile | H8: 17364 | I8: DISC20 | J8: 0.2 | K8: 17000 | L8: 45337 | M8: Total Discount
A9: S1007 | B9: Riya Kulkarni | C9: C202 | D9: Data Science | E9: B2 | F9: Saurabh | G9: Web | H9: 14549 | I9: DISC10 | J9: 0.1 | K9: 13000 | L9: 45316 | M9: =M6-M2 -> 1649570.2
A10: S1008 | B10: Aditya Iyer | C10: C203 | D10: Full Stack Dev | E10: B1 | F10: Priya | G10: Mobile | H10: 15858 | I10: DISC30 | J10: 0.3 | K10: 17000 | L10: 45336
A11: S1009 | B11: Kunal Singh | C11: C201 | D11: Data Analytics | E11: B3 | F11: Amit | G11: Web | H11: 14187 | I11: DISC20 | J11: 0.2 | K11: 14000 | L11: 45302
A12: S1010 | B12: Neha Verma | C12: C203 | D12: Full Stack Dev | E12: B3 | F12: Amit | G12: Tablet | H12: 15899 | I12: DISC30 | J12: 0.3 | K12: 17000 | L12: 45345
A13: S1011 | B13: Dev Patel | C13: C201 | D13: Data Analytics | E13: B1 | F13: Saurabh | G13: Mobile | H13: 13643 | I13: DISC30 | J13: 0.3 | K13: 14000 | L13: 45296
A14: S1012 | B14: Sneha Joshi | C14: C203 | D14: Full Stack Dev | E14: B1 | F14: Amit | G14: Mobile | H14: 16620 | K14: 17000 | L14: 45301
A15: S1013 | B15: Aditya Mehta | C15: C202 | D15: Data Science | E15: B3 | F15: Amit | G15: Tablet | H15: 12076 | I15: DISC15 | K15: 13000 | L15: 45319
A16: S1014 | B16: Kunal Joshi | C16: C204 | D16: UI UX Design | E16: B2 | F16: Saurabh | G16: Web | H16: 9087 | K16: 9000 | L16: 45297
A17: S1015 | B17: Dev Kulkarni | C17: C201 | D17: Data Analytics | E17: B1 | F17: Amit | G17: Web | H17: 15244 | K17: 14000 | L17: 45330
A18: S1016 | B18: Riya Verma | C18: C204 | D18: UI UX Design | E18: B3 | F18: Priya | G18: Tablet | H18: 8029 | I18: DISC15 | K18: 9000 | L18: 45347
A19: S1017 | B19: Aarav Singh | C19: C201 | D19: Data Analytics | E19: B3 | F19: Amit | G19: Mobile | H19: 15148 | I19: DISC30 | J19: 0.3 | K19: 14000 | L19: 45299
A20: S1018 | B20: Aditya Verma | C20: C202 | D20: Data Science | E20: B2 | F20: Saurabh | G20: Tablet | H20: 14587 | I20: DISC30 | J20: 0.3 | K20: 13000 | L20: 45324
A21: S1019 | B21: Dev Mehta | C21: C201 | D21: Data Analytics | E21: B3 | F21: Priya | G21: Tablet | H21: 14079 | I21: DISC15 | K21: 14000 | L21: 45304
A22: S1020 | B22: Karan Jain | C22: C202 | D22: Data Science | E22: B3 | F22: Amit | G22: Web | H22: 13453 | I22: DISC30 | J22: 0.3 | K22: 13000 | L22: 45323
A23: S1021 | B23: Aarav Shah | C23: C203 | D23: Full Stack Dev | E23: B2 | F23: Saurabh | G23: Web | H23: 15986 | I23: DISC15 | K23: 17000 | L23: 45352
A24: S1022 | B24: Riya Shah | C24: C204 | D24: UI UX Design | E24: B1 | F24: Amit | G24: Web | H24: 7525 | K24: 9000 | L24: 45352
A25: S1023 | B25: Manish Mehta | C25: C203 | D25: Full Stack Dev | E25: B3 | F25: Amit | G25: Mobile | H25: 18950 | I25: DISC20 | J25: 0.2 | K25: 17000 | L25: 45351
A26: S1024 | B26: Manish Patel | C26: C202 | D26: Data Science | E26: B3 | F26: Priya | G26: Mobile | H26: 13751 | I26: DISC30 | J26: 0.3 | K26: 13000 | L26: 45320
A27: S1025 | B27: Kunal Gupta | C27: C204 | D27: UI UX Design | E27: B1 | F27: Saurabh | G27: Web | H27: 7262 | I27: DISC30 | J27: 0.3 | K27: 9000 | L27: 45293
A28: S1026 | B28: Kavita Gupta | C28: C202 | D28: Data Science | E28: B3 | F28: Saurabh | G28: Web | H28: 11290 | I28: DISC10 | J28: 0.1 | K28: 13000 | L28: 45306
A29: S1027 | B29: Riya Kulkarni | C29: C203 | D29: Full Stack Dev | E29: B1 | F29: Amit | G29: Web | H29: 16140 | K29: 17000 | L29: 45305
A30: S1028 | B30: Manish Mehta | C30: C204 | D30: UI UX Design | E30: B1 | F30: Priya | G30: Mobile | H30: 7779 | I30: DISC10 | J30: 0.1 | K30: 9000 | L30: 45298
A31: S1029 | B31: Rohit Verma | C31: C203 | D31: Full Stack Dev | E31: B2 | F31: Priya | G31: Mobile | H31: 18538 | I31: DISC10 | J31: 0.1 | K31: 17000 | L31: 45335
A32: S1030 | B32: Rohit Singh | C32: C201 | D32: Data Analytics | E32: B1 | F32: Priya | G32: Tablet | H32: 13389 | I32: DISC10 | J32: 0.1 | K32: 14000 | L32: 45307
A33: S1031 | B33: Sneha Patil | C33: C204 | D33: UI UX Design | E33: B1 | F33: Priya | G33: Web | H33: 8140 | K33: 9000 | L33: 45307
A34: S1032 | B34: Meera Shah | C34: C204 | D34: UI UX Design | E34: B3 | F34: Saurabh | G34: Web | H34: 9671 | I34: DISC15 | K34: 9000 | L34: 45345
A35: S1033 | B35: Aarav Shah | C35: C202 | D35: Data Science | E35: B1 | F35: Priya | G35: Mobile | H35: 12971 | I35: DISC20 | J35: 0.2 | K35: 13000 | L35: 45347
A36: S1034 | B36: Rahul Kulkarni | C36: C202 | D36: Data Science | E36: B2 | F36: Saurabh | G36: Mobile | H36: 12086 | K36: 13000 | L36: 45310
A37: S1035 | B37: Rahul Desai | C37: C204 | D37: UI UX Design | E37: B1 | F37: Saurabh | G37: Mobile | H37: 7891 | I37: DISC10 | J37: 0.1 | K37: 9000 | L37: 45329
A38: S1036 | B38: Anjali Gupta | C38: C201 | D38: Data Analytics | E38: B3 | F38: Priya | G38: Web | H38: 12205 | I38: DISC15 | K38: 14000 | L38: 45322
A39: S1037 | B39: Manish Nair | C39: C202 | D39: Data Science | E39: B1 | F39: Amit | G39: Web | H39: 14487 | I39: DISC20 | J39: 0.2 | K39: 13000 | L39: 45296
A40: S1038 | B40: Kavita Shah | C40: C202 | D40: Data Science | E40: B2 | F40: Saurabh | G40: Tablet | H40: 12008 | I40: DISC15 | K40: 13000 | L40: 45330
A41: S1039 | B41: Aarav Joshi | C41: C201 | D41: Data Analytics | E41: B2 | F41: Amit | G41: Tablet | H41: 14315 | I41: DISC15 | K41: 14000 | L41: 45312
A42: S1040 | B42: Kunal Rao | C42: C202 | D42: Data Science | E42: B3 | F42: Amit | G42: Mobile | H42: 11977 | I42: DISC30 | J42: 0.3 | K42: 13000 | L42: 45317
A43: S1041 | B43: Karan Singh | C43: C203 | D43: Full Stack Dev | E43: B2 | F43: Priya | G43: Web | H43: 15038 | K43: 17000 | L43: 45331
A44: S1042 | B44: Kavita Shah | C44: C201 | D44: Data Analytics | E44: B3 | F44: Saurabh | G44: Tablet | H44: 13086 | I44: DISC20 | J44: 0.2 | K44: 14000 | L44: 45351
A45: S1043 | B45: Pooja Shah | C45: C202 | D45: Data Science | E45: B2 | F45: Priya | G45: Web | H45: 12794 | I45: DISC15 | K45: 13000 | L45: 45337
A46: S1044 | B46: Aditya Joshi | C46: C201 | D46: Data Analytics | E46: B3 | F46: Amit | G46: Mobile | H46: 15816 | I46: DISC10 | J46: 0.1 | K46: 14000 | L46: 45352
A47: S1045 | B47: Kunal Mehta | C47: C203 | D47: Full Stack Dev | E47: B1 | F47: Saurabh | G47: Tablet | H47: 17266 | I47: DISC20 | J47: 0.2 | K47: 17000 | L47: 45309
A48: S1046 | B48: Aditya Joshi | C48: C202 | D48: Data Science | E48: B3 | F48: Priya | G48: Web | H48: 13815 | I48: DISC30 | J48: 0.3 | K48: 13000 | L48: 45324
A49: S1047 | B49: Neha Rao | C49: C201 | D49: Data Analytics | E49: B1 | F49: Amit | G49: Mobile | H49: 15397 | I49: DISC30 | J49: 0.3 | K49: 14000 | L49: 45294
A50: S1048 | B50: Aarav Jain | C50: C202 | D50: Data Science | E50: B3 | F50: Priya | G50: Web | H50: 14036 | K50: 13000 | L50: 45327
A51: S1049 | B51: Anjali Verma | C51: C201 | D51: Data Analytics | E51: B1 | F51: Saurabh | G51: Tablet | H51: 15702 | I51: DISC20 | J51: 0.2 | K51: 14000 | L51: 45326
A52: S1050 | B52: Aarav Nair | C52: C203 | D52: Full Stack Dev | E52: B3 | F52: Amit | G52: Web | H52: 16760 | I52: DISC20 | J52: 0.2 | K52: 17000 | L52: 45294
A53: S1051 | B53: Aditya Jain | C53: C201 | D53: Data Analytics | E53: B2 | F53: Saurabh | G53: Tablet | H53: 13022 | I53: DISC10 | J53: 0.1 | K53: 14000 | L53: 45314
A54: S1052 | B54: Dev Gupta | C54: C204 | D54: UI UX Design | E54: B3 | F54: Amit | G54: Web | H54: 10791 | I54: DISC20 | J54: 0.2 | K54: 9000 | L54: 45347
A55: S1053 | B55: Karan Patel | C55: C202 | D55: Data Science | E55: B2 | F55: Saurabh | G55: Web | H55: 14016 | I55: DISC30 | J55: 0.3 | K55: 13000 | L55: 45342
A56: S1054 | B56: Kunal Verma | C56: C202 | D56: Data Science | E56: B2 | F56: Saurabh | G56: Tablet | H56: 11442 | K56: 13000 | L56: 45347
A57: S1055 | B57: Aarav Nair | C57: C204 | D57: UI UX Design | E57: B1 | F57: Saurabh | G57: Mobile | H57: 8432 | I57: DISC30 | J57: 0.3 | K57: 9000 | L57: 45344
A58: S1056 | B58: Dev Nair | C58: C202 | D58: Data Science | E58: B1 | F58: Saurabh | G58: Tablet | H58: 11791 | K58: 13000 | L58: 45313
A59: S1057 | B59: Aditya Nair | C59: C201 | D59: Data Analytics | E59: B2 | F59: Priya | G59: Tablet | H59: 14086 | K59: 14000 | L59: 45335
A60: S1058 | B60: Meera Gupta | C60: C203 | D60: Full Stack Dev | E60: B1 | F60: Saurabh | G60: Mobile | H60: 15731 | I60: DISC15 | K60: 17000 | L60: 45308
A61: S1059 | B61: Aarav Shah | C61: C204 | D61: UI UX Design | E61: B2 | F61: Amit | G61: Mobile | H61: 8787 | I61: DISC15 | K61: 9000 | L61: 45324
A62: S1060 | B62: Riya Verma | C62: C202 | D62: Data Science | E62: B2 | F62: Saurabh | G62: Tablet | H62: 12786 | I62: DISC10 | J62: 0.1 | K62: 13000 | L62: 45325
A63: S1061 | B63: Kunal Patel | C63: C202 | D63: Data Science | E63: B2 | F63: Priya | G63: Web | H63: 14886 | I63: DISC30 | J63: 0.3 | K63: 13000 | L63: 45331
A64: S1062 | B64: Pooja Singh | C64: C201 | D64: Data Analytics | E64: B3 | F64: Priya | G64: Tablet | H64: 13266 | K64: 14000 | L64: 45312
A65: S1063 | B65: Rahul Desai | C65: C203 | D65: Full Stack Dev | E65: B3 | F65: Saurabh | G65: Web | H65: 16722 | K65: 17000 | L65: 45335
A66: S1064 | B66: Anjali Mehta | C66: C203 | D66: Full Stack Dev | E66: B2 | F66: Amit | G66: Web | H66: 16244 | I66: DISC30 | J66: 0.3 | K66: 17000 | L66: 45305
A67: S1065 | B67: Rahul Patel | C67: C203 | D67: Full Stack Dev | E67: B2 | F67: Priya | G67: Mobile | H67: 17767 | I67: DISC20 | J67: 0.2 | K67: 17000 | L67: 45324
A68: S1066 | B68: Neha Patel | C68: C202 | D68: Data Science | E68: B3 | F68: Saurabh | G68: Mobile | H68: 13111 | I68: DISC15 | K68: 13000 | L68: 45313
A69: S1067 | B69: Riya Nair | C69: C202 | D69: Data Science | E69: B3 | F69: Priya | G69: Web | H69: 14303 | I69: DISC20 | J69: 0.2 | K69: 13000 | L69: 45301
A70: S1068 | B70: Aarav Kulkarni | C70: C202 | D70: Data Science | E70: B2 | F70: Amit | G70: Web | H70: 12865 | K70: 13000 | L70: 45348
A71: S1069 | B71: Rohit Joshi | C71: C202 | D71: Data Science | E71: B3 | F71: Amit | G71: Mobile | H71: 13024 | K71: 13000 | L71: 45307
A72: S1070 | B72: Karan Singh | C72: C201 | D72: Data Analytics | E72: B1 | F72: Priya | G72: Web | H72: 12720 | I72: DISC15 | K72: 14000 | L72: 45321
A73: S1071 | B73: Aarav Gupta | C73: C202 | D73: Data Science | E73: B1 | F73: Priya | G73: Web | H73: 14282 | K73: 13000 | L73: 45334
A74: S1072 | B74: Manish Gupta | C74: C203 | D74: Full Stack Dev | E74: B2 | F74: Amit | G74: Tablet | H74: 18653 | I74: DISC15 | K74: 17000 | L74: 45319
A75: S1073 | B75: Meera Gupta | C75: C204 | D75: UI UX Design | E75: B1 | F75: Amit | G75: Mobile | H75: 8843 | I75: DISC30 | J75: 0.3 | K75: 9000 | L75: 45340
A76: S1074 | B76: Sneha Nair | C76: C203 | D76: Full Stack Dev | E76: B3 | F76: Priya | G76: Tablet | H76: 15979 | I76: DISC30 | J76: 0.3 | K76: 17000 | L76: 45320
A77: S1075 | B77: Riya Desai | C77: C203 | D77: Full Stack Dev | E77: B1 | F77: Priya | G77: Mobile | H77: 16309 | I77: DISC15 | K77: 17000 | L77: 45297
A78: S1076 | B78: Karan Mehta | C78: C202 | D78: Data Science | E78: B2 | F78: Amit | G78: Web | H78: 13893 | I78: DISC20 | J78: 0.2 | K78: 13000 | L78: 45296
A79: S1077 | B79: Rahul Verma | C79: C203 | D79: Full Stack Dev | E79: B3 | F79: Priya | G79: Mobile | H79: 15255 | I79: DISC20 | J79: 0.2 | K79: 17000 | L79: 45345
A80: S1078 | B80: Rahul Verma | C80: C201 | D80: Data Analytics | E80: B3 | F80: Priya | G80: Mobile | H80: 12024 | I80: DISC30 | J80: 0.3 | K80: 14000 | L80: 45311
A81: S1079 | B81: Dev Verma | C81: C204 | D81: UI UX Design | E81: B3 | F81: Amit | G81: Tablet | H81: 9236 | I81: DISC15 | K81: 9000 | L81: 45349
A82: S1080 | B82: Sneha Iyer | C82: C202 | D82: Data Science | E82: B2 | F82: Priya | G82: Mobile | H82: 11118 | K82: 13000 | L82: 45313
A83: S1081 | B83: Rohit Singh | C83: C204 | D83: UI UX Design | E83: B3 | F83: Saurabh | G83: Mobile | H83: 10766 | I83: DISC20 | J83: 0.2 | K83: 9000 | L83: 45331
A84: S1082 | B84: Manish Kulkarni | C84: C204 | D84: UI UX Design | E84: B3 | F84: Amit | G84: Tablet | H84: 7111 | I84: DISC10 | J84: 0.1 | K84: 9000 | L84: 45333
A85: S1083 | B85: Rahul Mehta | C85: C204 | D85: UI UX Design | E85: B1 | F85: Saurabh | G85: Mobile | H85: 8552 | I85: DISC30 | J85: 0.3 | K85: 9000 | L85: 45305
A86: S1084 | B86: Neha Jain | C86: C203 | D86: Full Stack Dev | E86: B2 | F86: Priya | G86: Mobile | H86: 16033 | I86: DISC10 | J86: 0.1 | K86: 17000 | L86: 45322
A87: S1085 | B87: Aarav Desai | C87: C201 | D87: Data Analytics | E87: B2 | F87: Saurabh | G87: Tablet | H87: 12281 | I87: DISC10 | J87: 0.1 | K87: 14000 | L87: 45340
A88: S1086 | B88: Aarav Patil | C88: C202 | D88: Data Science | E88: B1 | F88: Amit | G88: Web | H88: 11977 | I88: DISC20 | J88: 0.2 | K88: 13000 | L88: 45322
A89: S1087 | B89: Rohit Shah | C89: C202 | D89: Data Science | E89: B2 | F89: Amit | G89: Mobile | H89: 14141 | I89: DISC30 | J89: 0.3 | K89: 13000 | L89: 45302
A90: S1088 | B90: Kavita Joshi | C90: C201 | D90: Data Analytics | E90: B1 | F90: Priya | G90: Web | H90: 14370 | I90: DISC10 | J90: 0.1 | K90: 14000 | L90: 45351
A91: S1089 | B91: Aditya Joshi | C91: C204 | D91: UI UX Design | E91: B2 | F91: Amit | G91: Web | H91: 7311 | I91: DISC15 | K91: 9000 | L91: 45336
A92: S1090 | B92: Meera Singh | C92: C202 | D92: Data Science | E92: B1 | F92: Amit | G92: Mobile | H92: 14482 | I92: DISC15 | K92: 13000 | L92: 45343
A93: S1091 | B93: Riya Patel | C93: C201 | D93: Data Analytics | E93: B2 | F93: Amit | G93: Mobile | H93: 14709 | I93: DISC30 | J93: 0.3 | K93: 14000 | L93: 45296
A94: S1092 | B94: Manish Singh | C94: C203 | D94: Full Stack Dev | E94: B1 | F94: Priya | G94: Mobile | H94: 15432 | K94: 17000 | L94: 45315
A95: S1093 | B95: Rohit Nair | C95: C204 | D95: UI UX Design | E95: B3 | F95: Saurabh | G95: Mobile | H95: 7721 | I95: DISC15 | K95: 9000 | L95: 45333
A96: S1094 | B96: Aditya Joshi | C96: C204 | D96: UI UX Design | E96: B2 | F96: Priya | G96: Tablet | H96: 9426 | I96: DISC30 | J96: 0.3 | K96: 9000 | L96: 45312
A97: S1095 | B97: Meera Patil | C97: C201 | D97: Data Analytics | E97: B2 | F97: Priya | G97: Web | H97: 15073 | K97: 14000 | L97: 45328
A98: S1096 | B98: Kavita Singh | C98: C204 | D98: UI UX Design | E98: B2 | F98: Saurabh | G98: Mobile | H98: 10485 | I98: DISC30 | J98: 0.3 | K98: 9000 | L98: 45303
A99: S1097 | B99: Neha Patil | C99: C203 | D99: Full Stack Dev | E99: B2 | F99: Priya | G99: Mobile | H99: 18605 | I99: DISC15 | K99: 17000 | L99: 45336
A100: S1098 | B100: Kunal Rao | C100: C201 | D100: Data Analytics | E100: B3 | F100: Saurabh | G100: Web | H100: 12988 | K100: 14000 | L100: 45323
...

Sheet Q9
A1: StudentID | B1: StudentName | C1: CourseID | D1: CourseName | E1: BatchID | F1: MentorName | G1: Platform | H1: PaymentAmount | I1: DiscountCode | J1: DiscountPercent | K1: TargetRevenue | L1: PaymentDate
A2: S1000 | B2: Rohit Shah | C2: C201 | D2: Data Analytics | E2: B3 | F2: Priya | G2: Web | H2: 12914 | I2: DISC20 | J2: 0.2 | K2: 14000 | L2: 45339
A3: S1001 | B3: Riya Singh | C3: C201 | D3: Data Analytics | E3: B3 | F3: Priya | G3: Web | H3: 12122 | I3: DISC10 | J3: 0.1 | K3: 14000 | L3: 45305 | O3: Counts no of Records = | Q3: =COUNTIFS($D$2:$D$1001,"Data Analytics",$G$2:$G$1001,"Web") -> 65
A4: S1002 | B4: Sneha Gupta | C4: C201 | D4: Data Analytics | E4: B3 | F4: Saurabh | G4: Tablet | H4: 14661 | I4: DISC15 | K4: 14000 | L4: 45318
A5: S1003 | B5: Sneha Iyer | C5: C203 | D5: Full Stack Dev | E5: B1 | F5: Saurabh | G5: Tablet | H5: 16731 | I5: DISC30 | J5: 0.3 | K5: 17000 | L5: 45309
A6: S1004 | B6: Karan Patil | C6: C203 | D6: Full Stack Dev | E6: B1 | F6: Saurabh | G6: Mobile | H6: 15396 | I6: DISC30 | J6: 0.3 | K6: 17000 | L6: 45346
A7: S1005 | B7: Pooja Joshi | C7: C203 | D7: Full Stack Dev | E7: B1 | F7: Amit | G7: Mobile | H7: 17196 | I7: DISC10 | J7: 0.1 | K7: 17000 | L7: 45351
A8: S1006 | B8: Rahul Shah | C8: C203 | D8: Full Stack Dev | E8: B3 | F8: Amit | G8: Mobile | H8: 17364 | I8: DISC20 | J8: 0.2 | K8: 17000 | L8: 45337
A9: S1007 | B9: Riya Kulkarni | C9: C202 | D9: Data Science | E9: B2 | F9: Saurabh | G9: Web | H9: 14549 | I9: DISC10 | J9: 0.1 | K9: 13000 | L9: 45316
A10: S1008 | B10: Aditya Iyer | C10: C203 | D10: Full Stack Dev | E10: B1 | F10: Priya | G10: Mobile | H10: 15858 | I10: DISC30 | J10: 0.3 | K10: 17000 | L10: 45336
A11: S1009 | B11: Kunal Singh | C11: C201 | D11: Data Analytics | E11: B3 | F11: Amit | G11: Web | H11: 14187 | I11: DISC20 | J11: 0.2 | K11: 14000 | L11: 45302
A12: S1010 | B12: Neha Verma | C12: C203 | D12: Full Stack Dev | E12: B3 | F12: Amit | G12: Tablet | H12: 15899 | I12: DISC30 | J12: 0.3 | K12: 17000 | L12: 45345
A13: S1011 | B13: Dev Patel | C13: C201 | D13: Data Analytics | E13: B1 | F13: Saurabh | G13: Mobile | H13: 13643 | I13: DISC30 | J13: 0.3 | K13: 14000 | L13: 45296
A14: S1012 | B14: Sneha Joshi | C14: C203 | D14: Full Stack Dev | E14: B1 | F14: Amit | G14: Mobile | H14: 16620 | K14: 17000 | L14: 45301
A15: S1013 | B15: Aditya Mehta | C15: C202 | D15: Data Science | E15: B3 | F15: Amit | G15: Tablet | H15: 12076 | I15: DISC15 | K15: 13000 | L15: 45319
A16: S1014 | B16: Kunal Joshi | C16: C204 | D16: UI UX Design | E16: B2 | F16: Saurabh | G16: Web | H16: 9087 | K16: 9000 | L16: 45297
A17: S1015 | B17: Dev Kulkarni | C17: C201 | D17: Data Analytics | E17: B1 | F17: Amit | G17: Web | H17: 15244 | K17: 14000 | L17: 45330
A18: S1016 | B18: Riya Verma | C18: C204 | D18: UI UX Design | E18: B3 | F18: Priya | G18: Tablet | H18: 8029 | I18: DISC15 | K18: 9000 | L18: 45347
A19: S1017 | B19: Aarav Singh | C19: C201 | D19: Data Analytics | E19: B3 | F19: Amit | G19: Mobile | H19: 15148 | I19: DISC30 | J19: 0.3 | K19: 14000 | L19: 45299
A20: S1018 | B20: Aditya Verma | C20: C202 | D20: Data Science | E20: B2 | F20: Saurabh | G20: Tablet | H20: 14587 | I20: DISC30 | J20: 0.3 | K20: 13000 | L20: 45324
A21: S1019 | B21: Dev Mehta | C21: C201 | D21: Data Analytics | E21: B3 | F21: Priya | G21: Tablet | H21: 14079 | I21: DISC15 | K21: 14000 | L21: 45304
A22: S1020 | B22: Karan Jain | C22: C202 | D22: Data Science | E22: B3 | F22: Amit | G22: Web | H22: 13453 | I22: DISC30 | J22: 0.3 | K22: 13000 | L22: 45323
A23: S1021 | B23: Aarav Shah | C23: C203 | D23: Full Stack Dev | E23: B2 | F23: Saurabh | G23: Web | H23: 15986 | I23: DISC15 | K23: 17000 | L23: 45352
A24: S1022 | B24: Riya Shah | C24: C204 | D24: UI UX Design | E24: B1 | F24: Amit | G24: Web | H24: 7525 | K24: 9000 | L24: 45352
A25: S1023 | B25: Manish Mehta | C25: C203 | D25: Full Stack Dev | E25: B3 | F25: Amit | G25: Mobile | H25: 18950 | I25: DISC20 | J25: 0.2 | K25: 17000 | L25: 45351
A26: S1024 | B26: Manish Patel | C26: C202 | D26: Data Science | E26: B3 | F26: Priya | G26: Mobile | H26: 13751 | I26: DISC30 | J26: 0.3 | K26: 13000 | L26: 45320
A27: S1025 | B27: Kunal Gupta | C27: C204 | D27: UI UX Design | E27: B1 | F27: Saurabh | G27: Web | H27: 7262 | I27: DISC30 | J27: 0.3 | K27: 9000 | L27: 45293
A28: S1026 | B28: Kavita Gupta | C28: C202 | D28: Data Science | E28: B3 | F28: Saurabh | G28: Web | H28: 11290 | I28: DISC10 | J28: 0.1 | K28: 13000 | L28: 45306
A29: S1027 | B29: Riya Kulkarni | C29: C203 | D29: Full Stack Dev | E29: B1 | F29: Amit | G29: Web | H29: 16140 | K29: 17000 | L29: 45305
A30: S1028 | B30: Manish Mehta | C30: C204 | D30: UI UX Design | E30: B1 | F30: Priya | G30: Mobile | H30: 7779 | I30: DISC10 | J30: 0.1 | K30: 9000 | L30: 45298
A31: S1029 | B31: Rohit Verma | C31: C203 | D31: Full Stack Dev | E31: B2 | F31: Priya | G31: Mobile | H31: 18538 | I31: DISC10 | J31: 0.1 | K31: 17000 | L31: 45335
A32: S1030 | B32: Rohit Singh | C32: C201 | D32: Data Analytics | E32: B1 | F32: Priya | G32: Tablet | H32: 13389 | I32: DISC10 | J32: 0.1 | K32: 14000 | L32: 45307
A33: S1031 | B33: Sneha Patil | C33: C204 | D33: UI UX Design | E33: B1 | F33: Priya | G33: Web | H33: 8140 | K33: 9000 | L33: 45307
A34: S1032 | B34: Meera Shah | C34: C204 | D34: UI UX Design | E34: B3 | F34: Saurabh | G34: Web | H34: 9671 | I34: DISC15 | K34: 9000 | L34: 45345
A35: S1033 | B35: Aarav Shah | C35: C202 | D35: Data Science | E35: B1 | F35: Priya | G35: Mobile | H35: 12971 | I35: DISC20 | J35: 0.2 | K35: 13000 | L35: 45347
A36: S1034 | B36: Rahul Kulkarni | C36: C202 | D36: Data Science | E36: B2 | F36: Saurabh | G36: Mobile | H36: 12086 | K36: 13000 | L36: 45310
A37: S1035 | B37: Rahul Desai | C37: C204 | D37: UI UX Design | E37: B1 | F37: Saurabh | G37: Mobile | H37: 7891 | I37: DISC10 | J37: 0.1 | K37: 9000 | L37: 45329
A38: S1036 | B38: Anjali Gupta | C38: C201 | D38: Data Analytics | E38: B3 | F38: Priya | G38: Web | H38: 12205 | I38: DISC15 | K38: 14000 | L38: 45322
A39: S1037 | B39: Manish Nair | C39: C202 | D39: Data Science | E39: B1 | F39: Amit | G39: Web | H39: 14487 | I39: DISC20 | J39: 0.2 | K39: 13000 | L39: 45296
A40: S1038 | B40: Kavita Shah | C40: C202 | D40: Data Science | E40: B2 | F40: Saurabh | G40: Tablet | H40: 12008 | I40: DISC15 | K40: 13000 | L40: 45330
A41: S1039 | B41: Aarav Joshi | C41: C201 | D41: Data Analytics | E41: B2 | F41: Amit | G41: Tablet | H41: 14315 | I41: DISC15 | K41: 14000 | L41: 45312
A42: S1040 | B42: Kunal Rao | C42: C202 | D42: Data Science | E42: B3 | F42: Amit | G42: Mobile | H42: 11977 | I42: DISC30 | J42: 0.3 | K42: 13000 | L42: 45317
A43: S1041 | B43: Karan Singh | C43: C203 | D43: Full Stack Dev | E43: B2 | F43: Priya | G43: Web | H43: 15038 | K43: 17000 | L43: 45331
A44: S1042 | B44: Kavita Shah | C44: C201 | D44: Data Analytics | E44: B3 | F44: Saurabh | G44: Tablet | H44: 13086 | I44: DISC20 | J44: 0.2 | K44: 14000 | L44: 45351
A45: S1043 | B45: Pooja Shah | C45: C202 | D45: Data Science | E45: B2 | F45: Priya | G45: Web | H45: 12794 | I45: DISC15 | K45: 13000 | L45: 45337
A46: S1044 | B46: Aditya Joshi | C46: C201 | D46: Data Analytics | E46: B3 | F46: Amit | G46: Mobile | H46: 15816 | I46: DISC10 | J46: 0.1 | K46: 14000 | L46: 45352
A47: S1045 | B47: Kunal Mehta | C47: C203 | D47: Full Stack Dev | E47: B1 | F47: Saurabh | G47: Tablet | H47: 17266 | I47: DISC20 | J47: 0.2 | K47: 17000 | L47: 45309
A48: S1046 | B48: Aditya Joshi | C48: C202 | D48: Data Science | E48: B3 | F48: Priya | G48: Web | H48: 13815 | I48: DISC30 | J48: 0.3 | K48: 13000 | L48: 45324
A49: S1047 | B49: Neha Rao | C49: C201 | D49: Data Analytics | E49: B1 | F49: Amit | G49: Mobile | H49: 15397 | I49: DISC30 | J49: 0.3 | K49: 14000 | L49: 45294
A50: S1048 | B50: Aarav Jain | C50: C202 | D50: Data Science | E50: B3 | F50: Priya | G50: Web | H50: 14036 | K50: 13000 | L50: 45327
A51: S1049 | B51: Anjali Verma | C51: C201 | D51: Data Analytics | E51: B1 | F51: Saurabh | G51: Tablet | H51: 15702 | I51: DISC20 | J51: 0.2 | K51: 14000 | L51: 45326
A52: S1050 | B52: Aarav Nair | C52: C203 | D52: Full Stack Dev | E52: B3 | F52: Amit | G52: Web | H52: 16760 | I52: DISC20 | J52: 0.2 | K52: 17000 | L52: 45294
A53: S1051 | B53: Aditya Jain | C53: C201 | D53: Data Analytics | E53: B2 | F53: Saurabh | G53: Tablet | H53: 13022 | I53: DISC10 | J53: 0.1 | K53: 14000 | L53: 45314
A54: S1052 | B54: Dev Gupta | C54: C204 | D54: UI UX Design | E54: B3 | F54: Amit | G54: Web | H54: 10791 | I54: DISC20 | J54: 0.2 | K54: 9000 | L54: 45347
A55: S1053 | B55: Karan Patel | C55: C202 | D55: Data Science | E55: B2 | F55: Saurabh | G55: Web | H55: 14016 | I55: DISC30 | J55: 0.3 | K55: 13000 | L55: 45342
A56: S1054 | B56: Kunal Verma | C56: C202 | D56: Data Science | E56: B2 | F56: Saurabh | G56: Tablet | H56: 11442 | K56: 13000 | L56: 45347
A57: S1055 | B57: Aarav Nair | C57: C204 | D57: UI UX Design | E57: B1 | F57: Saurabh | G57: Mobile | H57: 8432 | I57: DISC30 | J57: 0.3 | K57: 9000 | L57: 45344
A58: S1056 | B58: Dev Nair | C58: C202 | D58: Data Science | E58: B1 | F58: Saurabh | G58: Tablet | H58: 11791 | K58: 13000 | L58: 45313
A59: S1057 | B59: Aditya Nair | C59: C201 | D59: Data Analytics | E59: B2 | F59: Priya | G59: Tablet | H59: 14086 | K59: 14000 | L59: 45335
A60: S1058 | B60: Meera Gupta | C60: C203 | D60: Full Stack Dev | E60: B1 | F60: Saurabh | G60: Mobile | H60: 15731 | I60: DISC15 | K60: 17000 | L60: 45308
A61: S1059 | B61: Aarav Shah | C61: C204 | D61: UI UX Design | E61: B2 | F61: Amit | G61: Mobile | H61: 8787 | I61: DISC15 | K61: 9000 | L61: 45324
A62: S1060 | B62: Riya Verma | C62: C202 | D62: Data Science | E62: B2 | F62: Saurabh | G62: Tablet | H62: 12786 | I62: DISC10 | J62: 0.1 | K62: 13000 | L62: 45325
A63: S1061 | B63: Kunal Patel | C63: C202 | D63: Data Science | E63: B2 | F63: Priya | G63: Web | H63: 14886 | I63: DISC30 | J63: 0.3 | K63: 13000 | L63: 45331
A64: S1062 | B64: Pooja Singh | C64: C201 | D64: Data Analytics | E64: B3 | F64: Priya | G64: Tablet | H64: 13266 | K64: 14000 | L64: 45312
A65: S1063 | B65: Rahul Desai | C65: C203 | D65: Full Stack Dev | E65: B3 | F65: Saurabh | G65: Web | H65: 16722 | K65: 17000 | L65: 45335
A66: S1064 | B66: Anjali Mehta | C66: C203 | D66: Full Stack Dev | E66: B2 | F66: Amit | G66: Web | H66: 16244 | I66: DISC30 | J66: 0.3 | K66: 17000 | L66: 45305
A67: S1065 | B67: Rahul Patel | C67: C203 | D67: Full Stack Dev | E67: B2 | F67: Priya | G67: Mobile | H67: 17767 | I67: DISC20 | J67: 0.2 | K67: 17000 | L67: 45324
A68: S1066 | B68: Neha Patel | C68: C202 | D68: Data Science | E68: B3 | F68: Saurabh | G68: Mobile | H68: 13111 | I68: DISC15 | K68: 13000 | L68: 45313
A69: S1067 | B69: Riya Nair | C69: C202 | D69: Data Science | E69: B3 | F69: Priya | G69: Web | H69: 14303 | I69: DISC20 | J69: 0.2 | K69: 13000 | L69: 45301
A70: S1068 | B70: Aarav Kulkarni | C70: C202 | D70: Data Science | E70: B2 | F70: Amit | G70: Web | H70: 12865 | K70: 13000 | L70: 45348
A71: S1069 | B71: Rohit Joshi | C71: C202 | D71: Data Science | E71: B3 | F71: Amit | G71: Mobile | H71: 13024 | K71: 13000 | L71: 45307
A72: S1070 | B72: Karan Singh | C72: C201 | D72: Data Analytics | E72: B1 | F72: Priya | G72: Web | H72: 12720 | I72: DISC15 | K72: 14000 | L72: 45321
A73: S1071 | B73: Aarav Gupta | C73: C202 | D73: Data Science | E73: B1 | F73: Priya | G73: Web | H73: 14282 | K73: 13000 | L73: 45334
A74: S1072 | B74: Manish Gupta | C74: C203 | D74: Full Stack Dev | E74: B2 | F74: Amit | G74: Tablet | H74: 18653 | I74: DISC15 | K74: 17000 | L74: 45319
A75: S1073 | B75: Meera Gupta | C75: C204 | D75: UI UX Design | E75: B1 | F75: Amit | G75: Mobile | H75: 8843 | I75: DISC30 | J75: 0.3 | K75: 9000 | L75: 45340
A76: S1074 | B76: Sneha Nair | C76: C203 | D76: Full Stack Dev | E76: B3 | F76: Priya | G76: Tablet | H76: 15979 | I76: DISC30 | J76: 0.3 | K76: 17000 | L76: 45320
A77: S1075 | B77: Riya Desai | C77: C203 | D77: Full Stack Dev | E77: B1 | F77: Priya | G77: Mobile | H77: 16309 | I77: DISC15 | K77: 17000 | L77: 45297
A78: S1076 | B78: Karan Mehta | C78: C202 | D78: Data Science | E78: B2 | F78: Amit | G78: Web | H78: 13893 | I78: DISC20 | J78: 0.2 | K78: 13000 | L78: 45296
A79: S1077 | B79: Rahul Verma | C79: C203 | D79: Full Stack Dev | E79: B3 | F79: Priya | G79: Mobile | H79: 15255 | I79: DISC20 | J79: 0.2 | K79: 17000 | L79: 45345
A80: S1078 | B80: Rahul Verma | C80: C201 | D80: Data Analytics | E80: B3 | F80: Priya | G80: Mobile | H80: 12024 | I80: DISC30 | J80: 0.3 | K80: 14000 | L80: 45311
A81: S1079 | B81: Dev Verma | C81: C204 | D81: UI UX Design | E81: B3 | F81: Amit | G81: Tablet | H81: 9236 | I81: DISC15 | K81: 9000 | L81: 45349
A82: S1080 | B82: Sneha Iyer | C82: C202 | D82: Data Science | E82: B2 | F82: Priya | G82: Mobile | H82: 11118 | K82: 13000 | L82: 45313
A83: S1081 | B83: Rohit Singh | C83: C204 | D83: UI UX Design | E83: B3 | F83: Saurabh | G83: Mobile | H83: 10766 | I83: DISC20 | J83: 0.2 | K83: 9000 | L83: 45331
A84: S1082 | B84: Manish Kulkarni | C84: C204 | D84: UI UX Design | E84: B3 | F84: Amit | G84: Tablet | H84: 7111 | I84: DISC10 | J84: 0.1 | K84: 9000 | L84: 45333
A85: S1083 | B85: Rahul Mehta | C85: C204 | D85: UI UX Design | E85: B1 | F85: Saurabh | G85: Mobile | H85: 8552 | I85: DISC30 | J85: 0.3 | K85: 9000 | L85: 45305
A86: S1084 | B86: Neha Jain | C86: C203 | D86: Full Stack Dev | E86: B2 | F86: Priya | G86: Mobile | H86: 16033 | I86: DISC10 | J86: 0.1 | K86: 17000 | L86: 45322
A87: S1085 | B87: Aarav Desai | C87: C201 | D87: Data Analytics | E87: B2 | F87: Saurabh | G87: Tablet | H87: 12281 | I87: DISC10 | J87: 0.1 | K87: 14000 | L87: 45340
A88: S1086 | B88: Aarav Patil | C88: C202 | D88: Data Science | E88: B1 | F88: Amit | G88: Web | H88: 11977 | I88: DISC20 | J88: 0.2 | K88: 13000 | L88: 45322
A89: S1087 | B89: Rohit Shah | C89: C202 | D89: Data Science | E89: B2 | F89: Amit | G89: Mobile | H89: 14141 | I89: DISC30 | J89: 0.3 | K89: 13000 | L89: 45302
A90: S1088 | B90: Kavita Joshi | C90: C201 | D90: Data Analytics | E90: B1 | F90: Priya | G90: Web | H90: 14370 | I90: DISC10 | J90: 0.1 | K90: 14000 | L90: 45351
A91: S1089 | B91: Aditya Joshi | C91: C204 | D91: UI UX Design | E91: B2 | F91: Amit | G91: Web | H91: 7311 | I91: DISC15 | K91: 9000 | L91: 45336
A92: S1090 | B92: Meera Singh | C92: C202 | D92: Data Science | E92: B1 | F92: Amit | G92: Mobile | H92: 14482 | I92: DISC15 | K92: 13000 | L92: 45343
A93: S1091 | B93: Riya Patel | C93: C201 | D93: Data Analytics | E93: B2 | F93: Amit | G93: Mobile | H93: 14709 | I93: DISC30 | J93: 0.3 | K93: 14000 | L93: 45296
A94: S1092 | B94: Manish Singh | C94: C203 | D94: Full Stack Dev | E94: B1 | F94: Priya | G94: Mobile | H94: 15432 | K94: 17000 | L94: 45315
A95: S1093 | B95: Rohit Nair | C95: C204 | D95: UI UX Design | E95: B3 | F95: Saurabh | G95: Mobile | H95: 7721 | I95: DISC15 | K95: 9000 | L95: 45333
A96: S1094 | B96: Aditya Joshi | C96: C204 | D96: UI UX Design | E96: B2 | F96: Priya | G96: Tablet | H96: 9426 | I96: DISC30 | J96: 0.3 | K96: 9000 | L96: 45312
A97: S1095 | B97: Meera Patil | C97: C201 | D97: Data Analytics | E97: B2 | F97: Priya | G97: Web | H97: 15073 | K97: 14000 | L97: 45328
A98: S1096 | B98: Kavita Singh | C98: C204 | D98: UI UX Design | E98: B2 | F98: Saurabh | G98: Mobile | H98: 10485 | I98: DISC30 | J98: 0.3 | K98: 9000 | L98: 45303
A99: S1097 | B99: Neha Patil | C99: C203 | D99: Full Stack Dev | E99: B2 | F99: Priya | G99: Mobile | H99: 18605 | I99: DISC15 | K99: 17000 | L99: 45336
A100: S1098 | B100: Kunal Rao | C100: C201 | D100: Data Analytics | E100: B3 | F100: Saurabh | G100: Web | H100: 12988 | K100: 14000 | L100: 45323
...

Sheet Q10
A1: StudentID | B1: StudentName | C1: CourseID | D1: CourseName | E1: BatchID | F1: MentorName | G1: Platform | H1: PaymentAmount | I1: DiscountCode | J1: DiscountPercent | K1: TargetRevenue | L1: PaymentDate
A2: S1000 | B2: Rohit Shah | C2: C201 | D2: Data Analytics | E2: B3 | F2: Priya | G2: Web | H2: 12914 | I2: DISC20 | J2: 0.2 | K2: 14000 | L2: 45339
A3: S1001 | B3: Riya Singh | C3: C201 | D3: Data Analytics | E3: B3 | F3: Priya | G3: Web | H3: 12122 | I3: DISC10 | J3: 0.1 | K3: 14000 | L3: 45305 | N3: StudentID | O3: StudentName | P3: CourseID | Q3: CourseName | R3: BatchID | S3: MentorName | T3: Platform | U3: PaymentAmount | V3: DiscountCode | W3: DiscountPercent | X3: TargetRevenue | Y3: PaymentDate
A4: S1002 | B4: Sneha Gupta | C4: C201 | D4: Data Analytics | E4: B3 | F4: Saurabh | G4: Tablet | H4: 14661 | I4: DISC15 | K4: 14000 | L4: 45318 | N4: S1002 | O4: {=_xlfn.XLOOKUP(N4, Table1[StudentID], Table1[[StudentName]:[PaymentDate]])} -> Sneha Gupta | P4: C201 | Q4: Data Analytics | R4: B3 | S4: Saurabh | T4: Tablet | U4: 14661 | V4: DISC15 | W4: 0 | X4: 14000 | Y4: 45318
A5: S1003 | B5: Sneha Iyer | C5: C203 | D5: Full Stack Dev | E5: B1 | F5: Saurabh | G5: Tablet | H5: 16731 | I5: DISC30 | J5: 0.3 | K5: 17000 | L5: 45309
A6: S1004 | B6: Karan Patil | C6: C203 | D6: Full Stack Dev | E6: B1 | F6: Saurabh | G6: Mobile | H6: 15396 | I6: DISC30 | J6: 0.3 | K6: 17000 | L6: 45346
A7: S1005 | B7: Pooja Joshi | C7: C203 | D7: Full Stack Dev | E7: B1 | F7: Amit | G7: Mobile | H7: 17196 | I7: DISC10 | J7: 0.1 | K7: 17000 | L7: 45351
A8: S1006 | B8: Rahul Shah | C8: C203 | D8: Full Stack Dev | E8: B3 | F8: Amit | G8: Mobile | H8: 17364 | I8: DISC20 | J8: 0.2 | K8: 17000 | L8: 45337
A9: S1007 | B9: Riya Kulkarni | C9: C202 | D9: Data Science | E9: B2 | F9: Saurabh | G9: Web | H9: 14549 | I9: DISC10 | J9: 0.1 | K9: 13000 | L9: 45316
A10: S1008 | B10: Aditya Iyer | C10: C203 | D10: Full Stack Dev | E10: B1 | F10: Priya | G10: Mobile | H10: 15858 | I10: DISC30 | J10: 0.3 | K10: 17000 | L10: 45336
A11: S1009 | B11: Kunal Singh | C11: C201 | D11: Data Analytics | E11: B3 | F11: Amit | G11: Web | H11: 14187 | I11: DISC20 | J11: 0.2 | K11: 14000 | L11: 45302
A12: S1010 | B12: Neha Verma | C12: C203 | D12: Full Stack Dev | E12: B3 | F12: Amit | G12: Tablet | H12: 15899 | I12: DISC30 | J12: 0.3 | K12: 17000 | L12: 45345
A13: S1011 | B13: Dev Patel | C13: C201 | D13: Data Analytics | E13: B1 | F13: Saurabh | G13: Mobile | H13: 13643 | I13: DISC30 | J13: 0.3 | K13: 14000 | L13: 45296
A14: S1012 | B14: Sneha Joshi | C14: C203 | D14: Full Stack Dev | E14: B1 | F14: Amit | G14: Mobile | H14: 16620 | K14: 17000 | L14: 45301
A15: S1013 | B15: Aditya Mehta | C15: C202 | D15: Data Science | E15: B3 | F15: Amit | G15: Tablet | H15: 12076 | I15: DISC15 | K15: 13000 | L15: 45319
A16: S1014 | B16: Kunal Joshi | C16: C204 | D16: UI UX Design | E16: B2 | F16: Saurabh | G16: Web | H16: 9087 | K16: 9000 | L16: 45297
A17: S1015 | B17: Dev Kulkarni | C17: C201 | D17: Data Analytics | E17: B1 | F17: Amit | G17: Web | H17: 15244 | K17: 14000 | L17: 45330
A18: S1016 | B18: Riya Verma | C18: C204 | D18: UI UX Design | E18: B3 | F18: Priya | G18: Tablet | H18: 8029 | I18: DISC15 | K18: 9000 | L18: 45347
A19: S1017 | B19: Aarav Singh | C19: C201 | D19: Data Analytics | E19: B3 | F19: Amit | G19: Mobile | H19: 15148 | I19: DISC30 | J19: 0.3 | K19: 14000 | L19: 45299
A20: S1018 | B20: Aditya Verma | C20: C202 | D20: Data Science | E20: B2 | F20: Saurabh | G20: Tablet | H20: 14587 | I20: DISC30 | J20: 0.3 | K20: 13000 | L20: 45324
A21: S1019 | B21: Dev Mehta | C21: C201 | D21: Data Analytics | E21: B3 | F21: Priya | G21: Tablet | H21: 14079 | I21: DISC15 | K21: 14000 | L21: 45304
A22: S1020 | B22: Karan Jain | C22: C202 | D22: Data Science | E22: B3 | F22: Amit | G22: Web | H22: 13453 | I22: DISC30 | J22: 0.3 | K22: 13000 | L22: 45323
A23: S1021 | B23: Aarav Shah | C23: C203 | D23: Full Stack Dev | E23: B2 | F23: Saurabh | G23: Web | H23: 15986 | I23: DISC15 | K23: 17000 | L23: 45352
A24: S1022 | B24: Riya Shah | C24: C204 | D24: UI UX Design | E24: B1 | F24: Amit | G24: Web | H24: 7525 | K24: 9000 | L24: 45352
A25: S1023 | B25: Manish Mehta | C25: C203 | D25: Full Stack Dev | E25: B3 | F25: Amit | G25: Mobile | H25: 18950 | I25: DISC20 | J25: 0.2 | K25: 17000 | L25: 45351
A26: S1024 | B26: Manish Patel | C26: C202 | D26: Data Science | E26: B3 | F26: Priya | G26: Mobile | H26: 13751 | I26: DISC30 | J26: 0.3 | K26: 13000 | L26: 45320
A27: S1025 | B27: Kunal Gupta | C27: C204 | D27: UI UX Design | E27: B1 | F27: Saurabh | G27: Web | H27: 7262 | I27: DISC30 | J27: 0.3 | K27: 9000 | L27: 45293
A28: S1026 | B28: Kavita Gupta | C28: C202 | D28: Data Science | E28: B3 | F28: Saurabh | G28: Web | H28: 11290 | I28: DISC10 | J28: 0.1 | K28: 13000 | L28: 45306
A29: S1027 | B29: Riya Kulkarni | C29: C203 | D29: Full Stack Dev | E29: B1 | F29: Amit | G29: Web | H29: 16140 | K29: 17000 | L29: 45305
A30: S1028 | B30: Manish Mehta | C30: C204 | D30: UI UX Design | E30: B1 | F30: Priya | G30: Mobile | H30: 7779 | I30: DISC10 | J30: 0.1 | K30: 9000 | L30: 45298
A31: S1029 | B31: Rohit Verma | C31: C203 | D31: Full Stack Dev | E31: B2 | F31: Priya | G31: Mobile | H31: 18538 | I31: DISC10 | J31: 0.1 | K31: 17000 | L31: 45335
A32: S1030 | B32: Rohit Singh | C32: C201 | D32: Data Analytics | E32: B1 | F32: Priya | G32: Tablet | H32: 13389 | I32: DISC10 | J32: 0.1 | K32: 14000 | L32: 45307
A33: S1031 | B33: Sneha Patil | C33: C204 | D33: UI UX Design | E33: B1 | F33: Priya | G33: Web | H33: 8140 | K33: 9000 | L33: 45307
A34: S1032 | B34: Meera Shah | C34: C204 | D34: UI UX Design | E34: B3 | F34: Saurabh | G34: Web | H34: 9671 | I34: DISC15 | K34: 9000 | L34: 45345
A35: S1033 | B35: Aarav Shah | C35: C202 | D35: Data Science | E35: B1 | F35: Priya | G35: Mobile | H35: 12971 | I35: DISC20 | J35: 0.2 | K35: 13000 | L35: 45347
A36: S1034 | B36: Rahul Kulkarni | C36: C202 | D36: Data Science | E36: B2 | F36: Saurabh | G36: Mobile | H36: 12086 | K36: 13000 | L36: 45310
A37: S1035 | B37: Rahul Desai | C37: C204 | D37: UI UX Design | E37: B1 | F37: Saurabh | G37: Mobile | H37: 7891 | I37: DISC10 | J37: 0.1 | K37: 9000 | L37: 45329
A38: S1036 | B38: Anjali Gupta | C38: C201 | D38: Data Analytics | E38: B3 | F38: Priya | G38: Web | H38: 12205 | I38: DISC15 | K38: 14000 | L38: 45322
A39: S1037 | B39: Manish Nair | C39: C202 | D39: Data Science | E39: B1 | F39: Amit | G39: Web | H39: 14487 | I39: DISC20 | J39: 0.2 | K39: 13000 | L39: 45296
A40: S1038 | B40: Kavita Shah | C40: C202 | D40: Data Science | E40: B2 | F40: Saurabh | G40: Tablet | H40: 12008 | I40: DISC15 | K40: 13000 | L40: 45330
A41: S1039 | B41: Aarav Joshi | C41: C201 | D41: Data Analytics | E41: B2 | F41: Amit | G41: Tablet | H41: 14315 | I41: DISC15 | K41: 14000 | L41: 45312
A42: S1040 | B42: Kunal Rao | C42: C202 | D42: Data Science | E42: B3 | F42: Amit | G42: Mobile | H42: 11977 | I42: DISC30 | J42: 0.3 | K42: 13000 | L42: 45317
A43: S1041 | B43: Karan Singh | C43: C203 | D43: Full Stack Dev | E43: B2 | F43: Priya | G43: Web | H43: 15038 | K43: 17000 | L43: 45331
A44: S1042 | B44: Kavita Shah | C44: C201 | D44: Data Analytics | E44: B3 | F44: Saurabh | G44: Tablet | H44: 13086 | I44: DISC20 | J44: 0.2 | K44: 14000 | L44: 45351
A45: S1043 | B45: Pooja Shah | C45: C202 | D45: Data Science | E45: B2 | F45: Priya | G45: Web | H45: 12794 | I45: DISC15 | K45: 13000 | L45: 45337
A46: S1044 | B46: Aditya Joshi | C46: C201 | D46: Data Analytics | E46: B3 | F46: Amit | G46: Mobile | H46: 15816 | I46: DISC10 | J46: 0.1 | K46: 14000 | L46: 45352
A47: S1045 | B47: Kunal Mehta | C47: C203 | D47: Full Stack Dev | E47: B1 | F47: Saurabh | G47: Tablet | H47: 17266 | I47: DISC20 | J47: 0.2 | K47: 17000 | L47: 45309
A48: S1046 | B48: Aditya Joshi | C48: C202 | D48: Data Science | E48: B3 | F48: Priya | G48: Web | H48: 13815 | I48: DISC30 | J48: 0.3 | K48: 13000 | L48: 45324
A49: S1047 | B49: Neha Rao | C49: C201 | D49: Data Analytics | E49: B1 | F49: Amit | G49: Mobile | H49: 15397 | I49: DISC30 | J49: 0.3 | K49: 14000 | L49: 45294
A50: S1048 | B50: Aarav Jain | C50: C202 | D50: Data Science | E50: B3 | F50: Priya | G50: Web | H50: 14036 | K50: 13000 | L50: 45327
A51: S1049 | B51: Anjali Verma | C51: C201 | D51: Data Analytics | E51: B1 | F51: Saurabh | G51: Tablet | H51: 15702 | I51: DISC20 | J51: 0.2 | K51: 14000 | L51: 45326
A52: S1050 | B52: Aarav Nair | C52: C203 | D52: Full Stack Dev | E52: B3 | F52: Amit | G52: Web | H52: 16760 | I52: DISC20 | J52: 0.2 | K52: 17000 | L52: 45294
A53: S1051 | B53: Aditya Jain | C53: C201 | D53: Data Analytics | E53: B2 | F53: Saurabh | G53: Tablet | H53: 13022 | I53: DISC10 | J53: 0.1 | K53: 14000 | L53: 45314
A54: S1052 | B54: Dev Gupta | C54: C204 | D54: UI UX Design | E54: B3 | F54: Amit | G54: Web | H54: 10791 | I54: DISC20 | J54: 0.2 | K54: 9000 | L54: 45347
A55: S1053 | B55: Karan Patel | C55: C202 | D55: Data Science | E55: B2 | F55: Saurabh | G55: Web | H55: 14016 | I55: DISC30 | J55: 0.3 | K55: 13000 | L55: 45342
A56: S1054 | B56: Kunal Verma | C56: C202 | D56: Data Science | E56: B2 | F56: Saurabh | G56: Tablet | H56: 11442 | K56: 13000 | L56: 45347
A57: S1055 | B57: Aarav Nair | C57: C204 | D57: UI UX Design | E57: B1 | F57: Saurabh | G57: Mobile | H57: 8432 | I57: DISC30 | J57: 0.3 | K57: 9000 | L57: 45344
A58: S1056 | B58: Dev Nair | C58: C202 | D58: Data Science | E58: B1 | F58: Saurabh | G58: Tablet | H58: 11791 | K58: 13000 | L58: 45313
A59: S1057 | B59: Aditya Nair | C59: C201 | D59: Data Analytics | E59: B2 | F59: Priya | G59: Tablet | H59: 14086 | K59: 14000 | L59: 45335
A60: S1058 | B60: Meera Gupta | C60: C203 | D60: Full Stack Dev | E60: B1 | F60: Saurabh | G60: Mobile | H60: 15731 | I60: DISC15 | K60: 17000 | L60: 45308
A61: S1059 | B61: Aarav Shah | C61: C204 | D61: UI UX Design | E61: B2 | F61: Amit | G61: Mobile | H61: 8787 | I61: DISC15 | K61: 9000 | L61: 45324
A62: S1060 | B62: Riya Verma | C62: C202 | D62: Data Science | E62: B2 | F62: Saurabh | G62: Tablet | H62: 12786 | I62: DISC10 | J62: 0.1 | K62: 13000 | L62: 45325
A63: S1061 | B63: Kunal Patel | C63: C202 | D63: Data Science | E63: B2 | F63: Priya | G63: Web | H63: 14886 | I63: DISC30 | J63: 0.3 | K63: 13000 | L63: 45331
A64: S1062 | B64: Pooja Singh | C64: C201 | D64: Data Analytics | E64: B3 | F64: Priya | G64: Tablet | H64: 13266 | K64: 14000 | L64: 45312
A65: S1063 | B65: Rahul Desai | C65: C203 | D65: Full Stack Dev | E65: B3 | F65: Saurabh | G65: Web | H65: 16722 | K65: 17000 | L65: 45335
A66: S1064 | B66: Anjali Mehta | C66: C203 | D66: Full Stack Dev | E66: B2 | F66: Amit | G66: Web | H66: 16244 | I66: DISC30 | J66: 0.3 | K66: 17000 | L66: 45305
A67: S1065 | B67: Rahul Patel | C67: C203 | D67: Full Stack Dev | E67: B2 | F67: Priya | G67: Mobile | H67: 17767 | I67: DISC20 | J67: 0.2 | K67: 17000 | L67: 45324
A68: S1066 | B68: Neha Patel | C68: C202 | D68: Data Science | E68: B3 | F68: Saurabh | G68: Mobile | H68: 13111 | I68: DISC15 | K68: 13000 | L68: 45313
A69: S1067 | B69: Riya Nair | C69: C202 | D69: Data Science | E69: B3 | F69: Priya | G69: Web | H69: 14303 | I69: DISC20 | J69: 0.2 | K69: 13000 | L69: 45301
A70: S1068 | B70: Aarav Kulkarni | C70: C202 | D70: Data Science | E70: B2 | F70: Amit | G70: Web | H70: 12865 | K70: 13000 | L70: 45348
A71: S1069 | B71: Rohit Joshi | C71: C202 | D71: Data Science | E71: B3 | F71: Amit | G71: Mobile | H71: 13024 | K71: 13000 | L71: 45307
A72: S1070 | B72: Karan Singh | C72: C201 | D72: Data Analytics | E72: B1 | F72: Priya | G72: Web | H72: 12720 | I72: DISC15 | K72: 14000 | L72: 45321
A73: S1071 | B73: Aarav Gupta | C73: C202 | D73: Data Science | E73: B1 | F73: Priya | G73: Web | H73: 14282 | K73: 13000 | L73: 45334
A74: S1072 | B74: Manish Gupta | C74: C203 | D74: Full Stack Dev | E74: B2 | F74: Amit | G74: Tablet | H74: 18653 | I74: DISC15 | K74: 17000 | L74: 45319
A75: S1073 | B75: Meera Gupta | C75: C204 | D75: UI UX Design | E75: B1 | F75: Amit | G75: Mobile | H75: 8843 | I75: DISC30 | J75: 0.3 | K75: 9000 | L75: 45340
A76: S1074 | B76: Sneha Nair | C76: C203 | D76: Full Stack Dev | E76: B3 | F76: Priya | G76: Tablet | H76: 15979 | I76: DISC30 | J76: 0.3 | K76: 17000 | L76: 45320
A77: S1075 | B77: Riya Desai | C77: C203 | D77: Full Stack Dev | E77: B1 | F77: Priya | G77: Mobile | H77: 16309 | I77: DISC15 | K77: 17000 | L77: 45297
A78: S1076 | B78: Karan Mehta | C78: C202 | D78: Data Science | E78: B2 | F78: Amit | G78: Web | H78: 13893 | I78: DISC20 | J78: 0.2 | K78: 13000 | L78: 45296
A79: S1077 | B79: Rahul Verma | C79: C203 | D79: Full Stack Dev | E79: B3 | F79: Priya | G79: Mobile | H79: 15255 | I79: DISC20 | J79: 0.2 | K79: 17000 | L79: 45345
A80: S1078 | B80: Rahul Verma | C80: C201 | D80: Data Analytics | E80: B3 | F80: Priya | G80: Mobile | H80: 12024 | I80: DISC30 | J80: 0.3 | K80: 14000 | L80: 45311
A81: S1079 | B81: Dev Verma | C81: C204 | D81: UI UX Design | E81: B3 | F81: Amit | G81: Tablet | H81: 9236 | I81: DISC15 | K81: 9000 | L81: 45349
A82: S1080 | B82: Sneha Iyer | C82: C202 | D82: Data Science | E82: B2 | F82: Priya | G82: Mobile | H82: 11118 | K82: 13000 | L82: 45313
A83: S1081 | B83: Rohit Singh | C83: C204 | D83: UI UX Design | E83: B3 | F83: Saurabh | G83: Mobile | H83: 10766 | I83: DISC20 | J83: 0.2 | K83: 9000 | L83: 45331
A84: S1082 | B84: Manish Kulkarni | C84: C204 | D84: UI UX Design | E84: B3 | F84: Amit | G84: Tablet | H84: 7111 | I84: DISC10 | J84: 0.1 | K84: 9000 | L84: 45333
A85: S1083 | B85: Rahul Mehta | C85: C204 | D85: UI UX Design | E85: B1 | F85: Saurabh | G85: Mobile | H85: 8552 | I85: DISC30 | J85: 0.3 | K85: 9000 | L85: 45305
A86: S1084 | B86: Neha Jain | C86: C203 | D86: Full Stack Dev | E86: B2 | F86: Priya | G86: Mobile | H86: 16033 | I86: DISC10 | J86: 0.1 | K86: 17000 | L86: 45322
A87: S1085 | B87: Aarav Desai | C87: C201 | D87: Data Analytics | E87: B2 | F87: Saurabh | G87: Tablet | H87: 12281 | I87: DISC10 | J87: 0.1 | K87: 14000 | L87: 45340
A88: S1086 | B88: Aarav Patil | C88: C202 | D88: Data Science | E88: B1 | F88: Amit | G88: Web | H88: 11977 | I88: DISC20 | J88: 0.2 | K88: 13000 | L88: 45322
A89: S1087 | B89: Rohit Shah | C89: C202 | D89: Data Science | E89: B2 | F89: Amit | G89: Mobile | H89: 14141 | I89: DISC30 | J89: 0.3 | K89: 13000 | L89: 45302
A90: S1088 | B90: Kavita Joshi | C90: C201 | D90: Data Analytics | E90: B1 | F90: Priya | G90: Web | H90: 14370 | I90: DISC10 | J90: 0.1 | K90: 14000 | L90: 45351
A91: S1089 | B91: Aditya Joshi | C91: C204 | D91: UI UX Design | E91: B2 | F91: Amit | G91: Web | H91: 7311 | I91: DISC15 | K91: 9000 | L91: 45336
A92: S1090 | B92: Meera Singh | C92: C202 | D92: Data Science | E92: B1 | F92: Amit | G92: Mobile | H92: 14482 | I92: DISC15 | K92: 13000 | L92: 45343
A93: S1091 | B93: Riya Patel | C93: C201 | D93: Data Analytics | E93: B2 | F93: Amit | G93: Mobile | H93: 14709 | I93: DISC30 | J93: 0.3 | K93: 14000 | L93: 45296
A94: S1092 | B94: Manish Singh | C94: C203 | D94: Full Stack Dev | E94: B1 | F94: Priya | G94: Mobile | H94: 15432 | K94: 17000 | L94: 45315
A95: S1093 | B95: Rohit Nair | C95: C204 | D95: UI UX Design | E95: B3 | F95: Saurabh | G95: Mobile | H95: 7721 | I95: DISC15 | K95: 9000 | L95: 45333
A96: S1094 | B96: Aditya Joshi | C96: C204 | D96: UI UX Design | E96: B2 | F96: Priya | G96: Tablet | H96: 9426 | I96: DISC30 | J96: 0.3 | K96: 9000 | L96: 45312
A97: S1095 | B97: Meera Patil | C97: C201 | D97: Data Analytics | E97: B2 | F97: Priya | G97: Web | H97: 15073 | K97: 14000 | L97: 45328
A98: S1096 | B98: Kavita Singh | C98: C204 | D98: UI UX Design | E98: B2 | F98: Saurabh | G98: Mobile | H98: 10485 | I98: DISC30 | J98: 0.3 | K98: 9000 | L98: 45303
A99: S1097 | B99: Neha Patil | C99: C203 | D99: Full Stack Dev | E99: B2 | F99: Priya | G99: Mobile | H99: 18605 | I99: DISC15 | K99: 17000 | L99: 45336
A100: S1098 | B100: Kunal Rao | C100: C201 | D100: Data Analytics | E100: B3 | F100: Saurabh | G100: Web | H100: 12988 | K100: 14000 | L100: 45323
...

Sheet Q11
A1: StudentID | B1: StudentName | C1: CourseID | D1: CourseName | E1: BatchID | F1: MentorName | G1: Platform | H1: PaymentAmount | I1: DiscountCode | J1: DiscountPercent | K1: TargetRevenue | L1: PaymentDate
A2: S1000 | B2: Rohit Shah | C2: C201 | D2: Data Analytics | E2: B3 | F2: Priya | G2: Web | H2: 12914 | I2: DISC20 | J2: 0.2 | K2: 14000 | L2: 45339 | N2: Sum of PaymentAmount
A3: S1001 | B3: Riya Singh | C3: C201 | D3: Data Analytics | E3: B3 | F3: Priya | G3: Web | H3: 12122 | I3: DISC10 | J3: 0.1 | K3: 14000 | L3: 45305 | O3: Mobile | P3: Tablet | Q3: Web | R3: Grand Total
A4: S1002 | B4: Sneha Gupta | C4: C201 | D4: Data Analytics | E4: B3 | F4: Saurabh | G4: Tablet | H4: 14661 | I4: DISC15 | K4: 14000 | L4: 45318 | N4: Data Analytics | O4: 1119871 | P4: 1458981 | Q4: 928879 | R4: 3507731
A5: S1003 | B5: Sneha Iyer | C5: C203 | D5: Full Stack Dev | E5: B1 | F5: Saurabh | G5: Tablet | H5: 16731 | I5: DISC30 | J5: 0.3 | K5: 17000 | L5: 45309 | N5: Data Science | O5: 1167543 | P5: 921127 | Q5: 1067078 | R5: 3155748
A6: S1004 | B6: Karan Patil | C6: C203 | D6: Full Stack Dev | E6: B1 | F6: Saurabh | G6: Mobile | H6: 15396 | I6: DISC30 | J6: 0.3 | K6: 17000 | L6: 45346 | N6: Full Stack Dev | O6: 1348435 | P6: 1729206 | Q6: 1462566 | R6: 4540207
A7: S1005 | B7: Pooja Joshi | C7: C203 | D7: Full Stack Dev | E7: B1 | F7: Amit | G7: Mobile | H7: 17196 | I7: DISC10 | J7: 0.1 | K7: 17000 | L7: 45351 | N7: UI UX Design | O7: 660619 | P7: 792176 | Q7: 738812 | R7: 2191607
A8: S1006 | B8: Rahul Shah | C8: C203 | D8: Full Stack Dev | E8: B3 | F8: Amit | G8: Mobile | H8: 17364 | I8: DISC20 | J8: 0.2 | K8: 17000 | L8: 45337 | N8: Grand Total | O8: 4296468 | P8: 4901490 | Q8: 4197335 | R8: 13395293
A9: S1007 | B9: Riya Kulkarni | C9: C202 | D9: Data Science | E9: B2 | F9: Saurabh | G9: Web | H9: 14549 | I9: DISC10 | J9: 0.1 | K9: 13000 | L9: 45316
A10: S1008 | B10: Aditya Iyer | C10: C203 | D10: Full Stack Dev | E10: B1 | F10: Priya | G10: Mobile | H10: 15858 | I10: DISC30 | J10: 0.3 | K10: 17000 | L10: 45336
A11: S1009 | B11: Kunal Singh | C11: C201 | D11: Data Analytics | E11: B3 | F11: Amit | G11: Web | H11: 14187 | I11: DISC20 | J11: 0.2 | K11: 14000 | L11: 45302
A12: S1010 | B12: Neha Verma | C12: C203 | D12: Full Stack Dev | E12: B3 | F12: Amit | G12: Tablet | H12: 15899 | I12: DISC30 | J12: 0.3 | K12: 17000 | L12: 45345
A13: S1011 | B13: Dev Patel | C13: C201 | D13: Data Analytics | E13: B1 | F13: Saurabh | G13: Mobile | H13: 13643 | I13: DISC30 | J13: 0.3 | K13: 14000 | L13: 45296
A14: S1012 | B14: Sneha Joshi | C14: C203 | D14: Full Stack Dev | E14: B1 | F14: Amit | G14: Mobile | H14: 16620 | K14: 17000 | L14: 45301
A15: S1013 | B15: Aditya Mehta | C15: C202 | D15: Data Science | E15: B3 | F15: Amit | G15: Tablet | H15: 12076 | I15: DISC15 | K15: 13000 | L15: 45319
A16: S1014 | B16: Kunal Joshi | C16: C204 | D16: UI UX Design | E16: B2 | F16: Saurabh | G16: Web | H16: 9087 | K16: 9000 | L16: 45297
A17: S1015 | B17: Dev Kulkarni | C17: C201 | D17: Data Analytics | E17: B1 | F17: Amit | G17: Web | H17: 15244 | K17: 14000 | L17: 45330
A18: S1016 | B18: Riya Verma | C18: C204 | D18: UI UX Design | E18: B3 | F18: Priya | G18: Tablet | H18: 8029 | I18: DISC15 | K18: 9000 | L18: 45347
A19: S1017 | B19: Aarav Singh | C19: C201 | D19: Data Analytics | E19: B3 | F19: Amit | G19: Mobile | H19: 15148 | I19: DISC30 | J19: 0.3 | K19: 14000 | L19: 45299
A20: S1018 | B20: Aditya Verma | C20: C202 | D20: Data Science | E20: B2 | F20: Saurabh | G20: Tablet | H20: 14587 | I20: DISC30 | J20: 0.3 | K20: 13000 | L20: 45324
A21: S1019 | B21: Dev Mehta | C21: C201 | D21: Data Analytics | E21: B3 | F21: Priya | G21: Tablet | H21: 14079 | I21: DISC15 | K21: 14000 | L21: 45304
A22: S1020 | B22: Karan Jain | C22: C202 | D22: Data Science | E22: B3 | F22: Amit | G22: Web | H22: 13453 | I22: DISC30 | J22: 0.3 | K22: 13000 | L22: 45323
A23: S1021 | B23: Aarav Shah | C23: C203 | D23: Full Stack Dev | E23: B2 | F23: Saurabh | G23: Web | H23: 15986 | I23: DISC15 | K23: 17000 | L23: 45352
A24: S1022 | B24: Riya Shah | C24: C204 | D24: UI UX Design | E24: B1 | F24: Amit | G24: Web | H24: 7525 | K24: 9000 | L24: 45352
A25: S1023 | B25: Manish Mehta | C25: C203 | D25: Full Stack Dev | E25: B3 | F25: Amit | G25: Mobile | H25: 18950 | I25: DISC20 | J25: 0.2 | K25: 17000 | L25: 45351
A26: S1024 | B26: Manish Patel | C26: C202 | D26: Data Science | E26: B3 | F26: Priya | G26: Mobile | H26: 13751 | I26: DISC30 | J26: 0.3 | K26: 13000 | L26: 45320
A27: S1025 | B27: Kunal Gupta | C27: C204 | D27: UI UX Design | E27: B1 | F27: Saurabh | G27: Web | H27: 7262 | I27: DISC30 | J27: 0.3 | K27: 9000 | L27: 45293
A28: S1026 | B28: Kavita Gupta | C28: C202 | D28: Data Science | E28: B3 | F28: Saurabh | G28: Web | H28: 11290 | I28: DISC10 | J28: 0.1 | K28: 13000 | L28: 45306
A29: S1027 | B29: Riya Kulkarni | C29: C203 | D29: Full Stack Dev | E29: B1 | F29: Amit | G29: Web | H29: 16140 | K29: 17000 | L29: 45305
A30: S1028 | B30: Manish Mehta | C30: C204 | D30: UI UX Design | E30: B1 | F30: Priya | G30: Mobile | H30: 7779 | I30: DISC10 | J30: 0.1 | K30: 9000 | L30: 45298
A31: S1029 | B31: Rohit Verma | C31: C203 | D31: Full Stack Dev | E31: B2 | F31: Priya | G31: Mobile | H31: 18538 | I31: DISC10 | J31: 0.1 | K31: 17000 | L31: 45335
A32: S1030 | B32: Rohit Singh | C32: C201 | D32: Data Analytics | E32: B1 | F32: Priya | G32: Tablet | H32: 13389 | I32: DISC10 | J32: 0.1 | K32: 14000 | L32: 45307
A33: S1031 | B33: Sneha Patil | C33: C204 | D33: UI UX Design | E33: B1 | F33: Priya | G33: Web | H33: 8140 | K33: 9000 | L33: 45307
A34: S1032 | B34: Meera Shah | C34: C204 | D34: UI UX Design | E34: B3 | F34: Saurabh | G34: Web | H34: 9671 | I34: DISC15 | K34: 9000 | L34: 45345
A35: S1033 | B35: Aarav Shah | C35: C202 | D35: Data Science | E35: B1 | F35: Priya | G35: Mobile | H35: 12971 | I35: DISC20 | J35: 0.2 | K35: 13000 | L35: 45347
A36: S1034 | B36: Rahul Kulkarni | C36: C202 | D36: Data Science | E36: B2 | F36: Saurabh | G36: Mobile | H36: 12086 | K36: 13000 | L36: 45310
A37: S1035 | B37: Rahul Desai | C37: C204 | D37: UI UX Design | E37: B1 | F37: Saurabh | G37: Mobile | H37: 7891 | I37: DISC10 | J37: 0.1 | K37: 9000 | L37: 45329
A38: S1036 | B38: Anjali Gupta | C38: C201 | D38: Data Analytics | E38: B3 | F38: Priya | G38: Web | H38: 12205 | I38: DISC15 | K38: 14000 | L38: 45322
A39: S1037 | B39: Manish Nair | C39: C202 | D39: Data Science | E39: B1 | F39: Amit | G39: Web | H39: 14487 | I39: DISC20 | J39: 0.2 | K39: 13000 | L39: 45296
A40: S1038 | B40: Kavita Shah | C40: C202 | D40: Data Science | E40: B2 | F40: Saurabh | G40: Tablet | H40: 12008 | I40: DISC15 | K40: 13000 | L40: 45330
A41: S1039 | B41: Aarav Joshi | C41: C201 | D41: Data Analytics | E41: B2 | F41: Amit | G41: Tablet | H41: 14315 | I41: DISC15 | K41: 14000 | L41: 45312
A42: S1040 | B42: Kunal Rao | C42: C202 | D42: Data Science | E42: B3 | F42: Amit | G42: Mobile | H42: 11977 | I42: DISC30 | J42: 0.3 | K42: 13000 | L42: 45317
A43: S1041 | B43: Karan Singh | C43: C203 | D43: Full Stack Dev | E43: B2 | F43: Priya | G43: Web | H43: 15038 | K43: 17000 | L43: 45331
A44: S1042 | B44: Kavita Shah | C44: C201 | D44: Data Analytics | E44: B3 | F44: Saurabh | G44: Tablet | H44: 13086 | I44: DISC20 | J44: 0.2 | K44: 14000 | L44: 45351
A45: S1043 | B45: Pooja Shah | C45: C202 | D45: Data Science | E45: B2 | F45: Priya | G45: Web | H45: 12794 | I45: DISC15 | K45: 13000 | L45: 45337
A46: S1044 | B46: Aditya Joshi | C46: C201 | D46: Data Analytics | E46: B3 | F46: Amit | G46: Mobile | H46: 15816 | I46: DISC10 | J46: 0.1 | K46: 14000 | L46: 45352
A47: S1045 | B47: Kunal Mehta | C47: C203 | D47: Full Stack Dev | E47: B1 | F47: Saurabh | G47: Tablet | H47: 17266 | I47: DISC20 | J47: 0.2 | K47: 17000 | L47: 45309
A48: S1046 | B48: Aditya Joshi | C48: C202 | D48: Data Science | E48: B3 | F48: Priya | G48: Web | H48: 13815 | I48: DISC30 | J48: 0.3 | K48: 13000 | L48: 45324
A49: S1047 | B49: Neha Rao | C49: C201 | D49: Data Analytics | E49: B1 | F49: Amit | G49: Mobile | H49: 15397 | I49: DISC30 | J49: 0.3 | K49: 14000 | L49: 45294
A50: S1048 | B50: Aarav Jain | C50: C202 | D50: Data Science | E50: B3 | F50: Priya | G50: Web | H50: 14036 | K50: 13000 | L50: 45327
A51: S1049 | B51: Anjali Verma | C51: C201 | D51: Data Analytics | E51: B1 | F51: Saurabh | G51: Tablet | H51: 15702 | I51: DISC20 | J51: 0.2 | K51: 14000 | L51: 45326
A52: S1050 | B52: Aarav Nair | C52: C203 | D52: Full Stack Dev | E52: B3 | F52: Amit | G52: Web | H52: 16760 | I52: DISC20 | J52: 0.2 | K52: 17000 | L52: 45294
A53: S1051 | B53: Aditya Jain | C53: C201 | D53: Data Analytics | E53: B2 | F53: Saurabh | G53: Tablet | H53: 13022 | I53: DISC10 | J53: 0.1 | K53: 14000 | L53: 45314
A54: S1052 | B54: Dev Gupta | C54: C204 | D54: UI UX Design | E54: B3 | F54: Amit | G54: Web | H54: 10791 | I54: DISC20 | J54: 0.2 | K54: 9000 | L54: 45347
A55: S1053 | B55: Karan Patel | C55: C202 | D55: Data Science | E55: B2 | F55: Saurabh | G55: Web | H55: 14016 | I55: DISC30 | J55: 0.3 | K55: 13000 | L55: 45342
A56: S1054 | B56: Kunal Verma | C56: C202 | D56: Data Science | E56: B2 | F56: Saurabh | G56: Tablet | H56: 11442 | K56: 13000 | L56: 45347
A57: S1055 | B57: Aarav Nair | C57: C204 | D57: UI UX Design | E57: B1 | F57: Saurabh | G57: Mobile | H57: 8432 | I57: DISC30 | J57: 0.3 | K57: 9000 | L57: 45344
A58: S1056 | B58: Dev Nair | C58: C202 | D58: Data Science | E58: B1 | F58: Saurabh | G58: Tablet | H58: 11791 | K58: 13000 | L58: 45313
A59: S1057 | B59: Aditya Nair | C59: C201 | D59: Data Analytics | E59: B2 | F59: Priya | G59: Tablet | H59: 14086 | K59: 14000 | L59: 45335
A60: S1058 | B60: Meera Gupta | C60: C203 | D60: Full Stack Dev | E60: B1 | F60: Saurabh | G60: Mobile | H60: 15731 | I60: DISC15 | K60: 17000 | L60: 45308
A61: S1059 | B61: Aarav Shah | C61: C204 | D61: UI UX Design | E61: B2 | F61: Amit | G61: Mobile | H61: 8787 | I61: DISC15 | K61: 9000 | L61: 45324
A62: S1060 | B62: Riya Verma | C62: C202 | D62: Data Science | E62: B2 | F62: Saurabh | G62: Tablet | H62: 12786 | I62: DISC10 | J62: 0.1 | K62: 13000 | L62: 45325
A63: S1061 | B63: Kunal Patel | C63: C202 | D63: Data Science | E63: B2 | F63: Priya | G63: Web | H63: 14886 | I63: DISC30 | J63: 0.3 | K63: 13000 | L63: 45331
A64: S1062 | B64: Pooja Singh | C64: C201 | D64: Data Analytics | E64: B3 | F64: Priya | G64: Tablet | H64: 13266 | K64: 14000 | L64: 45312
A65: S1063 | B65: Rahul Desai | C65: C203 | D65: Full Stack Dev | E65: B3 | F65: Saurabh | G65: Web | H65: 16722 | K65: 17000 | L65: 45335
A66: S1064 | B66: Anjali Mehta | C66: C203 | D66: Full Stack Dev | E66: B2 | F66: Amit | G66: Web | H66: 16244 | I66: DISC30 | J66: 0.3 | K66: 17000 | L66: 45305
A67: S1065 | B67: Rahul Patel | C67: C203 | D67: Full Stack Dev | E67: B2 | F67: Priya | G67: Mobile | H67: 17767 | I67: DISC20 | J67: 0.2 | K67: 17000 | L67: 45324
A68: S1066 | B68: Neha Patel | C68: C202 | D68: Data Science | E68: B3 | F68: Saurabh | G68: Mobile | H68: 13111 | I68: DISC15 | K68: 13000 | L68: 45313
A69: S1067 | B69: Riya Nair | C69: C202 | D69: Data Science | E69: B3 | F69: Priya | G69: Web | H69: 14303 | I69: DISC20 | J69: 0.2 | K69: 13000 | L69: 45301
A70: S1068 | B70: Aarav Kulkarni | C70: C202 | D70: Data Science | E70: B2 | F70: Amit | G70: Web | H70: 12865 | K70: 13000 | L70: 45348
A71: S1069 | B71: Rohit Joshi | C71: C202 | D71: Data Science | E71: B3 | F71: Amit | G71: Mobile | H71: 13024 | K71: 13000 | L71: 45307
A72: S1070 | B72: Karan Singh | C72: C201 | D72: Data Analytics | E72: B1 | F72: Priya | G72: Web | H72: 12720 | I72: DISC15 | K72: 14000 | L72: 45321
A73: S1071 | B73: Aarav Gupta | C73: C202 | D73: Data Science | E73: B1 | F73: Priya | G73: Web | H73: 14282 | K73: 13000 | L73: 45334
A74: S1072 | B74: Manish Gupta | C74: C203 | D74: Full Stack Dev | E74: B2 | F74: Amit | G74: Tablet | H74: 18653 | I74: DISC15 | K74: 17000 | L74: 45319
A75: S1073 | B75: Meera Gupta | C75: C204 | D75: UI UX Design | E75: B1 | F75: Amit | G75: Mobile | H75: 8843 | I75: DISC30 | J75: 0.3 | K75: 9000 | L75: 45340
A76: S1074 | B76: Sneha Nair | C76: C203 | D76: Full Stack Dev | E76: B3 | F76: Priya | G76: Tablet | H76: 15979 | I76: DISC30 | J76: 0.3 | K76: 17000 | L76: 45320
A77: S1075 | B77: Riya Desai | C77: C203 | D77: Full Stack Dev | E77: B1 | F77: Priya | G77: Mobile | H77: 16309 | I77: DISC15 | K77: 17000 | L77: 45297
A78: S1076 | B78: Karan Mehta | C78: C202 | D78: Data Science | E78: B2 | F78: Amit | G78: Web | H78: 13893 | I78: DISC20 | J78: 0.2 | K78: 13000 | L78: 45296
A79: S1077 | B79: Rahul Verma | C79: C203 | D79: Full Stack Dev | E79: B3 | F79: Priya | G79: Mobile | H79: 15255 | I79: DISC20 | J79: 0.2 | K79: 17000 | L79: 45345
A80: S1078 | B80: Rahul Verma | C80: C201 | D80: Data Analytics | E80: B3 | F80: Priya | G80: Mobile | H80: 12024 | I80: DISC30 | J80: 0.3 | K80: 14000 | L80: 45311
A81: S1079 | B81: Dev Verma | C81: C204 | D81: UI UX Design | E81: B3 | F81: Amit | G81: Tablet | H81: 9236 | I81: DISC15 | K81: 9000 | L81: 45349
A82: S1080 | B82: Sneha Iyer | C82: C202 | D82: Data Science | E82: B2 | F82: Priya | G82: Mobile | H82: 11118 | K82: 13000 | L82: 45313
A83: S1081 | B83: Rohit Singh | C83: C204 | D83: UI UX Design | E83: B3 | F83: Saurabh | G83: Mobile | H83: 10766 | I83: DISC20 | J83: 0.2 | K83: 9000 | L83: 45331
A84: S1082 | B84: Manish Kulkarni | C84: C204 | D84: UI UX Design | E84: B3 | F84: Amit | G84: Tablet | H84: 7111 | I84: DISC10 | J84: 0.1 | K84: 9000 | L84: 45333
A85: S1083 | B85: Rahul Mehta | C85: C204 | D85: UI UX Design | E85: B1 | F85: Saurabh | G85: Mobile | H85: 8552 | I85: DISC30 | J85: 0.3 | K85: 9000 | L85: 45305
A86: S1084 | B86: Neha Jain | C86: C203 | D86: Full Stack Dev | E86: B2 | F86: Priya | G86: Mobile | H86: 16033 | I86: DISC10 | J86: 0.1 | K86: 17000 | L86: 45322
A87: S1085 | B87: Aarav Desai | C87: C201 | D87: Data Analytics | E87: B2 | F87: Saurabh | G87: Tablet | H87: 12281 | I87: DISC10 | J87: 0.1 | K87: 14000 | L87: 45340
A88: S1086 | B88: Aarav Patil | C88: C202 | D88: Data Science | E88: B1 | F88: Amit | G88: Web | H88: 11977 | I88: DISC20 | J88: 0.2 | K88: 13000 | L88: 45322
A89: S1087 | B89: Rohit Shah | C89: C202 | D89: Data Science | E89: B2 | F89: Amit | G89: Mobile | H89: 14141 | I89: DISC30 | J89: 0.3 | K89: 13000 | L89: 45302
A90: S1088 | B90: Kavita Joshi | C90: C201 | D90: Data Analytics | E90: B1 | F90: Priya | G90: Web | H90: 14370 | I90: DISC10 | J90: 0.1 | K90: 14000 | L90: 45351
A91: S1089 | B91: Aditya Joshi | C91: C204 | D91: UI UX Design | E91: B2 | F91: Amit | G91: Web | H91: 7311 | I91: DISC15 | K91: 9000 | L91: 45336
A92: S1090 | B92: Meera Singh | C92: C202 | D92: Data Science | E92: B1 | F92: Amit | G92: Mobile | H92: 14482 | I92: DISC15 | K92: 13000 | L92: 45343
A93: S1091 | B93: Riya Patel | C93: C201 | D93: Data Analytics | E93: B2 | F93: Amit | G93: Mobile | H93: 14709 | I93: DISC30 | J93: 0.3 | K93: 14000 | L93: 45296
A94: S1092 | B94: Manish Singh | C94: C203 | D94: Full Stack Dev | E94: B1 | F94: Priya | G94: Mobile | H94: 15432 | K94: 17000 | L94: 45315
A95: S1093 | B95: Rohit Nair | C95: C204 | D95: UI UX Design | E95: B3 | F95: Saurabh | G95: Mobile | H95: 7721 | I95: DISC15 | K95: 9000 | L95: 45333
A96: S1094 | B96: Aditya Joshi | C96: C204 | D96: UI UX Design | E96: B2 | F96: Priya | G96: Tablet | H96: 9426 | I96: DISC30 | J96: 0.3 | K96: 9000 | L96: 45312
A97: S1095 | B97: Meera Patil | C97: C201 | D97: Data Analytics | E97: B2 | F97: Priya | G97: Web | H97: 15073 | K97: 14000 | L97: 45328
A98: S1096 | B98: Kavita Singh | C98: C204 | D98: UI UX Design | E98: B2 | F98: Saurabh | G98: Mobile | H98: 10485 | I98: DISC30 | J98: 0.3 | K98: 9000 | L98: 45303
A99: S1097 | B99: Neha Patil | C99: C203 | D99: Full Stack Dev | E99: B2 | F99: Priya | G99: Mobile | H99: 18605 | I99: DISC15 | K99: 17000 | L99: 45336
A100: S1098 | B100: Kunal Rao | C100: C201 | D100: Data Analytics | E100: B3 | F100: Saurabh | G100: Web | H100: 12988 | K100: 14000 | L100: 45323
...

Sheet Q12
A1: StudentID | B1: StudentName | C1: CourseID | D1: CourseName | E1: BatchID | F1: MentorName | G1: Platform | H1: PaymentAmount | I1: DiscountCode | J1: DiscountPercent | K1: TargetRevenue | L1: PaymentDate | N1: Sum of Net Revenue
A2: S1000 | B2: Rohit Shah | C2: C201 | D2: Data Analytics | E2: B3 | F2: Priya | G2: Web | H2: 12914 | I2: DISC20 | J2: 0.2 | K2: 14000 | L2: 45339 | N2: -1.6208305e+09
A3: S1001 | B3: Riya Singh | C3: C201 | D3: Data Analytics | E3: B3 | F3: Priya | G3: Web | H3: 12122 | I3: DISC10 | J3: 0.1 | K3: 14000 | L3: 45305
A4: S1002 | B4: Sneha Gupta | C4: C201 | D4: Data Analytics | E4: B3 | F4: Saurabh | G4: Tablet | H4: 14661 | I4: DISC15 | K4: 14000 | L4: 45318
A5: S1003 | B5: Sneha Iyer | C5: C203 | D5: Full Stack Dev | E5: B1 | F5: Saurabh | G5: Tablet | H5: 16731 | I5: DISC30 | J5: 0.3 | K5: 17000 | L5: 45309
A6: S1004 | B6: Karan Patil | C6: C203 | D6: Full Stack Dev | E6: B1 | F6: Saurabh | G6: Mobile | H6: 15396 | I6: DISC30 | J6: 0.3 | K6: 17000 | L6: 45346
A7: S1005 | B7: Pooja Joshi | C7: C203 | D7: Full Stack Dev | E7: B1 | F7: Amit | G7: Mobile | H7: 17196 | I7: DISC10 | J7: 0.1 | K7: 17000 | L7: 45351
A8: S1006 | B8: Rahul Shah | C8: C203 | D8: Full Stack Dev | E8: B3 | F8: Amit | G8: Mobile | H8: 17364 | I8: DISC20 | J8: 0.2 | K8: 17000 | L8: 45337
A9: S1007 | B9: Riya Kulkarni | C9: C202 | D9: Data Science | E9: B2 | F9: Saurabh | G9: Web | H9: 14549 | I9: DISC10 | J9: 0.1 | K9: 13000 | L9: 45316
A10: S1008 | B10: Aditya Iyer | C10: C203 | D10: Full Stack Dev | E10: B1 | F10: Priya | G10: Mobile | H10: 15858 | I10: DISC30 | J10: 0.3 | K10: 17000 | L10: 45336
A11: S1009 | B11: Kunal Singh | C11: C201 | D11: Data Analytics | E11: B3 | F11: Amit | G11: Web | H11: 14187 | I11: DISC20 | J11: 0.2 | K11: 14000 | L11: 45302
A12: S1010 | B12: Neha Verma | C12: C203 | D12: Full Stack Dev | E12: B3 | F12: Amit | G12: Tablet | H12: 15899 | I12: DISC30 | J12: 0.3 | K12: 17000 | L12: 45345
A13: S1011 | B13: Dev Patel | C13: C201 | D13: Data Analytics | E13: B1 | F13: Saurabh | G13: Mobile | H13: 13643 | I13: DISC30 | J13: 0.3 | K13: 14000 | L13: 45296
A14: S1012 | B14: Sneha Joshi | C14: C203 | D14: Full Stack Dev | E14: B1 | F14: Amit | G14: Mobile | H14: 16620 | K14: 17000 | L14: 45301
A15: S1013 | B15: Aditya Mehta | C15: C202 | D15: Data Science | E15: B3 | F15: Amit | G15: Tablet | H15: 12076 | I15: DISC15 | K15: 13000 | L15: 45319
A16: S1014 | B16: Kunal Joshi | C16: C204 | D16: UI UX Design | E16: B2 | F16: Saurabh | G16: Web | H16: 9087 | K16: 9000 | L16: 45297
A17: S1015 | B17: Dev Kulkarni | C17: C201 | D17: Data Analytics | E17: B1 | F17: Amit | G17: Web | H17: 15244 | K17: 14000 | L17: 45330
A18: S1016 | B18: Riya Verma | C18: C204 | D18: UI UX Design | E18: B3 | F18: Priya | G18: Tablet | H18: 8029 | I18: DISC15 | K18: 9000 | L18: 45347
A19: S1017 | B19: Aarav Singh | C19: C201 | D19: Data Analytics | E19: B3 | F19: Amit | G19: Mobile | H19: 15148 | I19: DISC30 | J19: 0.3 | K19: 14000 | L19: 45299
A20: S1018 | B20: Aditya Verma | C20: C202 | D20: Data Science | E20: B2 | F20: Saurabh | G20: Tablet | H20: 14587 | I20: DISC30 | J20: 0.3 | K20: 13000 | L20: 45324
A21: S1019 | B21: Dev Mehta | C21: C201 | D21: Data Analytics | E21: B3 | F21: Priya | G21: Tablet | H21: 14079 | I21: DISC15 | K21: 14000 | L21: 45304
A22: S1020 | B22: Karan Jain | C22: C202 | D22: Data Science | E22: B3 | F22: Amit | G22: Web | H22: 13453 | I22: DISC30 | J22: 0.3 | K22: 13000 | L22: 45323
A23: S1021 | B23: Aarav Shah | C23: C203 | D23: Full Stack Dev | E23: B2 | F23: Saurabh | G23: Web | H23: 15986 | I23: DISC15 | K23: 17000 | L23: 45352
A24: S1022 | B24: Riya Shah | C24: C204 | D24: UI UX Design | E24: B1 | F24: Amit | G24: Web | H24: 7525 | K24: 9000 | L24: 45352
A25: S1023 | B25: Manish Mehta | C25: C203 | D25: Full Stack Dev | E25: B3 | F25: Amit | G25: Mobile | H25: 18950 | I25: DISC20 | J25: 0.2 | K25: 17000 | L25: 45351
A26: S1024 | B26: Manish Patel | C26: C202 | D26: Data Science | E26: B3 | F26: Priya | G26: Mobile | H26: 13751 | I26: DISC30 | J26: 0.3 | K26: 13000 | L26: 45320
A27: S1025 | B27: Kunal Gupta | C27: C204 | D27: UI UX Design | E27: B1 | F27: Saurabh | G27: Web | H27: 7262 | I27: DISC30 | J27: 0.3 | K27: 9000 | L27: 45293
A28: S1026 | B28: Kavita Gupta | C28: C202 | D28: Data Science | E28: B3 | F28: Saurabh | G28: Web | H28: 11290 | I28: DISC10 | J28: 0.1 | K28: 13000 | L28: 45306
A29: S1027 | B29: Riya Kulkarni | C29: C203 | D29: Full Stack Dev | E29: B1 | F29: Amit | G29: Web | H29: 16140 | K29: 17000 | L29: 45305
A30: S1028 | B30: Manish Mehta | C30: C204 | D30: UI UX Design | E30: B1 | F30: Priya | G30: Mobile | H30: 7779 | I30: DISC10 | J30: 0.1 | K30: 9000 | L30: 45298
A31: S1029 | B31: Rohit Verma | C31: C203 | D31: Full Stack Dev | E31: B2 | F31: Priya | G31: Mobile | H31: 18538 | I31: DISC10 | J31: 0.1 | K31: 17000 | L31: 45335
A32: S1030 | B32: Rohit Singh | C32: C201 | D32: Data Analytics | E32: B1 | F32: Priya | G32: Tablet | H32: 13389 | I32: DISC10 | J32: 0.1 | K32: 14000 | L32: 45307
A33: S1031 | B33: Sneha Patil | C33: C204 | D33: UI UX Design | E33: B1 | F33: Priya | G33: Web | H33: 8140 | K33: 9000 | L33: 45307
A34: S1032 | B34: Meera Shah | C34: C204 | D34: UI UX Design | E34: B3 | F34: Saurabh | G34: Web | H34: 9671 | I34: DISC15 | K34: 9000 | L34: 45345
A35: S1033 | B35: Aarav Shah | C35: C202 | D35: Data Science | E35: B1 | F35: Priya | G35: Mobile | H35: 12971 | I35: DISC20 | J35: 0.2 | K35: 13000 | L35: 45347
A36: S1034 | B36: Rahul Kulkarni | C36: C202 | D36: Data Science | E36: B2 | F36: Saurabh | G36: Mobile | H36: 12086 | K36: 13000 | L36: 45310
A37: S1035 | B37: Rahul Desai | C37: C204 | D37: UI UX Design | E37: B1 | F37: Saurabh | G37: Mobile | H37: 7891 | I37: DISC10 | J37: 0.1 | K37: 9000 | L37: 45329
A38: S1036 | B38: Anjali Gupta | C38: C201 | D38: Data Analytics | E38: B3 | F38: Priya | G38: Web | H38: 12205 | I38: DISC15 | K38: 14000 | L38: 45322
A39: S1037 | B39: Manish Nair | C39: C202 | D39: Data Science | E39: B1 | F39: Amit | G39: Web | H39: 14487 | I39: DISC20 | J39: 0.2 | K39: 13000 | L39: 45296
A40: S1038 | B40: Kavita Shah | C40: C202 | D40: Data Science | E40: B2 | F40: Saurabh | G40: Tablet | H40: 12008 | I40: DISC15 | K40: 13000 | L40: 45330
A41: S1039 | B41: Aarav Joshi | C41: C201 | D41: Data Analytics | E41: B2 | F41: Amit | G41: Tablet | H41: 14315 | I41: DISC15 | K41: 14000 | L41: 45312
A42: S1040 | B42: Kunal Rao | C42: C202 | D42: Data Science | E42: B3 | F42: Amit | G42: Mobile | H42: 11977 | I42: DISC30 | J42: 0.3 | K42: 13000 | L42: 45317
A43: S1041 | B43: Karan Singh | C43: C203 | D43: Full Stack Dev | E43: B2 | F43: Priya | G43: Web | H43: 15038 | K43: 17000 | L43: 45331
A44: S1042 | B44: Kavita Shah | C44: C201 | D44: Data Analytics | E44: B3 | F44: Saurabh | G44: Tablet | H44: 13086 | I44: DISC20 | J44: 0.2 | K44: 14000 | L44: 45351
A45: S1043 | B45: Pooja Shah | C45: C202 | D45: Data Science | E45: B2 | F45: Priya | G45: Web | H45: 12794 | I45: DISC15 | K45: 13000 | L45: 45337
A46: S1044 | B46: Aditya Joshi | C46: C201 | D46: Data Analytics | E46: B3 | F46: Amit | G46: Mobile | H46: 15816 | I46: DISC10 | J46: 0.1 | K46: 14000 | L46: 45352
A47: S1045 | B47: Kunal Mehta | C47: C203 | D47: Full Stack Dev | E47: B1 | F47: Saurabh | G47: Tablet | H47: 17266 | I47: DISC20 | J47: 0.2 | K47: 17000 | L47: 45309
A48: S1046 | B48: Aditya Joshi | C48: C202 | D48: Data Science | E48: B3 | F48: Priya | G48: Web | H48: 13815 | I48: DISC30 | J48: 0.3 | K48: 13000 | L48: 45324
A49: S1047 | B49: Neha Rao | C49: C201 | D49: Data Analytics | E49: B1 | F49: Amit | G49: Mobile | H49: 15397 | I49: DISC30 | J49: 0.3 | K49: 14000 | L49: 45294
A50: S1048 | B50: Aarav Jain | C50: C202 | D50: Data Science | E50: B3 | F50: Priya | G50: Web | H50: 14036 | K50: 13000 | L50: 45327
A51: S1049 | B51: Anjali Verma | C51: C201 | D51: Data Analytics | E51: B1 | F51: Saurabh | G51: Tablet | H51: 15702 | I51: DISC20 | J51: 0.2 | K51: 14000 | L51: 45326
A52: S1050 | B52: Aarav Nair | C52: C203 | D52: Full Stack Dev | E52: B3 | F52: Amit | G52: Web | H52: 16760 | I52: DISC20 | J52: 0.2 | K52: 17000 | L52: 45294
A53: S1051 | B53: Aditya Jain | C53: C201 | D53: Data Analytics | E53: B2 | F53: Saurabh | G53: Tablet | H53: 13022 | I53: DISC10 | J53: 0.1 | K53: 14000 | L53: 45314
A54: S1052 | B54: Dev Gupta | C54: C204 | D54: UI UX Design | E54: B3 | F54: Amit | G54: Web | H54: 10791 | I54: DISC20 | J54: 0.2 | K54: 9000 | L54: 45347
A55: S1053 | B55: Karan Patel | C55: C202 | D55: Data Science | E55: B2 | F55: Saurabh | G55: Web | H55: 14016 | I55: DISC30 | J55: 0.3 | K55: 13000 | L55: 45342
A56: S1054 | B56: Kunal Verma | C56: C202 | D56: Data Science | E56: B2 | F56: Saurabh | G56: Tablet | H56: 11442 | K56: 13000 | L56: 45347
A57: S1055 | B57: Aarav Nair | C57: C204 | D57: UI UX Design | E57: B1 | F57: Saurabh | G57: Mobile | H57: 8432 | I57: DISC30 | J57: 0.3 | K57: 9000 | L57: 45344
A58: S1056 | B58: Dev Nair | C58: C202 | D58: Data Science | E58: B1 | F58: Saurabh | G58: Tablet | H58: 11791 | K58: 13000 | L58: 45313
A59: S1057 | B59: Aditya Nair | C59: C201 | D59: Data Analytics | E59: B2 | F59: Priya | G59: Tablet | H59: 14086 | K59: 14000 | L59: 45335
A60: S1058 | B60: Meera Gupta | C60: C203 | D60: Full Stack Dev | E60: B1 | F60: Saurabh | G60: Mobile | H60: 15731 | I60: DISC15 | K60: 17000 | L60: 45308
A61: S1059 | B61: Aarav Shah | C61: C204 | D61: UI UX Design | E61: B2 | F61: Amit | G61: Mobile | H61: 8787 | I61: DISC15 | K61: 9000 | L61: 45324
A62: S1060 | B62: Riya Verma | C62: C202 | D62: Data Science | E62: B2 | F62: Saurabh | G62: Tablet | H62: 12786 | I62: DISC10 | J62: 0.1 | K62: 13000 | L62: 45325
A63: S1061 | B63: Kunal Patel | C63: C202 | D63: Data Science | E63: B2 | F63: Priya | G63: Web | H63: 14886 | I63: DISC30 | J63: 0.3 | K63: 13000 | L63: 45331
A64: S1062 | B64: Pooja Singh | C64: C201 | D64: Data Analytics | E64: B3 | F64: Priya | G64: Tablet | H64: 13266 | K64: 14000 | L64: 45312
A65: S1063 | B65: Rahul Desai | C65: C203 | D65: Full Stack Dev | E65: B3 | F65: Saurabh | G65: Web | H65: 16722 | K65: 17000 | L65: 45335
A66: S1064 | B66: Anjali Mehta | C66: C203 | D66: Full Stack Dev | E66: B2 | F66: Amit | G66: Web | H66: 16244 | I66: DISC30 | J66: 0.3 | K66: 17000 | L66: 45305
A67: S1065 | B67: Rahul Patel | C67: C203 | D67: Full Stack Dev | E67: B2 | F67: Priya | G67: Mobile | H67: 17767 | I67: DISC20 | J67: 0.2 | K67: 17000 | L67: 45324
A68: S1066 | B68: Neha Patel | C68: C202 | D68: Data Science | E68: B3 | F68: Saurabh | G68: Mobile | H68: 13111 | I68: DISC15 | K68: 13000 | L68: 45313
A69: S1067 | B69: Riya Nair | C69: C202 | D69: Data Science | E69: B3 | F69: Priya | G69: Web | H69: 14303 | I69: DISC20 | J69: 0.2 | K69: 13000 | L69: 45301
A70: S1068 | B70: Aarav Kulkarni | C70: C202 | D70: Data Science | E70: B2 | F70: Amit | G70: Web | H70: 12865 | K70: 13000 | L70: 45348
A71: S1069 | B71: Rohit Joshi | C71: C202 | D71: Data Science | E71: B3 | F71: Amit | G71: Mobile | H71: 13024 | K71: 13000 | L71: 45307
A72: S1070 | B72: Karan Singh | C72: C201 | D72: Data Analytics | E72: B1 | F72: Priya | G72: Web | H72: 12720 | I72: DISC15 | K72: 14000 | L72: 45321
A73: S1071 | B73: Aarav Gupta | C73: C202 | D73: Data Science | E73: B1 | F73: Priya | G73: Web | H73: 14282 | K73: 13000 | L73: 45334
A74: S1072 | B74: Manish Gupta | C74: C203 | D74: Full Stack Dev | E74: B2 | F74: Amit | G74: Tablet | H74: 18653 | I74: DISC15 | K74: 17000 | L74: 45319
A75: S1073 | B75: Meera Gupta | C75: C204 | D75: UI UX Design | E75: B1 | F75: Amit | G75: Mobile | H75: 8843 | I75: DISC30 | J75: 0.3 | K75: 9000 | L75: 45340
A76: S1074 | B76: Sneha Nair | C76: C203 | D76: Full Stack Dev | E76: B3 | F76: Priya | G76: Tablet | H76: 15979 | I76: DISC30 | J76: 0.3 | K76: 17000 | L76: 45320
A77: S1075 | B77: Riya Desai | C77: C203 | D77: Full Stack Dev | E77: B1 | F77: Priya | G77: Mobile | H77: 16309 | I77: DISC15 | K77: 17000 | L77: 45297
A78: S1076 | B78: Karan Mehta | C78: C202 | D78: Data Science | E78: B2 | F78: Amit | G78: Web | H78: 13893 | I78: DISC20 | J78: 0.2 | K78: 13000 | L78: 45296
A79: S1077 | B79: Rahul Verma | C79: C203 | D79: Full Stack Dev | E79: B3 | F79: Priya | G79: Mobile | H79: 15255 | I79: DISC20 | J79: 0.2 | K79: 17000 | L79: 45345
A80: S1078 | B80: Rahul Verma | C80: C201 | D80: Data Analytics | E80: B3 | F80: Priya | G80: Mobile | H80: 12024 | I80: DISC30 | J80: 0.3 | K80: 14000 | L80: 45311
A81: S1079 | B81: Dev Verma | C81: C204 | D81: UI UX Design | E81: B3 | F81: Amit | G81: Tablet | H81: 9236 | I81: DISC15 | K81: 9000 | L81: 45349
A82: S1080 | B82: Sneha Iyer | C82: C202 | D82: Data Science | E82: B2 | F82: Priya | G82: Mobile | H82: 11118 | K82: 13000 | L82: 45313
A83: S1081 | B83: Rohit Singh | C83: C204 | D83: UI UX Design | E83: B3 | F83: Saurabh | G83: Mobile | H83: 10766 | I83: DISC20 | J83: 0.2 | K83: 9000 | L83: 45331
A84: S1082 | B84: Manish Kulkarni | C84: C204 | D84: UI UX Design | E84: B3 | F84: Amit | G84: Tablet | H84: 7111 | I84: DISC10 | J84: 0.1 | K84: 9000 | L84: 45333
A85: S1083 | B85: Rahul Mehta | C85: C204 | D85: UI UX Design | E85: B1 | F85: Saurabh | G85: Mobile | H85: 8552 | I85: DISC30 | J85: 0.3 | K85: 9000 | L85: 45305
A86: S1084 | B86: Neha Jain | C86: C203 | D86: Full Stack Dev | E86: B2 | F86: Priya | G86: Mobile | H86: 16033 | I86: DISC10 | J86: 0.1 | K86: 17000 | L86: 45322
A87: S1085 | B87: Aarav Desai | C87: C201 | D87: Data Analytics | E87: B2 | F87: Saurabh | G87: Tablet | H87: 12281 | I87: DISC10 | J87: 0.1 | K87: 14000 | L87: 45340
A88: S1086 | B88: Aarav Patil | C88: C202 | D88: Data Science | E88: B1 | F88: Amit | G88: Web | H88: 11977 | I88: DISC20 | J88: 0.2 | K88: 13000 | L88: 45322
A89: S1087 | B89: Rohit Shah | C89: C202 | D89: Data Science | E89: B2 | F89: Amit | G89: Mobile | H89: 14141 | I89: DISC30 | J89: 0.3 | K89: 13000 | L89: 45302
A90: S1088 | B90: Kavita Joshi | C90: C201 | D90: Data Analytics | E90: B1 | F90: Priya | G90: Web | H90: 14370 | I90: DISC10 | J90: 0.1 | K90: 14000 | L90: 45351
A91: S1089 | B91: Aditya Joshi | C91: C204 | D91: UI UX Design | E91: B2 | F91: Amit | G91: Web | H91: 7311 | I91: DISC15 | K91: 9000 | L91: 45336
A92: S1090 | B92: Meera Singh | C92: C202 | D92: Data Science | E92: B1 | F92: Amit | G92: Mobile | H92: 14482 | I92: DISC15 | K92: 13000 | L92: 45343
A93: S1091 | B93: Riya Patel | C93: C201 | D93: Data Analytics | E93: B2 | F93: Amit | G93: Mobile | H93: 14709 | I93: DISC30 | J93: 0.3 | K93: 14000 | L93: 45296
A94: S1092 | B94: Manish Singh | C94: C203 | D94: Full Stack Dev | E94: B1 | F94: Priya | G94: Mobile | H94: 15432 | K94: 17000 | L94: 45315
A95: S1093 | B95: Rohit Nair | C95: C204 | D95: UI UX Design | E95: B3 | F95: Saurabh | G95: Mobile | H95: 7721 | I95: DISC15 | K95: 9000 | L95: 45333
A96: S1094 | B96: Aditya Joshi | C96: C204 | D96: UI UX Design | E96: B2 | F96: Priya | G96: Tablet | H96: 9426 | I96: DISC30 | J96: 0.3 | K96: 9000 | L96: 45312
A97: S1095 | B97: Meera Patil | C97: C201 | D97: Data Analytics | E97: B2 | F97: Priya | G97: Web | H97: 15073 | K97: 14000 | L97: 45328
A98: S1096 | B98: Kavita Singh | C98: C204 | D98: UI UX Design | E98: B2 | F98: Saurabh | G98: Mobile | H98: 10485 | I98: DISC30 | J98: 0.3 | K98: 9000 | L98: 45303
A99: S1097 | B99: Neha Patil | C99: C203 | D99: Full Stack Dev | E99: B2 | F99: Priya | G99: Mobile | H99: 18605 | I99: DISC15 | K99: 17000 | L99: 45336
A100: S1098 | B100: Kunal Rao | C100: C201 | D100: Data Analytics | E100: B3 | F100: Saurabh | G100: Web | H100: 12988 | K100: 14000 | L100: 45323
...

Sheet Q13
A1: Sales & Course Revenue Analytics Dashboard
A30: StudentID | B30: StudentName | C30: CourseID | D30: CourseName | E30: BatchID | F30: MentorName | G30: Platform | H30: PaymentAmount | I30: DiscountCode | J30: DiscountPercent | K30: TargetRevenue | L30: PaymentDate | M30: Performance Status | O30: Row Labels | P30: Sum of PaymentAmount
A31: S1000 | B31: Rohit Shah | C31: C201 | D31: Data Analytics | E31: B3 | F31: Priya | G31: Web | H31: 12914 | I31: DISC20 | J31: 0.2 | K31: 14000 | L31: 45339 | M31: =IF(H31>=K31,"Target Achieved","Below Target") -> Below Target | O31: Data Analytics | P31: 3507731
A32: S1001 | B32: Riya Singh | C32: C201 | D32: Data Analytics | E32: B3 | F32: Priya | G32: Web | H32: 12122 | I32: DISC10 | J32: 0.1 | K32: 14000 | L32: 45305 | M32: =IF(H32>=K32,"Target Achieved","Below Target") -> Below Target | O32: Data Science | P32: 3155748
A33: S1002 | B33: Sneha Gupta | C33: C201 | D33: Data Analytics | E33: B3 | F33: Saurabh | G33: Tablet | H33: 14661 | I33: DISC15 | K33: 14000 | L33: 45318 | M33: =IF(H33>=K33,"Target Achieved","Below Target") -> Target Achieved | O33: Full Stack Dev | P33: 4540207
A34: S1003 | B34: Sneha Iyer | C34: C203 | D34: Full Stack Dev | E34: B1 | F34: Saurabh | G34: Tablet | H34: 16731 | I34: DISC30 | J34: 0.3 | K34: 17000 | L34: 45309 | M34: =IF(H34>=K34,"Target Achieved","Below Target") -> Below Target | O34: UI UX Design | P34: 2191607
A35: S1004 | B35: Karan Patil | C35: C203 | D35: Full Stack Dev | E35: B1 | F35: Saurabh | G35: Mobile | H35: 15396 | I35: DISC30 | J35: 0.3 | K35: 17000 | L35: 45346 | M35: =IF(H35>=K35,"Target Achieved","Below Target") -> Below Target | O35: Grand Total | P35: 13395293
A36: S1005 | B36: Pooja Joshi | C36: C203 | D36: Full Stack Dev | E36: B1 | F36: Amit | G36: Mobile | H36: 17196 | I36: DISC10 | J36: 0.1 | K36: 17000 | L36: 45351 | M36: =IF(H36>=K36,"Target Achieved","Below Target") -> Target Achieved
A37: S1006 | B37: Rahul Shah | C37: C203 | D37: Full Stack Dev | E37: B3 | F37: Amit | G37: Mobile | H37: 17364 | I37: DISC20 | J37: 0.2 | K37: 17000 | L37: 45337 | M37: =IF(H37>=K37,"Target Achieved","Below Target") -> Target Achieved | O37: Row Labels | P37: Sum of PaymentAmount
A38: S1007 | B38: Riya Kulkarni | C38: C202 | D38: Data Science | E38: B2 | F38: Saurabh | G38: Web | H38: 14549 | I38: DISC10 | J38: 0.1 | K38: 13000 | L38: 45316 | M38: =IF(H38>=K38,"Target Achieved","Below Target") -> Target Achieved | O38: Jan | P38: 6584355
A39: S1008 | B39: Aditya Iyer | C39: C203 | D39: Full Stack Dev | E39: B1 | F39: Priya | G39: Mobile | H39: 15858 | I39: DISC30 | J39: 0.3 | K39: 17000 | L39: 45336 | M39: =IF(H39>=K39,"Target Achieved","Below Target") -> Below Target | O39: Feb | P39: 6606168
A40: S1009 | B40: Kunal Singh | C40: C201 | D40: Data Analytics | E40: B3 | F40: Amit | G40: Web | H40: 14187 | I40: DISC20 | J40: 0.2 | K40: 14000 | L40: 45302 | M40: =IF(H40>=K40,"Target Achieved","Below Target") -> Target Achieved | O40: Mar | P40: 204770
A41: S1010 | B41: Neha Verma | C41: C203 | D41: Full Stack Dev | E41: B3 | F41: Amit | G41: Tablet | H41: 15899 | I41: DISC30 | J41: 0.3 | K41: 17000 | L41: 45345 | M41: =IF(H41>=K41,"Target Achieved","Below Target") -> Below Target | O41: Grand Total | P41: 13395293
A42: S1011 | B42: Dev Patel | C42: C201 | D42: Data Analytics | E42: B1 | F42: Saurabh | G42: Mobile | H42: 13643 | I42: DISC30 | J42: 0.3 | K42: 14000 | L42: 45296 | M42: =IF(H42>=K42,"Target Achieved","Below Target") -> Below Target
A43: S1012 | B43: Sneha Joshi | C43: C203 | D43: Full Stack Dev | E43: B1 | F43: Amit | G43: Mobile | H43: 16620 | K43: 17000 | L43: 45301 | M43: =IF(H43>=K43,"Target Achieved","Below Target") -> Below Target
A44: S1013 | B44: Aditya Mehta | C44: C202 | D44: Data Science | E44: B3 | F44: Amit | G44: Tablet | H44: 12076 | I44: DISC15 | K44: 13000 | L44: 45319 | M44: =IF(H44>=K44,"Target Achieved","Below Target") -> Below Target
A45: S1014 | B45: Kunal Joshi | C45: C204 | D45: UI UX Design | E45: B2 | F45: Saurabh | G45: Web | H45: 9087 | K45: 9000 | L45: 45297 | M45: =IF(H45>=K45,"Target Achieved","Below Target") -> Target Achieved
A46: S1015 | B46: Dev Kulkarni | C46: C201 | D46: Data Analytics | E46: B1 | F46: Amit | G46: Web | H46: 15244 | K46: 14000 | L46: 45330 | M46: =IF(H46>=K46,"Target Achieved","Below Target") -> Target Achieved
A47: S1016 | B47: Riya Verma | C47: C204 | D47: UI UX Design | E47: B3 | F47: Priya | G47: Tablet | H47: 8029 | I47: DISC15 | K47: 9000 | L47: 45347 | M47: =IF(H47>=K47,"Target Achieved","Below Target") -> Below Target
A48: S1017 | B48: Aarav Singh | C48: C201 | D48: Data Analytics | E48: B3 | F48: Amit | G48: Mobile | H48: 15148 | I48: DISC30 | J48: 0.3 | K48: 14000 | L48: 45299 | M48: =IF(H48>=K48,"Target Achieved","Below Target") -> Target Achieved
A49: S1018 | B49: Aditya Verma | C49: C202 | D49: Data Science | E49: B2 | F49: Saurabh | G49: Tablet | H49: 14587 | I49: DISC30 | J49: 0.3 | K49: 13000 | L49: 45324 | M49: =IF(H49>=K49,"Target Achieved","Below Target") -> Target Achieved
A50: S1019 | B50: Dev Mehta | C50: C201 | D50: Data Analytics | E50: B3 | F50: Priya | G50: Tablet | H50: 14079 | I50: DISC15 | K50: 14000 | L50: 45304 | M50: =IF(H50>=K50,"Target Achieved","Below Target") -> Target Achieved
A51: S1020 | B51: Karan Jain | C51: C202 | D51: Data Science | E51: B3 | F51: Amit | G51: Web | H51: 13453 | I51: DISC30 | J51: 0.3 | K51: 13000 | L51: 45323 | M51: =IF(H51>=K51,"Target Achieved","Below Target") -> Target Achieved
A52: S1021 | B52: Aarav Shah | C52: C203 | D52: Full Stack Dev | E52: B2 | F52: Saurabh | G52: Web | H52: 15986 | I52: DISC15 | K52: 17000 | L52: 45352 | M52: =IF(H52>=K52,"Target Achieved","Below Target") -> Below Target
A53: S1022 | B53: Riya Shah | C53: C204 | D53: UI UX Design | E53: B1 | F53: Amit | G53: Web | H53: 7525 | K53: 9000 | L53: 45352 | M53: =IF(H53>=K53,"Target Achieved","Below Target") -> Below Target
A54: S1023 | B54: Manish Mehta | C54: C203 | D54: Full Stack Dev | E54: B3 | F54: Amit | G54: Mobile | H54: 18950 | I54: DISC20 | J54: 0.2 | K54: 17000 | L54: 45351 | M54: =IF(H54>=K54,"Target Achieved","Below Target") -> Target Achieved
A55: S1024 | B55: Manish Patel | C55: C202 | D55: Data Science | E55: B3 | F55: Priya | G55: Mobile | H55: 13751 | I55: DISC30 | J55: 0.3 | K55: 13000 | L55: 45320 | M55: =IF(H55>=K55,"Target Achieved","Below Target") -> Target Achieved
A56: S1025 | B56: Kunal Gupta | C56: C204 | D56: UI UX Design | E56: B1 | F56: Saurabh | G56: Web | H56: 7262 | I56: DISC30 | J56: 0.3 | K56: 9000 | L56: 45293 | M56: =IF(H56>=K56,"Target Achieved","Below Target") -> Below Target
A57: S1026 | B57: Kavita Gupta | C57: C202 | D57: Data Science | E57: B3 | F57: Saurabh | G57: Web | H57: 11290 | I57: DISC10 | J57: 0.1 | K57: 13000 | L57: 45306 | M57: =IF(H57>=K57,"Target Achieved","Below Target") -> Below Target
A58: S1027 | B58: Riya Kulkarni | C58: C203 | D58: Full Stack Dev | E58: B1 | F58: Amit | G58: Web | H58: 16140 | K58: 17000 | L58: 45305 | M58: =IF(H58>=K58,"Target Achieved","Below Target") -> Below Target
A59: S1028 | B59: Manish Mehta | C59: C204 | D59: UI UX Design | E59: B1 | F59: Priya | G59: Mobile | H59: 7779 | I59: DISC10 | J59: 0.1 | K59: 9000 | L59: 45298 | M59: =IF(H59>=K59,"Target Achieved","Below Target") -> Below Target
A60: S1029 | B60: Rohit Verma | C60: C203 | D60: Full Stack Dev | E60: B2 | F60: Priya | G60: Mobile | H60: 18538 | I60: DISC10 | J60: 0.1 | K60: 17000 | L60: 45335 | M60: =IF(H60>=K60,"Target Achieved","Below Target") -> Target Achieved
A61: S1030 | B61: Rohit Singh | C61: C201 | D61: Data Analytics | E61: B1 | F61: Priya | G61: Tablet | H61: 13389 | I61: DISC10 | J61: 0.1 | K61: 14000 | L61: 45307 | M61: =IF(H61>=K61,"Target Achieved","Below Target") -> Below Target
A62: S1031 | B62: Sneha Patil | C62: C204 | D62: UI UX Design | E62: B1 | F62: Priya | G62: Web | H62: 8140 | K62: 9000 | L62: 45307 | M62: =IF(H62>=K62,"Target Achieved","Below Target") -> Below Target
A63: S1032 | B63: Meera Shah | C63: C204 | D63: UI UX Design | E63: B3 | F63: Saurabh | G63: Web | H63: 9671 | I63: DISC15 | K63: 9000 | L63: 45345 | M63: =IF(H63>=K63,"Target Achieved","Below Target") -> Target Achieved
A64: S1033 | B64: Aarav Shah | C64: C202 | D64: Data Science | E64: B1 | F64: Priya | G64: Mobile | H64: 12971 | I64: DISC20 | J64: 0.2 | K64: 13000 | L64: 45347 | M64: =IF(H64>=K64,"Target Achieved","Below Target") -> Below Target
A65: S1034 | B65: Rahul Kulkarni | C65: C202 | D65: Data Science | E65: B2 | F65: Saurabh | G65: Mobile | H65: 12086 | K65: 13000 | L65: 45310 | M65: =IF(H65>=K65,"Target Achieved","Below Target") -> Below Target
A66: S1035 | B66: Rahul Desai | C66: C204 | D66: UI UX Design | E66: B1 | F66: Saurabh | G66: Mobile | H66: 7891 | I66: DISC10 | J66: 0.1 | K66: 9000 | L66: 45329 | M66: =IF(H66>=K66,"Target Achieved","Below Target") -> Below Target
A67: S1036 | B67: Anjali Gupta | C67: C201 | D67: Data Analytics | E67: B3 | F67: Priya | G67: Web | H67: 12205 | I67: DISC15 | K67: 14000 | L67: 45322 | M67: =IF(H67>=K67,"Target Achieved","Below Target") -> Below Target
A68: S1037 | B68: Manish Nair | C68: C202 | D68: Data Science | E68: B1 | F68: Amit | G68: Web | H68: 14487 | I68: DISC20 | J68: 0.2 | K68: 13000 | L68: 45296 | M68: =IF(H68>=K68,"Target Achieved","Below Target") -> Target Achieved
A69: S1038 | B69: Kavita Shah | C69: C202 | D69: Data Science | E69: B2 | F69: Saurabh | G69: Tablet | H69: 12008 | I69: DISC15 | K69: 13000 | L69: 45330 | M69: =IF(H69>=K69,"Target Achieved","Below Target") -> Below Target
A70: S1039 | B70: Aarav Joshi | C70: C201 | D70: Data Analytics | E70: B2 | F70: Amit | G70: Tablet | H70: 14315 | I70: DISC15 | K70: 14000 | L70: 45312 | M70: =IF(H70>=K70,"Target Achieved","Below Target") -> Target Achieved
A71: S1040 | B71: Kunal Rao | C71: C202 | D71: Data Science | E71: B3 | F71: Amit | G71: Mobile | H71: 11977 | I71: DISC30 | J71: 0.3 | K71: 13000 | L71: 45317 | M71: =IF(H71>=K71,"Target Achieved","Below Target") -> Below Target
A72: S1041 | B72: Karan Singh | C72: C203 | D72: Full Stack Dev | E72: B2 | F72: Priya | G72: Web | H72: 15038 | K72: 17000 | L72: 45331 | M72: =IF(H72>=K72,"Target Achieved","Below Target") -> Below Target
A73: S1042 | B73: Kavita Shah | C73: C201 | D73: Data Analytics | E73: B3 | F73: Saurabh | G73: Tablet | H73: 13086 | I73: DISC20 | J73: 0.2 | K73: 14000 | L73: 45351 | M73: =IF(H73>=K73,"Target Achieved","Below Target") -> Below Target
A74: S1043 | B74: Pooja Shah | C74: C202 | D74: Data Science | E74: B2 | F74: Priya | G74: Web | H74: 12794 | I74: DISC15 | K74: 13000 | L74: 45337 | M74: =IF(H74>=K74,"Target Achieved","Below Target") -> Below Target
A75: S1044 | B75: Aditya Joshi | C75: C201 | D75: Data Analytics | E75: B3 | F75: Amit | G75: Mobile | H75: 15816 | I75: DISC10 | J75: 0.1 | K75: 14000 | L75: 45352 | M75: =IF(H75>=K75,"Target Achieved","Below Target") -> Target Achieved
A76: S1045 | B76: Kunal Mehta | C76: C203 | D76: Full Stack Dev | E76: B1 | F76: Saurabh | G76: Tablet | H76: 17266 | I76: DISC20 | J76: 0.2 | K76: 17000 | L76: 45309 | M76: =IF(H76>=K76,"Target Achieved","Below Target") -> Target Achieved
A77: S1046 | B77: Aditya Joshi | C77: C202 | D77: Data Science | E77: B3 | F77: Priya | G77: Web | H77: 13815 | I77: DISC30 | J77: 0.3 | K77: 13000 | L77: 45324 | M77: =IF(H77>=K77,"Target Achieved","Below Target") -> Target Achieved
A78: S1047 | B78: Neha Rao | C78: C201 | D78: Data Analytics | E78: B1 | F78: Amit | G78: Mobile | H78: 15397 | I78: DISC30 | J78: 0.3 | K78: 14000 | L78: 45294 | M78: =IF(H78>=K78,"Target Achieved","Below Target") -> Target Achieved
A79: S1048 | B79: Aarav Jain | C79: C202 | D79: Data Science | E79: B3 | F79: Priya | G79: Web | H79: 14036 | K79: 13000 | L79: 45327 | M79: =IF(H79>=K79,"Target Achieved","Below Target") -> Target Achieved
A80: S1049 | B80: Anjali Verma | C80: C201 | D80: Data Analytics | E80: B1 | F80: Saurabh | G80: Tablet | H80: 15702 | I80: DISC20 | J80: 0.2 | K80: 14000 | L80: 45326 | M80: =IF(H80>=K80,"Target Achieved","Below Target") -> Target Achieved
A81: S1050 | B81: Aarav Nair | C81: C203 | D81: Full Stack Dev | E81: B3 | F81: Amit | G81: Web | H81: 16760 | I81: DISC20 | J81: 0.2 | K81: 17000 | L81: 45294 | M81: =IF(H81>=K81,"Target Achieved","Below Target") -> Below Target
A82: S1051 | B82: Aditya Jain | C82: C201 | D82: Data Analytics | E82: B2 | F82: Saurabh | G82: Tablet | H82: 13022 | I82: DISC10 | J82: 0.1 | K82: 14000 | L82: 45314 | M82: =IF(H82>=K82,"Target Achieved","Below Target") -> Below Target
A83: S1052 | B83: Dev Gupta | C83: C204 | D83: UI UX Design | E83: B3 | F83: Amit | G83: Web | H83: 10791 | I83: DISC20 | J83: 0.2 | K83: 9000 | L83: 45347 | M83: =IF(H83>=K83,"Target Achieved","Below Target") -> Target Achieved
A84: S1053 | B84: Karan Patel | C84: C202 | D84: Data Science | E84: B2 | F84: Saurabh | G84: Web | H84: 14016 | I84: DISC30 | J84: 0.3 | K84: 13000 | L84: 45342 | M84: =IF(H84>=K84,"Target Achieved","Below Target") -> Target Achieved
A85: S1054 | B85: Kunal Verma | C85: C202 | D85: Data Science | E85: B2 | F85: Saurabh | G85: Tablet | H85: 11442 | K85: 13000 | L85: 45347 | M85: =IF(H85>=K85,"Target Achieved","Below Target") -> Below Target
A86: S1055 | B86: Aarav Nair | C86: C204 | D86: UI UX Design | E86: B1 | F86: Saurabh | G86: Mobile | H86: 8432 | I86: DISC30 | J86: 0.3 | K86: 9000 | L86: 45344 | M86: =IF(H86>=K86,"Target Achieved","Below Target") -> Below Target
A87: S1056 | B87: Dev Nair | C87: C202 | D87: Data Science | E87: B1 | F87: Saurabh | G87: Tablet | H87: 11791 | K87: 13000 | L87: 45313 | M87: =IF(H87>=K87,"Target Achieved","Below Target") -> Below Target
A88: S1057 | B88: Aditya Nair | C88: C201 | D88: Data Analytics | E88: B2 | F88: Priya | G88: Tablet | H88: 14086 | K88: 14000 | L88: 45335 | M88: =IF(H88>=K88,"Target Achieved","Below Target") -> Target Achieved
A89: S1058 | B89: Meera Gupta | C89: C203 | D89: Full Stack Dev | E89: B1 | F89: Saurabh | G89: Mobile | H89: 15731 | I89: DISC15 | K89: 17000 | L89: 45308 | M89: =IF(H89>=K89,"Target Achieved","Below Target") -> Below Target
A90: S1059 | B90: Aarav Shah | C90: C204 | D90: UI UX Design | E90: B2 | F90: Amit | G90: Mobile | H90: 8787 | I90: DISC15 | K90: 9000 | L90: 45324 | M90: =IF(H90>=K90,"Target Achieved","Below Target") -> Below Target
A91: S1060 | B91: Riya Verma | C91: C202 | D91: Data Science | E91: B2 | F91: Saurabh | G91: Tablet | H91: 12786 | I91: DISC10 | J91: 0.1 | K91: 13000 | L91: 45325 | M91: =IF(H91>=K91,"Target Achieved","Below Target") -> Below Target
A92: S1061 | B92: Kunal Patel | C92: C202 | D92: Data Science | E92: B2 | F92: Priya | G92: Web | H92: 14886 | I92: DISC30 | J92: 0.3 | K92: 13000 | L92: 45331 | M92: =IF(H92>=K92,"Target Achieved","Below Target") -> Target Achieved
A93: S1062 | B93: Pooja Singh | C93: C201 | D93: Data Analytics | E93: B3 | F93: Priya | G93: Tablet | H93: 13266 | K93: 14000 | L93: 45312 | M93: =IF(H93>=K93,"Target Achieved","Below Target") -> Below Target
A94: S1063 | B94: Rahul Desai | C94: C203 | D94: Full Stack Dev | E94: B3 | F94: Saurabh | G94: Web | H94: 16722 | K94: 17000 | L94: 45335 | M94: =IF(H94>=K94,"Target Achieved","Below Target") -> Below Target
A95: S1064 | B95: Anjali Mehta | C95: C203 | D95: Full Stack Dev | E95: B2 | F95: Amit | G95: Web | H95: 16244 | I95: DISC30 | J95: 0.3 | K95: 17000 | L95: 45305 | M95: =IF(H95>=K95,"Target Achieved","Below Target") -> Below Target
A96: S1065 | B96: Rahul Patel | C96: C203 | D96: Full Stack Dev | E96: B2 | F96: Priya | G96: Mobile | H96: 17767 | I96: DISC20 | J96: 0.2 | K96: 17000 | L96: 45324 | M96: =IF(H96>=K96,"Target Achieved","Below Target") -> Target Achieved
A97: S1066 | B97: Neha Patel | C97: C202 | D97: Data Science | E97: B3 | F97: Saurabh | G97: Mobile | H97: 13111 | I97: DISC15 | K97: 13000 | L97: 45313 | M97: =IF(H97>=K97,"Target Achieved","Below Target") -> Target Achieved
A98: S1067 | B98: Riya Nair | C98: C202 | D98: Data Science | E98: B3 | F98: Priya | G98: Web | H98: 14303 | I98: DISC20 | J98: 0.2 | K98: 13000 | L98: 45301 | M98: =IF(H98>=K98,"Target Achieved","Below Target") -> Target Achieved
A99: S1068 | B99: Aarav Kulkarni | C99: C202 | D99: Data Science | E99: B2 | F99: Amit | G99: Web | H99: 12865 | K99: 13000 | L99: 45348 | M99: =IF(H99>=K99,"Target Achieved","Below Target") -> Below Target
A100: S1069 | B100: Rohit Joshi | C100: C202 | D100: Data Science | E100: B3 | F100: Amit | G100: Mobile | H100: 13024 | K100: 13000 | L100: 45307 | M100: =IF(H100>=K100,"Target Achieved","Below Target") -> Target Achieved
A101: S1070 | B101: Karan Singh | C101: C201 | D101: Data Analytics | E101: B1 | F101: Priya | G101: Web | H101: 12720 | I101: DISC15 | K101: 14000 | L101: 45321 | M101: =IF(H101>=K101,"Target Achieved","Below Target") -> Below Target
A102: S1071 | B102: Aarav Gupta | C102: C202 | D102: Data Science | E102: B1 | F102: Priya | G102: Web | H102: 14282 | K102: 13000 | L102: 45334 | M102: =IF(H102>=K102,"Target Achieved","Below Target") -> Target Achieved
A103: S1072 | B103: Manish Gupta | C103: C203 | D103: Full Stack Dev | E103: B2 | F103: Amit | G103: Tablet | H103: 18653 | I103: DISC15 | K103: 17000 | L103: 45319 | M103: =IF(H103>=K103,"Target Achieved","Below Target") -> Target Achieved
A104: S1073 | B104: Meera Gupta | C104: C204 | D104: UI UX Design | E104: B1 | F104: Amit | G104: Mobile | H104: 8843 | I104: DISC30 | J104: 0.3 | K104: 9000 | L104: 45340 | M104: =IF(H104>=K104,"Target Achieved","Below Target") -> Below Target
A105: S1074 | B105: Sneha Nair | C105: C203 | D105: Full Stack Dev | E105: B3 | F105: Priya | G105: Tablet | H105: 15979 | I105: DISC30 | J105: 0.3 | K105: 17000 | L105: 45320 | M105: =IF(H105>=K105,"Target Achieved","Below Target") -> Below Target
A106: S1075 | B106: Riya Desai | C106: C203 | D106: Full Stack Dev | E106: B1 | F106: Priya | G106: Mobile | H106: 16309 | I106: DISC15 | K106: 17000 | L106: 45297 | M106: =IF(H106>=K106,"Target Achieved","Below Target") -> Below Target
A107: S1076 | B107: Karan Mehta | C107: C202 | D107: Data Science | E107: B2 | F107: Amit | G107: Web | H107: 13893 | I107: DISC20 | J107: 0.2 | K107: 13000 | L107: 45296 | M107: =IF(H107>=K107,"Target Achieved","Below Target") -> Target Achieved
A108: S1077 | B108: Rahul Verma | C108: C203 | D108: Full Stack Dev | E108: B3 | F108: Priya | G108: Mobile | H108: 15255 | I108: DISC20 | J108: 0.2 | K108: 17000 | L108: 45345 | M108: =IF(H108>=K108,"Target Achieved","Below Target") -> Below Target
A109: S1078 | B109: Rahul Verma | C109: C201 | D109: Data Analytics | E109: B3 | F109: Priya | G109: Mobile | H109: 12024 | I109: DISC30 | J109: 0.3 | K109: 14000 | L109: 45311 | M109: =IF(H109>=K109,"Target Achieved","Below Target") -> Below Target
A110: S1079 | B110: Dev Verma | C110: C204 | D110: UI UX Design | E110: B3 | F110: Amit | G110: Tablet | H110: 9236 | I110: DISC15 | K110: 9000 | L110: 45349 | M110: =IF(H110>=K110,"Target Achieved","Below Target") -> Target Achieved
A111: S1080 | B111: Sneha Iyer | C111: C202 | D111: Data Science | E111: B2 | F111: Priya | G111: Mobile | H111: 11118 | K111: 13000 | L111: 45313 | M111: =IF(H111>=K111,"Target Achieved","Below Target") -> Below Target
A112: S1081 | B112: Rohit Singh | C112: C204 | D112: UI UX Design | E112: B3 | F112: Saurabh | G112: Mobile | H112: 10766 | I112: DISC20 | J112: 0.2 | K112: 9000 | L112: 45331 | M112: =IF(H112>=K112,"Target Achieved","Below Target") -> Target Achieved
A113: S1082 | B113: Manish Kulkarni | C113: C204 | D113: UI UX Design | E113: B3 | F113: Amit | G113: Tablet | H113: 7111 | I113: DISC10 | J113: 0.1 | K113: 9000 | L113: 45333 | M113: =IF(H113>=K113,"Target Achieved","Below Target") -> Below Target
A114: S1083 | B114: Rahul Mehta | C114: C204 | D114: UI UX Design | E114: B1 | F114: Saurabh | G114: Mobile | H114: 8552 | I114: DISC30 | J114: 0.3 | K114: 9000 | L114: 45305 | M114: =IF(H114>=K114,"Target Achieved","Below Target") -> Below Target
A115: S1084 | B115: Neha Jain | C115: C203 | D115: Full Stack Dev | E115: B2 | F115: Priya | G115: Mobile | H115: 16033 | I115: DISC10 | J115: 0.1 | K115: 17000 | L115: 45322 | M115: =IF(H115>=K115,"Target Achieved","Below Target") -> Below Target
A116: S1085 | B116: Aarav Desai | C116: C201 | D116: Data Analytics | E116: B2 | F116: Saurabh | G116: Tablet | H116: 12281 | I116: DISC10 | J116: 0.1 | K116: 14000 | L116: 45340 | M116: =IF(H116>=K116,"Target Achieved","Below Target") -> Below Target
A117: S1086 | B117: Aarav Patil | C117: C202 | D117: Data Science | E117: B1 | F117: Amit | G117: Web | H117: 11977 | I117: DISC20 | J117: 0.2 | K117: 13000 | L117: 45322 | M117: =IF(H117>=K117,"Target Achieved","Below Target") -> Below Target
A118: S1087 | B118: Rohit Shah | C118: C202 | D118: Data Science | E118: B2 | F118: Amit | G118: Mobile | H118: 14141 | I118: DISC30 | J118: 0.3 | K118: 13000 | L118: 45302 | M118: =IF(H118>=K118,"Target Achieved","Below Target") -> Target Achieved
A119: S1088 | B119: Kavita Joshi | C119: C201 | D119: Data Analytics | E119: B1 | F119: Priya | G119: Web | H119: 14370 | I119: DISC10 | J119: 0.1 | K119: 14000 | L119: 45351 | M119: =IF(H119>=K119,"Target Achieved","Below Target") -> Target Achieved
A120: S1089 | B120: Aditya Joshi | C120: C204 | D120: UI UX Design | E120: B2 | F120: Amit | G120: Web | H120: 7311 | I120: DISC15 | K120: 9000 | L120: 45336 | M120: =IF(H120>=K120,"Target Achieved","Below Target") -> Below Target
A121: S1090 | B121: Meera Singh | C121: C202 | D121: Data Science | E121: B1 | F121: Amit | G121: Mobile | H121: 14482 | I121: DISC15 | K121: 13000 | L121: 45343 | M121: =IF(H121>=K121,"Target Achieved","Below Target") -> Target Achieved
A122: S1091 | B122: Riya Patel | C122: C201 | D122: Data Analytics | E122: B2 | F122: Amit | G122: Mobile | H122: 14709 | I122: DISC30 | J122: 0.3 | K122: 14000 | L122: 45296 | M122: =IF(H122>=K122,"Target Achieved","Below Target") -> Target Achieved
A123: S1092 | B123: Manish Singh | C123: C203 | D123: Full Stack Dev | E123: B1 | F123: Priya | G123: Mobile | H123: 15432 | K123: 17000 | L123: 45315 | M123: =IF(H123>=K123,"Target Achieved","Below Target") -> Below Target
A124: S1093 | B124: Rohit Nair | C124: C204 | D124: UI UX Design | E124: B3 | F124: Saurabh | G124: Mobile | H124: 7721 | I124: DISC15 | K124: 9000 | L124: 45333 | M124: =IF(H124>=K124,"Target Achieved","Below Target") -> Below Target
A125: S1094 | B125: Aditya Joshi | C125: C204 | D125: UI UX Design | E125: B2 | F125: Priya | G125: Tablet | H125: 9426 | I125: DISC30 | J125: 0.3 | K125: 9000 | L125: 45312 | M125: =IF(H125>=K125,"Target Achieved","Below Target") -> Target Achieved
A126: S1095 | B126: Meera Patil | C126: C201 | D126: Data Analytics | E126: B2 | F126: Priya | G126: Web | H126: 15073 | K126: 14000 | L126: 45328 | M126: =IF(H126>=K126,"Target Achieved","Below Target") -> Target Achieved
A127: S1096 | B127: Kavita Singh | C127: C204 | D127: UI UX Design | E127: B2 | F127: Saurabh | G127: Mobile | H127: 10485 | I127: DISC30 | J127: 0.3 | K127: 9000 | L127: 45303 | M127: =IF(H127>=K127,"Target Achieved","Below Target") -> Target Achieved
A128: S1097 | B128: Neha Patil | C128: C203 | D128: Full Stack Dev | E128: B2 | F128: Priya | G128: Mobile | H128: 18605 | I128: DISC15 | K128: 17000 | L128: 45336 | M128: =IF(H128>=K128,"Target Achieved","Below Target") -> Target Achieved
...

Sheet Q14
A1: 1. Top-Performing Combination Details:
A3: Category: Full Stack
A5: Platform: Tablet
A7: Revenue Generated: ₹17,29,206
A9: 2. Brief Explanation:
A11: High Industry Demand: | D11: Full Stack Development is one of the most sought-after and comprehensive technical courses,
D12: resulting in higher student enrollment and higher course fees compared to other categories.
A15: Optimal Learning Experience: | D15: Tablets offer an ideal balance between mobility and screen size for coding practices
D16: , reviewing assignments, and watching detailed video tutorials, making it the preferred learning platform for tech students.
